{"data":[{"i":1,"n":"","u":"https://i.imgur.com/0AJ0QeY.png","t":"https://i.imgur.com/0AJ0QeYl.jpg","k":"","f":false},{"i":2,"n":"","u":"https://i.imgur.com/0Bjntg6.png","t":"https://i.imgur.com/0Bjntg6l.jpg","k":"","f":false},{"i":3,"n":"","u":"https://i.imgur.com/0hdTPVn.png","t":"https://i.imgur.com/0hdTPVnl.jpg","k":"","f":true},{"i":4,"n":"","u":"https://i.imgur.com/0J9bFyR.png","t":"https://i.imgur.com/0J9bFyRl.jpg","k":"","f":false},{"i":5,"n":"","u":"https://i.imgur.com/0kn3P6x.png","t":"https://i.imgur.com/0kn3P6xl.jpg","k":"","f":false},{"i":6,"n":"","u":"https://i.imgur.com/0PyGRnD.png","t":"https://i.imgur.com/0PyGRnDl.jpg","k":"","f":false},{"i":7,"n":"","u":"https://i.imgur.com/10w1042.png","t":"https://i.imgur.com/10w1042l.jpg","k":"","f":true},{"i":8,"n":"","u":"https://i.imgur.com/158RkGU.png","t":"https://i.imgur.com/158RkGUl.jpg","k":"","f":false},{"i":9,"n":"","u":"https://i.imgur.com/16IEoN7.png","t":"https://i.imgur.com/16IEoN7l.jpg","k":"","f":false},{"i":10,"n":"","u":"https://i.imgur.com/1Gab5Qy.png","t":"https://i.imgur.com/1Gab5Qyl.jpg","k":"","f":false},{"i":11,"n":"","u":"https://i.imgur.com/1J8fPIq.png","t":"https://i.imgur.com/1J8fPIql.jpg","k":"","f":false},{"i":12,"n":"","u":"https://i.imgur.com/1muM5sr.png","t":"https://i.imgur.com/1muM5srl.jpg","k":"","f":false},{"i":13,"n":"","u":"https://i.imgur.com/1njOpEQ.png","t":"https://i.imgur.com/1njOpEQl.jpg","k":"","f":false},{"i":14,"n":"","u":"https://i.imgur.com/1PW8AV8.png","t":"https://i.imgur.com/1PW8AV8l.jpg","k":"","f":false},{"i":15,"n":"","u":"https://i.imgur.com/1q9R0cq.png","t":"https://i.imgur.com/1q9R0cql.jpg","k":"","f":false},{"i":16,"n":"","u":"https://i.imgur.com/23Jl81B.png","t":"https://i.imgur.com/23Jl81Bl.jpg","k":"","f":false},{"i":17,"n":"","u":"https://i.imgur.com/2B9RQ1x.png","t":"https://i.imgur.com/2B9RQ1xl.jpg","k":"","f":false},{"i":18,"n":"","u":"https://i.imgur.com/2FSwkzb.png","t":"https://i.imgur.com/2FSwkzbl.jpg","k":"","f":false},{"i":19,"n":"","u":"https://i.imgur.com/2m3B7ST.png","t":"https://i.imgur.com/2m3B7STl.jpg","k":"","f":false},{"i":20,"n":"","u":"https://i.imgur.com/2S1h3pf.png","t":"https://i.imgur.com/2S1h3pfl.jpg","k":"","f":false},{"i":21,"n":"","u":"https://i.imgur.com/36ohlVa.png","t":"https://i.imgur.com/36ohlVal.jpg","k":"","f":true},{"i":22,"n":"","u":"https://i.imgur.com/38QRdJg.png","t":"https://i.imgur.com/38QRdJgl.jpg","k":"","f":false},{"i":23,"n":"","u":"https://i.imgur.com/3C7Bcbt.png","t":"https://i.imgur.com/3C7Bcbtl.jpg","k":"","f":false},{"i":24,"n":"","u":"https://i.imgur.com/3FXCygD.png","t":"https://i.imgur.com/3FXCygDl.jpg","k":"","f":false},{"i":25,"n":"","u":"https://i.imgur.com/3RJGYyx.png","t":"https://i.imgur.com/3RJGYyxl.jpg","k":"","f":false},{"i":26,"n":"","u":"https://i.imgur.com/3TYZRlE.png","t":"https://i.imgur.com/3TYZRlEl.jpg","k":"","f":false},{"i":27,"n":"","u":"https://i.imgur.com/42vV9xl.png","t":"https://i.imgur.com/42vV9xll.jpg","k":"","f":false},{"i":28,"n":"","u":"https://i.imgur.com/4H55MlO.png","t":"https://i.imgur.com/4H55MlOl.jpg","k":"","f":false},{"i":29,"n":"","u":"https://i.imgur.com/4oxWeqw.png","t":"https://i.imgur.com/4oxWeqwl.jpg","k":"","f":false},{"i":30,"n":"","u":"https://i.imgur.com/4ZKCjUW.png","t":"https://i.imgur.com/4ZKCjUWl.jpg","k":"","f":false},{"i":31,"n":"","u":"https://i.imgur.com/50E0cPw.png","t":"https://i.imgur.com/50E0cPwl.jpg","k":"","f":true},{"i":32,"n":"","u":"https://i.imgur.com/53gZDZK.png","t":"https://i.imgur.com/53gZDZKl.jpg","k":"","f":false},{"i":33,"n":"","u":"https://i.imgur.com/53rSpPZ.png","t":"https://i.imgur.com/53rSpPZl.jpg","k":"","f":false},{"i":34,"n":"","u":"https://i.imgur.com/59Rq1hV.png","t":"https://i.imgur.com/59Rq1hVl.jpg","k":"","f":false},{"i":35,"n":"","u":"https://i.imgur.com/5DnSN2T.png","t":"https://i.imgur.com/5DnSN2Tl.jpg","k":"","f":false},{"i":36,"n":"","u":"https://i.imgur.com/5rWcnNx.png","t":"https://i.imgur.com/5rWcnNxl.jpg","k":"","f":false},{"i":37,"n":"","u":"https://i.imgur.com/5w0qVRi.png","t":"https://i.imgur.com/5w0qVRil.jpg","k":"","f":false},{"i":38,"n":"","u":"https://i.imgur.com/5WAez5a.png","t":"https://i.imgur.com/5WAez5al.jpg","k":"","f":false},{"i":39,"n":"","u":"https://i.imgur.com/5YjcLH8.png","t":"https://i.imgur.com/5YjcLH8l.jpg","k":"","f":true},{"i":40,"n":"","u":"https://i.imgur.com/5yVIh0X.png","t":"https://i.imgur.com/5yVIh0Xl.jpg","k":"","f":false},{"i":41,"n":"","u":"https://i.imgur.com/5ZQZZvl.png","t":"https://i.imgur.com/5ZQZZvll.jpg","k":"","f":true},{"i":42,"n":"","u":"https://i.imgur.com/6cHCTUU.png","t":"https://i.imgur.com/6cHCTUUl.jpg","k":"","f":false},{"i":43,"n":"","u":"https://i.imgur.com/6Daaepc.png","t":"https://i.imgur.com/6Daaepcl.jpg","k":"","f":true},{"i":44,"n":"","u":"https://i.imgur.com/6FNsUET.png","t":"https://i.imgur.com/6FNsUETl.jpg","k":"","f":false},{"i":45,"n":"","u":"https://i.imgur.com/6Gd4eOm.png","t":"https://i.imgur.com/6Gd4eOml.jpg","k":"","f":true},{"i":46,"n":"","u":"https://i.imgur.com/6JRtI1E.png","t":"https://i.imgur.com/6JRtI1El.jpg","k":"","f":true},{"i":47,"n":"","u":"https://i.imgur.com/6Ul3FFn.png","t":"https://i.imgur.com/6Ul3FFnl.jpg","k":"","f":false},{"i":48,"n":"","u":"https://i.imgur.com/6vTEBoE.png","t":"https://i.imgur.com/6vTEBoEl.jpg","k":"","f":false},{"i":49,"n":"","u":"https://i.imgur.com/6ZvhC5e.png","t":"https://i.imgur.com/6ZvhC5el.jpg","k":"","f":false},{"i":50,"n":"","u":"https://i.imgur.com/7AqFwR4.png","t":"https://i.imgur.com/7AqFwR4l.jpg","k":"","f":true},{"i":51,"n":"","u":"https://i.imgur.com/7MBcGZY.png","t":"https://i.imgur.com/7MBcGZYl.jpg","k":"","f":false},{"i":52,"n":"","u":"https://i.imgur.com/7rRxMAb.png","t":"https://i.imgur.com/7rRxMAbl.jpg","k":"","f":false},{"i":53,"n":"","u":"https://i.imgur.com/7vUaJcT.png","t":"https://i.imgur.com/7vUaJcTl.jpg","k":"","f":false},{"i":54,"n":"","u":"https://i.imgur.com/83FVXZS.png","t":"https://i.imgur.com/83FVXZSl.jpg","k":"","f":false},{"i":55,"n":"","u":"https://i.imgur.com/8EBpy79.png","t":"https://i.imgur.com/8EBpy79l.jpg","k":"","f":false},{"i":56,"n":"","u":"https://i.imgur.com/8f186ve.png","t":"https://i.imgur.com/8f186vel.jpg","k":"","f":false},{"i":57,"n":"","u":"https://i.imgur.com/8F91TOQ.png","t":"https://i.imgur.com/8F91TOQl.jpg","k":"","f":false},{"i":58,"n":"","u":"https://i.imgur.com/8GfF5lu.png","t":"https://i.imgur.com/8GfF5lul.jpg","k":"","f":true},{"i":59,"n":"","u":"https://i.imgur.com/8oUuOhS.png","t":"https://i.imgur.com/8oUuOhSl.jpg","k":"","f":false},{"i":60,"n":"","u":"https://i.imgur.com/90jovL7.png","t":"https://i.imgur.com/90jovL7l.jpg","k":"","f":false},{"i":61,"n":"","u":"https://i.imgur.com/9JG038x.png","t":"https://i.imgur.com/9JG038xl.jpg","k":"","f":false},{"i":62,"n":"","u":"https://i.imgur.com/9lRwbpM.png","t":"https://i.imgur.com/9lRwbpMl.jpg","k":"","f":false},{"i":63,"n":"","u":"https://i.imgur.com/9NQ3K5N.png","t":"https://i.imgur.com/9NQ3K5Nl.jpg","k":"","f":false},{"i":64,"n":"","u":"https://i.imgur.com/9PZS1fB.png","t":"https://i.imgur.com/9PZS1fBl.jpg","k":"","f":false},{"i":65,"n":"","u":"https://i.imgur.com/9Vc9fKc.png","t":"https://i.imgur.com/9Vc9fKcl.jpg","k":"","f":false},{"i":66,"n":"","u":"https://i.imgur.com/9yvxKG7.png","t":"https://i.imgur.com/9yvxKG7l.jpg","k":"","f":false},{"i":67,"n":"","u":"https://i.imgur.com/a2TiB5n.png","t":"https://i.imgur.com/a2TiB5nl.jpg","k":"","f":false},{"i":68,"n":"","u":"https://i.imgur.com/A3X15hP.png","t":"https://i.imgur.com/A3X15hPl.jpg","k":"","f":false},{"i":69,"n":"","u":"https://i.imgur.com/A4uOOJy.png","t":"https://i.imgur.com/A4uOOJyl.jpg","k":"","f":false},{"i":70,"n":"","u":"https://i.imgur.com/AaiMGvX.png","t":"https://i.imgur.com/AaiMGvXl.jpg","k":"","f":false},{"i":71,"n":"","u":"https://i.imgur.com/acTr18I.png","t":"https://i.imgur.com/acTr18Il.jpg","k":"","f":false},{"i":72,"n":"","u":"https://i.imgur.com/ACTSEYk.png","t":"https://i.imgur.com/ACTSEYkl.jpg","k":"","f":false},{"i":73,"n":"","u":"https://i.imgur.com/aDHpaji.png","t":"https://i.imgur.com/aDHpajil.jpg","k":"","f":false},{"i":74,"n":"","u":"https://i.imgur.com/afozx0p.png","t":"https://i.imgur.com/afozx0pl.jpg","k":"","f":false},{"i":75,"n":"","u":"https://i.imgur.com/AI48xNN.png","t":"https://i.imgur.com/AI48xNNl.jpg","k":"","f":false},{"i":76,"n":"","u":"https://i.imgur.com/AiOyQIF.png","t":"https://i.imgur.com/AiOyQIFl.jpg","k":"","f":false},{"i":77,"n":"","u":"https://i.imgur.com/aJNb63T.png","t":"https://i.imgur.com/aJNb63Tl.jpg","k":"","f":true},{"i":78,"n":"","u":"https://i.imgur.com/aQ2yblx.png","t":"https://i.imgur.com/aQ2yblxl.jpg","k":"","f":false},{"i":79,"n":"","u":"https://i.imgur.com/arTo2Ix.png","t":"https://i.imgur.com/arTo2Ixl.jpg","k":"","f":false},{"i":80,"n":"","u":"https://i.imgur.com/aTvw3VT.png","t":"https://i.imgur.com/aTvw3VTl.jpg","k":"","f":false},{"i":81,"n":"","u":"https://i.imgur.com/az2PdDX.png","t":"https://i.imgur.com/az2PdDXl.jpg","k":"","f":false},{"i":82,"n":"","u":"https://i.imgur.com/az7HsMj.png","t":"https://i.imgur.com/az7HsMjl.jpg","k":"","f":false},{"i":83,"n":"","u":"https://i.imgur.com/bbnGIsr.png","t":"https://i.imgur.com/bbnGIsrl.jpg","k":"","f":false},{"i":84,"n":"","u":"https://i.imgur.com/BFvAaqv.png","t":"https://i.imgur.com/BFvAaqvl.jpg","k":"","f":false},{"i":85,"n":"","u":"https://i.imgur.com/BGFopNy.png","t":"https://i.imgur.com/BGFopNyl.jpg","k":"","f":false},{"i":86,"n":"","u":"https://i.imgur.com/bhp3vB9.png","t":"https://i.imgur.com/bhp3vB9l.jpg","k":"","f":false},{"i":87,"n":"","u":"https://i.imgur.com/BhpgpUr.png","t":"https://i.imgur.com/BhpgpUrl.jpg","k":"","f":false},{"i":88,"n":"","u":"https://i.imgur.com/bpWNXs0.png","t":"https://i.imgur.com/bpWNXs0l.jpg","k":"","f":false},{"i":89,"n":"","u":"https://i.imgur.com/brzcpWu.png","t":"https://i.imgur.com/brzcpWul.jpg","k":"","f":false},{"i":90,"n":"","u":"https://i.imgur.com/BvnQWVh.png","t":"https://i.imgur.com/BvnQWVhl.jpg","k":"","f":true},{"i":91,"n":"","u":"https://i.imgur.com/bWdGLbU.png","t":"https://i.imgur.com/bWdGLbUl.jpg","k":"","f":false},{"i":92,"n":"","u":"https://i.imgur.com/bYGRUvD.png","t":"https://i.imgur.com/bYGRUvDl.jpg","k":"","f":false},{"i":93,"n":"","u":"https://i.imgur.com/c6Ehtgs.png","t":"https://i.imgur.com/c6Ehtgsl.jpg","k":"","f":false},{"i":94,"n":"","u":"https://i.imgur.com/cAbFQQA.png","t":"https://i.imgur.com/cAbFQQAl.jpg","k":"","f":true},{"i":95,"n":"","u":"https://i.imgur.com/cAMv9T7.png","t":"https://i.imgur.com/cAMv9T7l.jpg","k":"","f":false},{"i":96,"n":"","u":"https://i.imgur.com/cFaoiPG.png","t":"https://i.imgur.com/cFaoiPGl.jpg","k":"","f":false},{"i":97,"n":"","u":"https://i.imgur.com/cNw7QmW.png","t":"https://i.imgur.com/cNw7QmWl.jpg","k":"","f":false},{"i":98,"n":"","u":"https://i.imgur.com/cQfumQw.png","t":"https://i.imgur.com/cQfumQwl.jpg","k":"","f":false},{"i":99,"n":"","u":"https://i.imgur.com/CRoSLZZ.png","t":"https://i.imgur.com/CRoSLZZl.jpg","k":"","f":false},{"i":100,"n":"","u":"https://i.imgur.com/csAsw7b.png","t":"https://i.imgur.com/csAsw7bl.jpg","k":"","f":false},{"i":101,"n":"","u":"https://i.imgur.com/cScgREy.png","t":"https://i.imgur.com/cScgREyl.jpg","k":"","f":false},{"i":102,"n":"","u":"https://i.imgur.com/cSiZxcY.png","t":"https://i.imgur.com/cSiZxcYl.jpg","k":"","f":false},{"i":103,"n":"","u":"https://i.imgur.com/cTJVOEd.png","t":"https://i.imgur.com/cTJVOEdl.jpg","k":"","f":false},{"i":104,"n":"","u":"https://i.imgur.com/Czz7rcZ.png","t":"https://i.imgur.com/Czz7rcZl.jpg","k":"","f":false},{"i":105,"n":"","u":"https://i.imgur.com/D1qoqUX.png","t":"https://i.imgur.com/D1qoqUXl.jpg","k":"","f":false},{"i":106,"n":"","u":"https://i.imgur.com/D1zqNcY.png","t":"https://i.imgur.com/D1zqNcYl.jpg","k":"","f":false},{"i":107,"n":"","u":"https://i.imgur.com/d9pnvZY.png","t":"https://i.imgur.com/d9pnvZYl.jpg","k":"","f":false},{"i":108,"n":"","u":"https://i.imgur.com/D9WnwBz.png","t":"https://i.imgur.com/D9WnwBzl.jpg","k":"","f":false},{"i":109,"n":"","u":"https://i.imgur.com/DAMwJZH.png","t":"https://i.imgur.com/DAMwJZHl.jpg","k":"","f":false},{"i":110,"n":"","u":"https://i.imgur.com/DbjsDxQ.png","t":"https://i.imgur.com/DbjsDxQl.jpg","k":"","f":true},{"i":111,"n":"","u":"https://i.imgur.com/DdG8sWj.png","t":"https://i.imgur.com/DdG8sWjl.jpg","k":"","f":false},{"i":112,"n":"","u":"https://i.imgur.com/DEpCo6W.png","t":"https://i.imgur.com/DEpCo6Wl.jpg","k":"","f":false},{"i":113,"n":"","u":"https://i.imgur.com/DFIc1IA.png","t":"https://i.imgur.com/DFIc1IAl.jpg","k":"","f":false},{"i":114,"n":"","u":"https://i.imgur.com/DgF7Wh9.png","t":"https://i.imgur.com/DgF7Wh9l.jpg","k":"","f":false},{"i":115,"n":"","u":"https://i.imgur.com/DJX8eb2.png","t":"https://i.imgur.com/DJX8eb2l.jpg","k":"","f":true},{"i":116,"n":"","u":"https://i.imgur.com/DLboJfZ.png","t":"https://i.imgur.com/DLboJfZl.jpg","k":"","f":true},{"i":117,"n":"","u":"https://i.imgur.com/DM0VSFo.png","t":"https://i.imgur.com/DM0VSFol.jpg","k":"","f":false},{"i":118,"n":"","u":"https://i.imgur.com/DqMWu7e.png","t":"https://i.imgur.com/DqMWu7el.jpg","k":"","f":false},{"i":119,"n":"","u":"https://i.imgur.com/dxTaICp.png","t":"https://i.imgur.com/dxTaICpl.jpg","k":"","f":false},{"i":120,"n":"","u":"https://i.imgur.com/Dzea0xw.png","t":"https://i.imgur.com/Dzea0xwl.jpg","k":"","f":false},{"i":121,"n":"","u":"https://i.imgur.com/E7mdIbu.png","t":"https://i.imgur.com/E7mdIbul.jpg","k":"","f":true},{"i":122,"n":"","u":"https://i.imgur.com/EA8VPdq.png","t":"https://i.imgur.com/EA8VPdql.jpg","k":"","f":false},{"i":123,"n":"","u":"https://i.imgur.com/Ed1PpWr.png","t":"https://i.imgur.com/Ed1PpWrl.jpg","k":"","f":false},{"i":124,"n":"","u":"https://i.imgur.com/EEnW7vL.png","t":"https://i.imgur.com/EEnW7vLl.jpg","k":"","f":false},{"i":125,"n":"","u":"https://i.imgur.com/EkeK8o4.png","t":"https://i.imgur.com/EkeK8o4l.jpg","k":"","f":false},{"i":126,"n":"","u":"https://i.imgur.com/ElQ7OTR.png","t":"https://i.imgur.com/ElQ7OTRl.jpg","k":"","f":true},{"i":127,"n":"","u":"https://i.imgur.com/eMk5d3Y.png","t":"https://i.imgur.com/eMk5d3Yl.jpg","k":"","f":false},{"i":128,"n":"","u":"https://i.imgur.com/ENst823.png","t":"https://i.imgur.com/ENst823l.jpg","k":"","f":false},{"i":129,"n":"","u":"https://i.imgur.com/eOLPL5Y.png","t":"https://i.imgur.com/eOLPL5Yl.jpg","k":"","f":false},{"i":130,"n":"","u":"https://i.imgur.com/eOWqGuA.png","t":"https://i.imgur.com/eOWqGuAl.jpg","k":"","f":false},{"i":131,"n":"","u":"https://i.imgur.com/ERlVx4N.png","t":"https://i.imgur.com/ERlVx4Nl.jpg","k":"","f":false},{"i":132,"n":"","u":"https://i.imgur.com/Es98Ktd.png","t":"https://i.imgur.com/Es98Ktdl.jpg","k":"","f":true},{"i":133,"n":"","u":"https://i.imgur.com/EvJ5i7b.png","t":"https://i.imgur.com/EvJ5i7bl.jpg","k":"","f":false},{"i":134,"n":"","u":"https://i.imgur.com/EwDQKYf.png","t":"https://i.imgur.com/EwDQKYfl.jpg","k":"","f":true},{"i":135,"n":"","u":"https://i.imgur.com/F0uE0oi.png","t":"https://i.imgur.com/F0uE0oil.jpg","k":"","f":false},{"i":136,"n":"","u":"https://i.imgur.com/F0Y7msp.png","t":"https://i.imgur.com/F0Y7mspl.jpg","k":"","f":false},{"i":137,"n":"","u":"https://i.imgur.com/fADOa3N.png","t":"https://i.imgur.com/fADOa3Nl.jpg","k":"","f":true},{"i":138,"n":"","u":"https://i.imgur.com/FcbMZZJ.png","t":"https://i.imgur.com/FcbMZZJl.jpg","k":"","f":false},{"i":139,"n":"","u":"https://i.imgur.com/FccxScS.png","t":"https://i.imgur.com/FccxScSl.jpg","k":"","f":false},{"i":140,"n":"","u":"https://i.imgur.com/fdFxLQ8.png","t":"https://i.imgur.com/fdFxLQ8l.jpg","k":"","f":false},{"i":141,"n":"","u":"https://i.imgur.com/feF3nFO.png","t":"https://i.imgur.com/feF3nFOl.jpg","k":"","f":false},{"i":142,"n":"","u":"https://i.imgur.com/feWfMOI.png","t":"https://i.imgur.com/feWfMOIl.jpg","k":"","f":false},{"i":143,"n":"","u":"https://i.imgur.com/fJBjviG.png","t":"https://i.imgur.com/fJBjviGl.jpg","k":"","f":false},{"i":144,"n":"","u":"https://i.imgur.com/foZF0YW.png","t":"https://i.imgur.com/foZF0YWl.jpg","k":"","f":false},{"i":145,"n":"","u":"https://i.imgur.com/FQEp2Mp.png","t":"https://i.imgur.com/FQEp2Mpl.jpg","k":"","f":true},{"i":146,"n":"","u":"https://i.imgur.com/FrggZk2.png","t":"https://i.imgur.com/FrggZk2l.jpg","k":"","f":false},{"i":147,"n":"","u":"https://i.imgur.com/fSrMs7C.png","t":"https://i.imgur.com/fSrMs7Cl.jpg","k":"","f":true},{"i":148,"n":"","u":"https://i.imgur.com/FWpVvzJ.png","t":"https://i.imgur.com/FWpVvzJl.jpg","k":"","f":false},{"i":149,"n":"","u":"https://i.imgur.com/Fzizayl.png","t":"https://i.imgur.com/Fzizayll.jpg","k":"","f":false},{"i":150,"n":"","u":"https://i.imgur.com/g44OH1b.png","t":"https://i.imgur.com/g44OH1bl.jpg","k":"","f":false},{"i":151,"n":"","u":"https://i.imgur.com/G8Buy70.png","t":"https://i.imgur.com/G8Buy70l.jpg","k":"","f":false},{"i":152,"n":"","u":"https://i.imgur.com/gCg1rHl.png","t":"https://i.imgur.com/gCg1rHll.jpg","k":"","f":true},{"i":153,"n":"","u":"https://i.imgur.com/GDRinWF.png","t":"https://i.imgur.com/GDRinWFl.jpg","k":"","f":false},{"i":154,"n":"","u":"https://i.imgur.com/Gfrmn53.png","t":"https://i.imgur.com/Gfrmn53l.jpg","k":"","f":false},{"i":155,"n":"","u":"https://i.imgur.com/GJPRGbm.png","t":"https://i.imgur.com/GJPRGbml.jpg","k":"","f":false},{"i":156,"n":"","u":"https://i.imgur.com/Goj4yFw.png","t":"https://i.imgur.com/Goj4yFwl.jpg","k":"","f":false},{"i":157,"n":"","u":"https://i.imgur.com/GR5xUTC.png","t":"https://i.imgur.com/GR5xUTCl.jpg","k":"","f":false},{"i":158,"n":"","u":"https://i.imgur.com/Grxp6Q2.png","t":"https://i.imgur.com/Grxp6Q2l.jpg","k":"","f":false},{"i":159,"n":"","u":"https://i.imgur.com/gwZCI3k.png","t":"https://i.imgur.com/gwZCI3kl.jpg","k":"","f":false},{"i":160,"n":"","u":"https://i.imgur.com/h3XVedx.png","t":"https://i.imgur.com/h3XVedxl.jpg","k":"","f":false},{"i":161,"n":"","u":"https://i.imgur.com/H3Zd17X.png","t":"https://i.imgur.com/H3Zd17Xl.jpg","k":"","f":false},{"i":162,"n":"","u":"https://i.imgur.com/h6IErA8.png","t":"https://i.imgur.com/h6IErA8l.jpg","k":"","f":false},{"i":163,"n":"","u":"https://i.imgur.com/HhLsj3v.png","t":"https://i.imgur.com/HhLsj3vl.jpg","k":"","f":false},{"i":164,"n":"","u":"https://i.imgur.com/HIhXg5Q.png","t":"https://i.imgur.com/HIhXg5Ql.jpg","k":"","f":false},{"i":165,"n":"","u":"https://i.imgur.com/HJeTWVu.png","t":"https://i.imgur.com/HJeTWVul.jpg","k":"","f":false},{"i":166,"n":"","u":"https://i.imgur.com/HMAXyUP.png","t":"https://i.imgur.com/HMAXyUPl.jpg","k":"","f":false},{"i":167,"n":"","u":"https://i.imgur.com/hnE8suL.png","t":"https://i.imgur.com/hnE8suLl.jpg","k":"","f":false},{"i":168,"n":"","u":"https://i.imgur.com/hP7El26.png","t":"https://i.imgur.com/hP7El26l.jpg","k":"","f":false},{"i":169,"n":"","u":"https://i.imgur.com/hTyguQs.png","t":"https://i.imgur.com/hTyguQsl.jpg","k":"","f":false},{"i":170,"n":"","u":"https://i.imgur.com/hvEgZQx.png","t":"https://i.imgur.com/hvEgZQxl.jpg","k":"","f":false},{"i":171,"n":"","u":"https://i.imgur.com/hZ4wkiS.png","t":"https://i.imgur.com/hZ4wkiSl.jpg","k":"","f":false},{"i":172,"n":"","u":"https://i.imgur.com/i260iTc.png","t":"https://i.imgur.com/i260iTcl.jpg","k":"","f":false},{"i":173,"n":"","u":"https://i.imgur.com/I3J5p6k.png","t":"https://i.imgur.com/I3J5p6kl.jpg","k":"","f":false},{"i":174,"n":"","u":"https://i.imgur.com/I3qFLIw.png","t":"https://i.imgur.com/I3qFLIwl.jpg","k":"","f":false},{"i":175,"n":"","u":"https://i.imgur.com/I5r5gZ6.png","t":"https://i.imgur.com/I5r5gZ6l.jpg","k":"","f":false},{"i":176,"n":"","u":"https://i.imgur.com/i9u2nP9.png","t":"https://i.imgur.com/i9u2nP9l.jpg","k":"","f":false},{"i":177,"n":"","u":"https://i.imgur.com/ici2LMY.png","t":"https://i.imgur.com/ici2LMYl.jpg","k":"","f":false},{"i":178,"n":"","u":"https://i.imgur.com/ijiLoKY.png","t":"https://i.imgur.com/ijiLoKYl.jpg","k":"","f":false},{"i":179,"n":"","u":"https://i.imgur.com/InK7JgT.png","t":"https://i.imgur.com/InK7JgTl.jpg","k":"","f":false},{"i":180,"n":"","u":"https://i.imgur.com/isGtMnw.png","t":"https://i.imgur.com/isGtMnwl.jpg","k":"","f":false},{"i":181,"n":"","u":"https://i.imgur.com/iSTpsE2.png","t":"https://i.imgur.com/iSTpsE2l.jpg","k":"","f":false},{"i":182,"n":"","u":"https://i.imgur.com/ItIbX4H.png","t":"https://i.imgur.com/ItIbX4Hl.jpg","k":"","f":false},{"i":183,"n":"","u":"https://i.imgur.com/iW3KI79.png","t":"https://i.imgur.com/iW3KI79l.jpg","k":"","f":false},{"i":184,"n":"","u":"https://i.imgur.com/iYtBjxl.png","t":"https://i.imgur.com/iYtBjxll.jpg","k":"","f":false},{"i":185,"n":"","u":"https://i.imgur.com/IZP5ixY.png","t":"https://i.imgur.com/IZP5ixYl.jpg","k":"","f":false},{"i":186,"n":"","u":"https://i.imgur.com/jcwMjqW.png","t":"https://i.imgur.com/jcwMjqWl.jpg","k":"","f":false},{"i":187,"n":"","u":"https://i.imgur.com/JFpolfq.png","t":"https://i.imgur.com/JFpolfql.jpg","k":"","f":true},{"i":188,"n":"","u":"https://i.imgur.com/JFxG8Gz.png","t":"https://i.imgur.com/JFxG8Gzl.jpg","k":"","f":false},{"i":189,"n":"","u":"https://i.imgur.com/JjJdXWk.png","t":"https://i.imgur.com/JjJdXWkl.jpg","k":"","f":false},{"i":190,"n":"","u":"https://i.imgur.com/jjWWjjj.png","t":"https://i.imgur.com/jjWWjjjl.jpg","k":"","f":false},{"i":191,"n":"","u":"https://i.imgur.com/jKdEIrG.png","t":"https://i.imgur.com/jKdEIrGl.jpg","k":"","f":false},{"i":192,"n":"","u":"https://i.imgur.com/jLPMRkJ.png","t":"https://i.imgur.com/jLPMRkJl.jpg","k":"","f":false},{"i":193,"n":"","u":"https://i.imgur.com/joZ0Mdf.png","t":"https://i.imgur.com/joZ0Mdfl.jpg","k":"","f":false},{"i":194,"n":"","u":"https://i.imgur.com/jP0HaLi.png","t":"https://i.imgur.com/jP0HaLil.jpg","k":"","f":false},{"i":195,"n":"","u":"https://i.imgur.com/JPNwp1I.png","t":"https://i.imgur.com/JPNwp1Il.jpg","k":"","f":false},{"i":196,"n":"","u":"https://i.imgur.com/jqztWvE.png","t":"https://i.imgur.com/jqztWvEl.jpg","k":"","f":false},{"i":197,"n":"","u":"https://i.imgur.com/JTIkKsC.png","t":"https://i.imgur.com/JTIkKsCl.jpg","k":"","f":false},{"i":198,"n":"","u":"https://i.imgur.com/JtnfHi4.png","t":"https://i.imgur.com/JtnfHi4l.jpg","k":"","f":false},{"i":199,"n":"","u":"https://i.imgur.com/jUm6kDY.png","t":"https://i.imgur.com/jUm6kDYl.jpg","k":"","f":false},{"i":200,"n":"","u":"https://i.imgur.com/jwxyzHW.png","t":"https://i.imgur.com/jwxyzHWl.jpg","k":"","f":false},{"i":201,"n":"","u":"https://i.imgur.com/k5ovLAs.png","t":"https://i.imgur.com/k5ovLAsl.jpg","k":"","f":false},{"i":202,"n":"","u":"https://i.imgur.com/K6WlGJy.png","t":"https://i.imgur.com/K6WlGJyl.jpg","k":"","f":true},{"i":203,"n":"","u":"https://i.imgur.com/K99IeNc.png","t":"https://i.imgur.com/K99IeNcl.jpg","k":"","f":false},{"i":204,"n":"","u":"https://i.imgur.com/KapsUFW.png","t":"https://i.imgur.com/KapsUFWl.jpg","k":"","f":false},{"i":205,"n":"","u":"https://i.imgur.com/KB1wWjw.png","t":"https://i.imgur.com/KB1wWjwl.jpg","k":"","f":false},{"i":206,"n":"","u":"https://i.imgur.com/kco74mY.png","t":"https://i.imgur.com/kco74mYl.jpg","k":"","f":false},{"i":207,"n":"","u":"https://i.imgur.com/KF7NePc.png","t":"https://i.imgur.com/KF7NePcl.jpg","k":"","f":true},{"i":208,"n":"","u":"https://i.imgur.com/KFUkBh0.png","t":"https://i.imgur.com/KFUkBh0l.jpg","k":"","f":false},{"i":209,"n":"","u":"https://i.imgur.com/Kj9uPMS.png","t":"https://i.imgur.com/Kj9uPMSl.jpg","k":"","f":false},{"i":210,"n":"","u":"https://i.imgur.com/kLaHbqW.png","t":"https://i.imgur.com/kLaHbqWl.jpg","k":"","f":false},{"i":211,"n":"","u":"https://i.imgur.com/kOjDI7Q.png","t":"https://i.imgur.com/kOjDI7Ql.jpg","k":"","f":false},{"i":212,"n":"","u":"https://i.imgur.com/KOYsezj.png","t":"https://i.imgur.com/KOYsezjl.jpg","k":"","f":false},{"i":213,"n":"","u":"https://i.imgur.com/kpHvH4g.png","t":"https://i.imgur.com/kpHvH4gl.jpg","k":"","f":false},{"i":214,"n":"","u":"https://i.imgur.com/KTcBzCy.png","t":"https://i.imgur.com/KTcBzCyl.jpg","k":"","f":false},{"i":215,"n":"","u":"https://i.imgur.com/KUmmz6E.png","t":"https://i.imgur.com/KUmmz6El.jpg","k":"","f":false},{"i":216,"n":"","u":"https://i.imgur.com/kXlyiKv.png","t":"https://i.imgur.com/kXlyiKvl.jpg","k":"","f":true},{"i":217,"n":"","u":"https://i.imgur.com/kZzx1Pc.png","t":"https://i.imgur.com/kZzx1Pcl.jpg","k":"","f":false},{"i":218,"n":"","u":"https://i.imgur.com/L01oGgY.png","t":"https://i.imgur.com/L01oGgYl.jpg","k":"","f":false},{"i":219,"n":"","u":"https://i.imgur.com/L4ULAFm.png","t":"https://i.imgur.com/L4ULAFml.jpg","k":"","f":true},{"i":220,"n":"","u":"https://i.imgur.com/LCwFfEs.png","t":"https://i.imgur.com/LCwFfEsl.jpg","k":"","f":true},{"i":221,"n":"","u":"https://i.imgur.com/lfQGnAh.png","t":"https://i.imgur.com/lfQGnAhl.jpg","k":"","f":false},{"i":222,"n":"","u":"https://i.imgur.com/LGOQRmH.png","t":"https://i.imgur.com/LGOQRmHl.jpg","k":"","f":false},{"i":223,"n":"","u":"https://i.imgur.com/lH7Au31.png","t":"https://i.imgur.com/lH7Au31l.jpg","k":"","f":false},{"i":224,"n":"","u":"https://i.imgur.com/lhxaXMi.png","t":"https://i.imgur.com/lhxaXMil.jpg","k":"","f":false},{"i":225,"n":"","u":"https://i.imgur.com/lkmIvLz.png","t":"https://i.imgur.com/lkmIvLzl.jpg","k":"","f":false},{"i":226,"n":"","u":"https://i.imgur.com/lKXFQSc.png","t":"https://i.imgur.com/lKXFQScl.jpg","k":"","f":false},{"i":227,"n":"","u":"https://i.imgur.com/ll0hAPI.png","t":"https://i.imgur.com/ll0hAPIl.jpg","k":"","f":false},{"i":228,"n":"","u":"https://i.imgur.com/LlybLhn.png","t":"https://i.imgur.com/LlybLhnl.jpg","k":"","f":false},{"i":229,"n":"","u":"https://i.imgur.com/ln3WrO8.png","t":"https://i.imgur.com/ln3WrO8l.jpg","k":"","f":false},{"i":230,"n":"","u":"https://i.imgur.com/lQ7qBYv.png","t":"https://i.imgur.com/lQ7qBYvl.jpg","k":"","f":false},{"i":231,"n":"","u":"https://i.imgur.com/LQgkCfb.png","t":"https://i.imgur.com/LQgkCfbl.jpg","k":"","f":false},{"i":232,"n":"","u":"https://i.imgur.com/lQqpIZc.png","t":"https://i.imgur.com/lQqpIZcl.jpg","k":"","f":false},{"i":233,"n":"","u":"https://i.imgur.com/lsbI67C.png","t":"https://i.imgur.com/lsbI67Cl.jpg","k":"","f":false},{"i":234,"n":"","u":"https://i.imgur.com/lScSAvM.png","t":"https://i.imgur.com/lScSAvMl.jpg","k":"","f":false},{"i":235,"n":"","u":"https://i.imgur.com/LUuYWOb.png","t":"https://i.imgur.com/LUuYWObl.jpg","k":"","f":false},{"i":236,"n":"","u":"https://i.imgur.com/lwTqQd2.png","t":"https://i.imgur.com/lwTqQd2l.jpg","k":"","f":false},{"i":237,"n":"","u":"https://i.imgur.com/lYSgjxB.png","t":"https://i.imgur.com/lYSgjxBl.jpg","k":"","f":false},{"i":238,"n":"","u":"https://i.imgur.com/mAmyqL6.png","t":"https://i.imgur.com/mAmyqL6l.jpg","k":"","f":true},{"i":239,"n":"","u":"https://i.imgur.com/MC5Ipxi.png","t":"https://i.imgur.com/MC5Ipxil.jpg","k":"","f":false},{"i":240,"n":"","u":"https://i.imgur.com/MeZqAXQ.png","t":"https://i.imgur.com/MeZqAXQl.jpg","k":"","f":false},{"i":241,"n":"","u":"https://i.imgur.com/mfYHkls.png","t":"https://i.imgur.com/mfYHklsl.jpg","k":"","f":false},{"i":242,"n":"","u":"https://i.imgur.com/mqwiduQ.png","t":"https://i.imgur.com/mqwiduQl.jpg","k":"","f":true},{"i":243,"n":"","u":"https://i.imgur.com/MT9cMLc.png","t":"https://i.imgur.com/MT9cMLcl.jpg","k":"","f":false},{"i":244,"n":"","u":"https://i.imgur.com/MTiORZf.png","t":"https://i.imgur.com/MTiORZfl.jpg","k":"","f":false},{"i":245,"n":"","u":"https://i.imgur.com/Mtmbm45.png","t":"https://i.imgur.com/Mtmbm45l.jpg","k":"","f":false},{"i":246,"n":"","u":"https://i.imgur.com/mtuo5Nn.png","t":"https://i.imgur.com/mtuo5Nnl.jpg","k":"","f":false},{"i":247,"n":"","u":"https://i.imgur.com/Mubzeyn.png","t":"https://i.imgur.com/Mubzeynl.jpg","k":"","f":false},{"i":248,"n":"","u":"https://i.imgur.com/mvvPEun.png","t":"https://i.imgur.com/mvvPEunl.jpg","k":"","f":false},{"i":249,"n":"","u":"https://i.imgur.com/mz0zX5D.png","t":"https://i.imgur.com/mz0zX5Dl.jpg","k":"","f":false},{"i":250,"n":"","u":"https://i.imgur.com/MZycHO7.png","t":"https://i.imgur.com/MZycHO7l.jpg","k":"","f":false},{"i":251,"n":"","u":"https://i.imgur.com/N8qztKy.png","t":"https://i.imgur.com/N8qztKyl.jpg","k":"","f":false},{"i":252,"n":"","u":"https://i.imgur.com/naQsy8g.png","t":"https://i.imgur.com/naQsy8gl.jpg","k":"","f":false},{"i":253,"n":"","u":"https://i.imgur.com/nCmabko.png","t":"https://i.imgur.com/nCmabkol.jpg","k":"","f":false},{"i":254,"n":"","u":"https://i.imgur.com/ND8sYQR.png","t":"https://i.imgur.com/ND8sYQRl.jpg","k":"","f":false},{"i":255,"n":"","u":"https://i.imgur.com/nH1ZmeS.png","t":"https://i.imgur.com/nH1ZmeSl.jpg","k":"","f":false},{"i":256,"n":"","u":"https://i.imgur.com/NM2jKgT.png","t":"https://i.imgur.com/NM2jKgTl.jpg","k":"","f":false},{"i":257,"n":"","u":"https://i.imgur.com/nN5V2md.png","t":"https://i.imgur.com/nN5V2mdl.jpg","k":"","f":false},{"i":258,"n":"","u":"https://i.imgur.com/NnDpzFe.png","t":"https://i.imgur.com/NnDpzFel.jpg","k":"","f":false},{"i":259,"n":"","u":"https://i.imgur.com/noWMc5o.png","t":"https://i.imgur.com/noWMc5ol.jpg","k":"","f":false},{"i":260,"n":"","u":"https://i.imgur.com/nPZ7mrn.png","t":"https://i.imgur.com/nPZ7mrnl.jpg","k":"","f":false},{"i":261,"n":"","u":"https://i.imgur.com/NqjQtMW.png","t":"https://i.imgur.com/NqjQtMWl.jpg","k":"","f":false},{"i":262,"n":"","u":"https://i.imgur.com/NsVSLea.png","t":"https://i.imgur.com/NsVSLeal.jpg","k":"","f":false},{"i":263,"n":"","u":"https://i.imgur.com/nuJ89s6.png","t":"https://i.imgur.com/nuJ89s6l.jpg","k":"","f":false},{"i":264,"n":"","u":"https://i.imgur.com/nWIR0Uh.png","t":"https://i.imgur.com/nWIR0Uhl.jpg","k":"","f":true},{"i":265,"n":"","u":"https://i.imgur.com/nyNVhnT.png","t":"https://i.imgur.com/nyNVhnTl.jpg","k":"","f":false},{"i":266,"n":"","u":"https://i.imgur.com/nZbTNG3.png","t":"https://i.imgur.com/nZbTNG3l.jpg","k":"","f":false},{"i":267,"n":"","u":"https://i.imgur.com/nzFDvqw.png","t":"https://i.imgur.com/nzFDvqwl.jpg","k":"","f":false},{"i":268,"n":"","u":"https://i.imgur.com/o4H0OK2.png","t":"https://i.imgur.com/o4H0OK2l.jpg","k":"","f":true},{"i":269,"n":"","u":"https://i.imgur.com/o5uJDWL.png","t":"https://i.imgur.com/o5uJDWLl.jpg","k":"","f":false},{"i":270,"n":"","u":"https://i.imgur.com/O7x3GnE.png","t":"https://i.imgur.com/O7x3GnEl.jpg","k":"","f":false},{"i":271,"n":"","u":"https://i.imgur.com/oA8fLq2.png","t":"https://i.imgur.com/oA8fLq2l.jpg","k":"","f":false},{"i":272,"n":"","u":"https://i.imgur.com/OaM4gk5.png","t":"https://i.imgur.com/OaM4gk5l.jpg","k":"","f":true},{"i":273,"n":"","u":"https://i.imgur.com/OaWFncI.png","t":"https://i.imgur.com/OaWFncIl.jpg","k":"","f":false},{"i":274,"n":"","u":"https://i.imgur.com/Ofmjyii.png","t":"https://i.imgur.com/Ofmjyiil.jpg","k":"","f":false},{"i":275,"n":"","u":"https://i.imgur.com/OJUvz76.png","t":"https://i.imgur.com/OJUvz76l.jpg","k":"","f":false},{"i":276,"n":"","u":"https://i.imgur.com/OJxCj8j.png","t":"https://i.imgur.com/OJxCj8jl.jpg","k":"","f":false},{"i":277,"n":"","u":"https://i.imgur.com/olPDMwt.png","t":"https://i.imgur.com/olPDMwtl.jpg","k":"","f":false},{"i":278,"n":"","u":"https://i.imgur.com/OLWqo9k.png","t":"https://i.imgur.com/OLWqo9kl.jpg","k":"","f":false},{"i":279,"n":"","u":"https://i.imgur.com/Oo7Qbe0.png","t":"https://i.imgur.com/Oo7Qbe0l.jpg","k":"","f":false},{"i":280,"n":"","u":"https://i.imgur.com/OOAybjw.png","t":"https://i.imgur.com/OOAybjwl.jpg","k":"","f":false},{"i":281,"n":"","u":"https://i.imgur.com/op1fEl3.png","t":"https://i.imgur.com/op1fEl3l.jpg","k":"","f":false},{"i":282,"n":"","u":"https://i.imgur.com/Or1frK5.png","t":"https://i.imgur.com/Or1frK5l.jpg","k":"","f":false},{"i":283,"n":"","u":"https://i.imgur.com/oYzApCg.png","t":"https://i.imgur.com/oYzApCgl.jpg","k":"","f":false},{"i":284,"n":"","u":"https://i.imgur.com/p1nsDhj.png","t":"https://i.imgur.com/p1nsDhjl.jpg","k":"","f":false},{"i":285,"n":"","u":"https://i.imgur.com/P4SF6c4.png","t":"https://i.imgur.com/P4SF6c4l.jpg","k":"","f":false},{"i":286,"n":"","u":"https://i.imgur.com/p89S75D.png","t":"https://i.imgur.com/p89S75Dl.jpg","k":"","f":false},{"i":287,"n":"","u":"https://i.imgur.com/paDvNVS.png","t":"https://i.imgur.com/paDvNVSl.jpg","k":"","f":false},{"i":288,"n":"","u":"https://i.imgur.com/PD9lNCZ.png","t":"https://i.imgur.com/PD9lNCZl.jpg","k":"","f":false},{"i":289,"n":"","u":"https://i.imgur.com/PDnx9b0.png","t":"https://i.imgur.com/PDnx9b0l.jpg","k":"","f":false},{"i":290,"n":"","u":"https://i.imgur.com/PdqUV76.png","t":"https://i.imgur.com/PdqUV76l.jpg","k":"","f":false},{"i":291,"n":"","u":"https://i.imgur.com/PHyf4TM.png","t":"https://i.imgur.com/PHyf4TMl.jpg","k":"","f":false},{"i":292,"n":"","u":"https://i.imgur.com/pkRKfnT.png","t":"https://i.imgur.com/pkRKfnTl.jpg","k":"","f":false},{"i":293,"n":"","u":"https://i.imgur.com/pKXy1Em.png","t":"https://i.imgur.com/pKXy1Eml.jpg","k":"","f":false},{"i":294,"n":"","u":"https://i.imgur.com/pmVhQ5F.png","t":"https://i.imgur.com/pmVhQ5Fl.jpg","k":"","f":true},{"i":295,"n":"","u":"https://i.imgur.com/pn9lLhk.png","t":"https://i.imgur.com/pn9lLhkl.jpg","k":"","f":false},{"i":296,"n":"","u":"https://i.imgur.com/PqWz0h6.png","t":"https://i.imgur.com/PqWz0h6l.jpg","k":"","f":false},{"i":297,"n":"","u":"https://i.imgur.com/pRkXTFJ.png","t":"https://i.imgur.com/pRkXTFJl.jpg","k":"","f":true},{"i":298,"n":"","u":"https://i.imgur.com/pspt9iw.png","t":"https://i.imgur.com/pspt9iwl.jpg","k":"","f":false},{"i":299,"n":"","u":"https://i.imgur.com/PV3ujF0.png","t":"https://i.imgur.com/PV3ujF0l.jpg","k":"","f":false},{"i":300,"n":"","u":"https://i.imgur.com/PVjsHd1.png","t":"https://i.imgur.com/PVjsHd1l.jpg","k":"","f":false},{"i":301,"n":"","u":"https://i.imgur.com/PvMWoyE.png","t":"https://i.imgur.com/PvMWoyEl.jpg","k":"","f":true},{"i":302,"n":"","u":"https://i.imgur.com/q4jRT9c.png","t":"https://i.imgur.com/q4jRT9cl.jpg","k":"","f":false},{"i":303,"n":"","u":"https://i.imgur.com/Q8PetAS.png","t":"https://i.imgur.com/Q8PetASl.jpg","k":"","f":false},{"i":304,"n":"","u":"https://i.imgur.com/q9VrR7b.png","t":"https://i.imgur.com/q9VrR7bl.jpg","k":"","f":false},{"i":305,"n":"","u":"https://i.imgur.com/qMnscLJ.png","t":"https://i.imgur.com/qMnscLJl.jpg","k":"","f":false},{"i":306,"n":"","u":"https://i.imgur.com/QQb7V0w.png","t":"https://i.imgur.com/QQb7V0wl.jpg","k":"","f":false},{"i":307,"n":"","u":"https://i.imgur.com/qr35k1y.png","t":"https://i.imgur.com/qr35k1yl.jpg","k":"","f":true},{"i":308,"n":"","u":"https://i.imgur.com/QTvL1OY.png","t":"https://i.imgur.com/QTvL1OYl.jpg","k":"","f":false},{"i":309,"n":"","u":"https://i.imgur.com/QUDkCmp.png","t":"https://i.imgur.com/QUDkCmpl.jpg","k":"","f":false},{"i":310,"n":"","u":"https://i.imgur.com/QZGTEf2.png","t":"https://i.imgur.com/QZGTEf2l.jpg","k":"","f":false},{"i":311,"n":"","u":"https://i.imgur.com/r3RC4ss.png","t":"https://i.imgur.com/r3RC4ssl.jpg","k":"","f":false},{"i":312,"n":"","u":"https://i.imgur.com/R5CFaqM.png","t":"https://i.imgur.com/R5CFaqMl.jpg","k":"","f":false},{"i":313,"n":"","u":"https://i.imgur.com/r6D6LBv.png","t":"https://i.imgur.com/r6D6LBvl.jpg","k":"","f":false},{"i":314,"n":"","u":"https://i.imgur.com/RfubQna.png","t":"https://i.imgur.com/RfubQnal.jpg","k":"","f":false},{"i":315,"n":"","u":"https://i.imgur.com/rKuvnzl.png","t":"https://i.imgur.com/rKuvnzll.jpg","k":"","f":false},{"i":316,"n":"","u":"https://i.imgur.com/rRLlKIV.png","t":"https://i.imgur.com/rRLlKIVl.jpg","k":"","f":false},{"i":317,"n":"","u":"https://i.imgur.com/RtJJ8ul.png","t":"https://i.imgur.com/RtJJ8ull.jpg","k":"","f":false},{"i":318,"n":"","u":"https://i.imgur.com/Rzf5IzW.png","t":"https://i.imgur.com/Rzf5IzWl.jpg","k":"","f":false},{"i":319,"n":"","u":"https://i.imgur.com/s7gFAmW.png","t":"https://i.imgur.com/s7gFAmWl.jpg","k":"","f":false},{"i":320,"n":"","u":"https://i.imgur.com/S7Ietxg.png","t":"https://i.imgur.com/S7Ietxgl.jpg","k":"","f":false},{"i":321,"n":"","u":"https://i.imgur.com/S8TbZg1.png","t":"https://i.imgur.com/S8TbZg1l.jpg","k":"","f":false},{"i":322,"n":"","u":"https://i.imgur.com/s95uS7d.png","t":"https://i.imgur.com/s95uS7dl.jpg","k":"","f":false},{"i":323,"n":"","u":"https://i.imgur.com/sC8ifC4.png","t":"https://i.imgur.com/sC8ifC4l.jpg","k":"","f":false},{"i":324,"n":"","u":"https://i.imgur.com/SCg3aTh.png","t":"https://i.imgur.com/SCg3aThl.jpg","k":"","f":true},{"i":325,"n":"","u":"https://i.imgur.com/SFJjdap.png","t":"https://i.imgur.com/SFJjdapl.jpg","k":"","f":false},{"i":326,"n":"","u":"https://i.imgur.com/sgU3ZfH.png","t":"https://i.imgur.com/sgU3ZfHl.jpg","k":"","f":false},{"i":327,"n":"","u":"https://i.imgur.com/sja2pGc.png","t":"https://i.imgur.com/sja2pGcl.jpg","k":"","f":false},{"i":328,"n":"","u":"https://i.imgur.com/Sk2REs8.png","t":"https://i.imgur.com/Sk2REs8l.jpg","k":"","f":false},{"i":329,"n":"","u":"https://i.imgur.com/SkEfGlK.png","t":"https://i.imgur.com/SkEfGlKl.jpg","k":"","f":false},{"i":330,"n":"","u":"https://i.imgur.com/skpoVoa.png","t":"https://i.imgur.com/skpoVoal.jpg","k":"","f":false},{"i":331,"n":"","u":"https://i.imgur.com/SlfI7Dh.png","t":"https://i.imgur.com/SlfI7Dhl.jpg","k":"","f":true},{"i":332,"n":"","u":"https://i.imgur.com/snKrjIs.png","t":"https://i.imgur.com/snKrjIsl.jpg","k":"","f":false},{"i":333,"n":"","u":"https://i.imgur.com/soQCDo3.png","t":"https://i.imgur.com/soQCDo3l.jpg","k":"","f":false},{"i":334,"n":"","u":"https://i.imgur.com/sQhbT4R.png","t":"https://i.imgur.com/sQhbT4Rl.jpg","k":"","f":false},{"i":335,"n":"","u":"https://i.imgur.com/SShe9TN.png","t":"https://i.imgur.com/SShe9TNl.jpg","k":"","f":false},{"i":336,"n":"","u":"https://i.imgur.com/Sx0MJHD.png","t":"https://i.imgur.com/Sx0MJHDl.jpg","k":"","f":false},{"i":337,"n":"","u":"https://i.imgur.com/Sxjfjhc.png","t":"https://i.imgur.com/Sxjfjhcl.jpg","k":"","f":false},{"i":338,"n":"","u":"https://i.imgur.com/T0RmfJW.png","t":"https://i.imgur.com/T0RmfJWl.jpg","k":"","f":false},{"i":339,"n":"","u":"https://i.imgur.com/T254nX9.png","t":"https://i.imgur.com/T254nX9l.jpg","k":"","f":false},{"i":340,"n":"","u":"https://i.imgur.com/t5eVQwJ.png","t":"https://i.imgur.com/t5eVQwJl.jpg","k":"","f":false},{"i":341,"n":"","u":"https://i.imgur.com/T640mxv.png","t":"https://i.imgur.com/T640mxvl.jpg","k":"","f":false},{"i":342,"n":"","u":"https://i.imgur.com/T7rVH31.png","t":"https://i.imgur.com/T7rVH31l.jpg","k":"","f":false},{"i":343,"n":"","u":"https://i.imgur.com/t7y91oQ.png","t":"https://i.imgur.com/t7y91oQl.jpg","k":"","f":false},{"i":344,"n":"","u":"https://i.imgur.com/t9V7y3r.png","t":"https://i.imgur.com/t9V7y3rl.jpg","k":"","f":false},{"i":345,"n":"","u":"https://i.imgur.com/tCH0eO9.png","t":"https://i.imgur.com/tCH0eO9l.jpg","k":"","f":true},{"i":346,"n":"","u":"https://i.imgur.com/tgdZJ8s.png","t":"https://i.imgur.com/tgdZJ8sl.jpg","k":"","f":false},{"i":347,"n":"","u":"https://i.imgur.com/tLTJKSV.png","t":"https://i.imgur.com/tLTJKSVl.jpg","k":"","f":false},{"i":348,"n":"","u":"https://i.imgur.com/tMadmGT.png","t":"https://i.imgur.com/tMadmGTl.jpg","k":"","f":false},{"i":349,"n":"","u":"https://i.imgur.com/TuXB9Bv.png","t":"https://i.imgur.com/TuXB9Bvl.jpg","k":"","f":true},{"i":350,"n":"","u":"https://i.imgur.com/Tv2smBa.png","t":"https://i.imgur.com/Tv2smBal.jpg","k":"","f":false},{"i":351,"n":"","u":"https://i.imgur.com/U5rpRne.png","t":"https://i.imgur.com/U5rpRnel.jpg","k":"","f":false},{"i":352,"n":"","u":"https://i.imgur.com/Ua0F1EH.png","t":"https://i.imgur.com/Ua0F1EHl.jpg","k":"","f":false},{"i":353,"n":"","u":"https://i.imgur.com/ua3XSVc.png","t":"https://i.imgur.com/ua3XSVcl.jpg","k":"","f":false},{"i":354,"n":"","u":"https://i.imgur.com/Uay107D.png","t":"https://i.imgur.com/Uay107Dl.jpg","k":"","f":false},{"i":355,"n":"","u":"https://i.imgur.com/ufgR0Sy.png","t":"https://i.imgur.com/ufgR0Syl.jpg","k":"","f":false},{"i":356,"n":"","u":"https://i.imgur.com/UidmMoz.png","t":"https://i.imgur.com/UidmMozl.jpg","k":"","f":false},{"i":357,"n":"","u":"https://i.imgur.com/UQ7vbwY.png","t":"https://i.imgur.com/UQ7vbwYl.jpg","k":"","f":false},{"i":358,"n":"","u":"https://i.imgur.com/UQVf6xe.png","t":"https://i.imgur.com/UQVf6xel.jpg","k":"","f":true},{"i":359,"n":"","u":"https://i.imgur.com/utgHZ94.png","t":"https://i.imgur.com/utgHZ94l.jpg","k":"","f":false},{"i":360,"n":"","u":"https://i.imgur.com/uTmzJZz.png","t":"https://i.imgur.com/uTmzJZzl.jpg","k":"","f":false},{"i":361,"n":"","u":"https://i.imgur.com/UTwOEmV.png","t":"https://i.imgur.com/UTwOEmVl.jpg","k":"","f":false},{"i":362,"n":"","u":"https://i.imgur.com/uVh3ODo.png","t":"https://i.imgur.com/uVh3ODol.jpg","k":"","f":false},{"i":363,"n":"","u":"https://i.imgur.com/uwqbt5Y.png","t":"https://i.imgur.com/uwqbt5Yl.jpg","k":"","f":false},{"i":364,"n":"","u":"https://i.imgur.com/UxC3PVU.png","t":"https://i.imgur.com/UxC3PVUl.jpg","k":"","f":false},{"i":365,"n":"","u":"https://i.imgur.com/v5F7MDW.png","t":"https://i.imgur.com/v5F7MDWl.jpg","k":"","f":false},{"i":366,"n":"","u":"https://i.imgur.com/VBW3rZ6.png","t":"https://i.imgur.com/VBW3rZ6l.jpg","k":"","f":false},{"i":367,"n":"","u":"https://i.imgur.com/vGlN1F1.png","t":"https://i.imgur.com/vGlN1F1l.jpg","k":"","f":false},{"i":368,"n":"","u":"https://i.imgur.com/VGzSk7s.png","t":"https://i.imgur.com/VGzSk7sl.jpg","k":"","f":false},{"i":369,"n":"","u":"https://i.imgur.com/VKj35fh.png","t":"https://i.imgur.com/VKj35fhl.jpg","k":"","f":true},{"i":370,"n":"","u":"https://i.imgur.com/vl2ogWZ.png","t":"https://i.imgur.com/vl2ogWZl.jpg","k":"","f":false},{"i":371,"n":"","u":"https://i.imgur.com/vNMNWAz.png","t":"https://i.imgur.com/vNMNWAzl.jpg","k":"","f":false},{"i":372,"n":"","u":"https://i.imgur.com/Vnqsjfj.png","t":"https://i.imgur.com/Vnqsjfjl.jpg","k":"","f":false},{"i":373,"n":"","u":"https://i.imgur.com/VoatzHC.png","t":"https://i.imgur.com/VoatzHCl.jpg","k":"","f":false},{"i":374,"n":"","u":"https://i.imgur.com/vpNVDlv.png","t":"https://i.imgur.com/vpNVDlvl.jpg","k":"","f":false},{"i":375,"n":"","u":"https://i.imgur.com/VqSW0J2.png","t":"https://i.imgur.com/VqSW0J2l.jpg","k":"","f":false},{"i":376,"n":"","u":"https://i.imgur.com/vR3eBMa.png","t":"https://i.imgur.com/vR3eBMal.jpg","k":"","f":false},{"i":377,"n":"","u":"https://i.imgur.com/vV1vbMa.png","t":"https://i.imgur.com/vV1vbMal.jpg","k":"","f":true},{"i":378,"n":"","u":"https://i.imgur.com/vXC5OEV.png","t":"https://i.imgur.com/vXC5OEVl.jpg","k":"","f":false},{"i":379,"n":"","u":"https://i.imgur.com/vy98FLS.png","t":"https://i.imgur.com/vy98FLSl.jpg","k":"","f":false},{"i":380,"n":"","u":"https://i.imgur.com/vyR4usd.png","t":"https://i.imgur.com/vyR4usdl.jpg","k":"","f":false},{"i":381,"n":"","u":"https://i.imgur.com/W1qUJRF.png","t":"https://i.imgur.com/W1qUJRFl.jpg","k":"","f":false},{"i":382,"n":"","u":"https://i.imgur.com/w4xUXpO.png","t":"https://i.imgur.com/w4xUXpOl.jpg","k":"","f":false},{"i":383,"n":"","u":"https://i.imgur.com/W8vxr4s.png","t":"https://i.imgur.com/W8vxr4sl.jpg","k":"","f":false},{"i":384,"n":"","u":"https://i.imgur.com/wajUpir.png","t":"https://i.imgur.com/wajUpirl.jpg","k":"","f":false},{"i":385,"n":"","u":"https://i.imgur.com/WDlZOUn.png","t":"https://i.imgur.com/WDlZOUnl.jpg","k":"","f":false},{"i":386,"n":"","u":"https://i.imgur.com/WIWfPfE.png","t":"https://i.imgur.com/WIWfPfEl.jpg","k":"","f":false},{"i":387,"n":"","u":"https://i.imgur.com/wJdt5Fr.png","t":"https://i.imgur.com/wJdt5Frl.jpg","k":"","f":false},{"i":388,"n":"","u":"https://i.imgur.com/wOdeVUN.png","t":"https://i.imgur.com/wOdeVUNl.jpg","k":"","f":false},{"i":389,"n":"","u":"https://i.imgur.com/WQcXFBA.png","t":"https://i.imgur.com/WQcXFBAl.jpg","k":"","f":false},{"i":390,"n":"","u":"https://i.imgur.com/WXwThvZ.png","t":"https://i.imgur.com/WXwThvZl.jpg","k":"","f":false},{"i":391,"n":"","u":"https://i.imgur.com/wZMulhJ.png","t":"https://i.imgur.com/wZMulhJl.jpg","k":"","f":false},{"i":392,"n":"","u":"https://i.imgur.com/x6RgaXJ.png","t":"https://i.imgur.com/x6RgaXJl.jpg","k":"","f":false},{"i":393,"n":"","u":"https://i.imgur.com/XA3tSKX.png","t":"https://i.imgur.com/XA3tSKXl.jpg","k":"","f":false},{"i":394,"n":"","u":"https://i.imgur.com/xCmcJCj.png","t":"https://i.imgur.com/xCmcJCjl.jpg","k":"","f":false},{"i":395,"n":"","u":"https://i.imgur.com/xDS9mar.png","t":"https://i.imgur.com/xDS9marl.jpg","k":"","f":false},{"i":396,"n":"","u":"https://i.imgur.com/XEmUDFl.png","t":"https://i.imgur.com/XEmUDFll.jpg","k":"","f":false},{"i":397,"n":"","u":"https://i.imgur.com/xHcPgRq.png","t":"https://i.imgur.com/xHcPgRql.jpg","k":"","f":false},{"i":398,"n":"","u":"https://i.imgur.com/XizzO6D.png","t":"https://i.imgur.com/XizzO6Dl.jpg","k":"","f":true},{"i":399,"n":"","u":"https://i.imgur.com/xKQm4Mk.png","t":"https://i.imgur.com/xKQm4Mkl.jpg","k":"","f":false},{"i":400,"n":"","u":"https://i.imgur.com/xNlCa6a.png","t":"https://i.imgur.com/xNlCa6al.jpg","k":"","f":false},{"i":401,"n":"","u":"https://i.imgur.com/XQG18Ut.png","t":"https://i.imgur.com/XQG18Utl.jpg","k":"","f":false},{"i":402,"n":"","u":"https://i.imgur.com/xqthg0Z.png","t":"https://i.imgur.com/xqthg0Zl.jpg","k":"","f":false},{"i":403,"n":"","u":"https://i.imgur.com/xRilwWz.png","t":"https://i.imgur.com/xRilwWzl.jpg","k":"","f":false},{"i":404,"n":"","u":"https://i.imgur.com/y0gpCRS.png","t":"https://i.imgur.com/y0gpCRSl.jpg","k":"","f":true},{"i":405,"n":"","u":"https://i.imgur.com/y3gAYld.png","t":"https://i.imgur.com/y3gAYldl.jpg","k":"","f":false},{"i":406,"n":"","u":"https://i.imgur.com/y51tLBk.png","t":"https://i.imgur.com/y51tLBkl.jpg","k":"","f":false},{"i":407,"n":"","u":"https://i.imgur.com/y7Fyz2x.png","t":"https://i.imgur.com/y7Fyz2xl.jpg","k":"","f":false},{"i":408,"n":"","u":"https://i.imgur.com/Y85I1is.png","t":"https://i.imgur.com/Y85I1isl.jpg","k":"","f":false},{"i":409,"n":"","u":"https://i.imgur.com/Y8rape7.png","t":"https://i.imgur.com/Y8rape7l.jpg","k":"","f":false},{"i":410,"n":"","u":"https://i.imgur.com/yEQt776.png","t":"https://i.imgur.com/yEQt776l.jpg","k":"","f":false},{"i":411,"n":"","u":"https://i.imgur.com/ygCvrX1.png","t":"https://i.imgur.com/ygCvrX1l.jpg","k":"","f":false},{"i":412,"n":"","u":"https://i.imgur.com/yGE4XSq.png","t":"https://i.imgur.com/yGE4XSql.jpg","k":"","f":true},{"i":413,"n":"","u":"https://i.imgur.com/YjXr4qc.png","t":"https://i.imgur.com/YjXr4qcl.jpg","k":"","f":false},{"i":414,"n":"","u":"https://i.imgur.com/YKdqAOg.png","t":"https://i.imgur.com/YKdqAOgl.jpg","k":"","f":false},{"i":415,"n":"","u":"https://i.imgur.com/yLbboAS.png","t":"https://i.imgur.com/yLbboASl.jpg","k":"","f":false},{"i":416,"n":"","u":"https://i.imgur.com/yM1FfFA.png","t":"https://i.imgur.com/yM1FfFAl.jpg","k":"","f":true},{"i":417,"n":"","u":"https://i.imgur.com/yNh1rTE.png","t":"https://i.imgur.com/yNh1rTEl.jpg","k":"","f":false},{"i":418,"n":"","u":"https://i.imgur.com/YpHpaEc.png","t":"https://i.imgur.com/YpHpaEcl.jpg","k":"","f":false},{"i":419,"n":"","u":"https://i.imgur.com/yprBxOQ.png","t":"https://i.imgur.com/yprBxOQl.jpg","k":"","f":false},{"i":420,"n":"","u":"https://i.imgur.com/yqByvAd.png","t":"https://i.imgur.com/yqByvAdl.jpg","k":"","f":false},{"i":421,"n":"","u":"https://i.imgur.com/yuBc8i0.png","t":"https://i.imgur.com/yuBc8i0l.jpg","k":"","f":false},{"i":422,"n":"","u":"https://i.imgur.com/YzXpYYJ.png","t":"https://i.imgur.com/YzXpYYJl.jpg","k":"","f":false},{"i":423,"n":"","u":"https://i.imgur.com/z23Nkkk.png","t":"https://i.imgur.com/z23Nkkkl.jpg","k":"","f":true},{"i":424,"n":"","u":"https://i.imgur.com/z2LfEnk.png","t":"https://i.imgur.com/z2LfEnkl.jpg","k":"","f":false},{"i":425,"n":"","u":"https://i.imgur.com/z3Kxb8Q.png","t":"https://i.imgur.com/z3Kxb8Ql.jpg","k":"","f":false},{"i":426,"n":"","u":"https://i.imgur.com/z4Np7db.png","t":"https://i.imgur.com/z4Np7dbl.jpg","k":"","f":false},{"i":427,"n":"","u":"https://i.imgur.com/z9rleWM.png","t":"https://i.imgur.com/z9rleWMl.jpg","k":"","f":false},{"i":428,"n":"","u":"https://i.imgur.com/zbCEQOs.png","t":"https://i.imgur.com/zbCEQOsl.jpg","k":"","f":false},{"i":429,"n":"","u":"https://i.imgur.com/ZcEIRAm.png","t":"https://i.imgur.com/ZcEIRAml.jpg","k":"","f":true},{"i":430,"n":"","u":"https://i.imgur.com/zdkMBR0.png","t":"https://i.imgur.com/zdkMBR0l.jpg","k":"","f":false},{"i":431,"n":"","u":"https://i.imgur.com/ziSUEq1.png","t":"https://i.imgur.com/ziSUEq1l.jpg","k":"","f":false},{"i":432,"n":"","u":"https://i.imgur.com/ZLVtg55.png","t":"https://i.imgur.com/ZLVtg55l.jpg","k":"","f":false},{"i":433,"n":"","u":"https://i.imgur.com/zmuOG2t.png","t":"https://i.imgur.com/zmuOG2tl.jpg","k":"","f":false},{"i":434,"n":"","u":"https://i.imgur.com/znchPL0.png","t":"https://i.imgur.com/znchPL0l.jpg","k":"","f":true},{"i":435,"n":"","u":"https://i.imgur.com/ZQ2wIu4.png","t":"https://i.imgur.com/ZQ2wIu4l.jpg","k":"","f":false},{"i":436,"n":"","u":"https://i.imgur.com/ZwEdA6E.png","t":"https://i.imgur.com/ZwEdA6El.jpg","k":"","f":false},{"i":437,"n":"","u":"https://i.imgur.com/ZXb8ZxX.png","t":"https://i.imgur.com/ZXb8ZxXl.jpg","k":"","f":false},{"i":438,"n":"","u":"https://i.imgur.com/zY5KNl2.png","t":"https://i.imgur.com/zY5KNl2l.jpg","k":"","f":false}]}