{"data":[{"i":1,"n":"","u":"https://i.imgur.com/0aEQHXX.jpg","t":"https://i.imgur.com/0aEQHXXl.jpg","k":"","f":false},{"i":2,"n":"","u":"https://i.imgur.com/0cWidQi.jpg","t":"https://i.imgur.com/0cWidQil.jpg","k":"","f":false},{"i":3,"n":"","u":"https://i.imgur.com/0RopxRE.jpg","t":"https://i.imgur.com/0RopxREl.jpg","k":"","f":false},{"i":4,"n":"","u":"https://i.imgur.com/0SXW7Cd.jpg","t":"https://i.imgur.com/0SXW7Cdl.jpg","k":"","f":false},{"i":5,"n":"","u":"https://i.imgur.com/0TFmsmU.jpg","t":"https://i.imgur.com/0TFmsmUl.jpg","k":"","f":false},{"i":6,"n":"","u":"https://i.imgur.com/0xKHWxF.png","t":"https://i.imgur.com/0xKHWxFl.jpg","k":"","f":true},{"i":7,"n":"","u":"https://i.imgur.com/11teaZA.jpg","t":"https://i.imgur.com/11teaZAl.jpg","k":"","f":false},{"i":8,"n":"","u":"https://i.imgur.com/15Gci6a.jpg","t":"https://i.imgur.com/15Gci6al.jpg","k":"","f":false},{"i":9,"n":"","u":"https://i.imgur.com/16ZB0yn.jpg","t":"https://i.imgur.com/16ZB0ynl.jpg","k":"","f":false},{"i":10,"n":"","u":"https://i.imgur.com/176pSWP.png","t":"https://i.imgur.com/176pSWPl.jpg","k":"","f":false},{"i":11,"n":"","u":"https://i.imgur.com/18iJRLd.png","t":"https://i.imgur.com/18iJRLdl.jpg","k":"","f":false},{"i":12,"n":"","u":"https://i.imgur.com/1AGVrIX.jpg","t":"https://i.imgur.com/1AGVrIXl.jpg","k":"","f":false},{"i":13,"n":"","u":"https://i.imgur.com/1an1EDW.jpg","t":"https://i.imgur.com/1an1EDWl.jpg","k":"","f":true},{"i":14,"n":"","u":"https://i.imgur.com/1GRf7iX.jpg","t":"https://i.imgur.com/1GRf7iXl.jpg","k":"","f":false},{"i":15,"n":"","u":"https://i.imgur.com/1h9Pvnt.jpg","t":"https://i.imgur.com/1h9Pvntl.jpg","k":"","f":false},{"i":16,"n":"","u":"https://i.imgur.com/1IPud8u.jpg","t":"https://i.imgur.com/1IPud8ul.jpg","k":"","f":false},{"i":17,"n":"","u":"https://i.imgur.com/1lzTfrB.jpg","t":"https://i.imgur.com/1lzTfrBl.jpg","k":"","f":true},{"i":18,"n":"","u":"https://i.imgur.com/1PclcFa.jpg","t":"https://i.imgur.com/1PclcFal.jpg","k":"","f":false},{"i":19,"n":"","u":"https://i.imgur.com/1qJV1qU.jpg","t":"https://i.imgur.com/1qJV1qUl.jpg","k":"","f":true},{"i":20,"n":"","u":"https://i.imgur.com/1QPiHYm.jpg","t":"https://i.imgur.com/1QPiHYml.jpg","k":"","f":true},{"i":21,"n":"","u":"https://i.imgur.com/1QZcDIe.jpg","t":"https://i.imgur.com/1QZcDIel.jpg","k":"","f":false},{"i":22,"n":"","u":"https://i.imgur.com/1X6YGq5.jpg","t":"https://i.imgur.com/1X6YGq5l.jpg","k":"","f":false},{"i":23,"n":"","u":"https://i.imgur.com/1xeOreQ.jpg","t":"https://i.imgur.com/1xeOreQl.jpg","k":"","f":false},{"i":24,"n":"","u":"https://i.imgur.com/1zHiPAe.jpg","t":"https://i.imgur.com/1zHiPAel.jpg","k":"","f":false},{"i":25,"n":"","u":"https://i.imgur.com/28Lk9Bk.jpg","t":"https://i.imgur.com/28Lk9Bkl.jpg","k":"","f":false},{"i":26,"n":"","u":"https://i.imgur.com/29k3sTw.jpg","t":"https://i.imgur.com/29k3sTwl.jpg","k":"","f":false},{"i":27,"n":"","u":"https://i.imgur.com/2f1InRN.jpg","t":"https://i.imgur.com/2f1InRNl.jpg","k":"","f":false},{"i":28,"n":"","u":"https://i.imgur.com/2kYGCI0.jpg","t":"https://i.imgur.com/2kYGCI0l.jpg","k":"","f":false},{"i":29,"n":"","u":"https://i.imgur.com/2n3OR9i.jpg","t":"https://i.imgur.com/2n3OR9il.jpg","k":"","f":false},{"i":30,"n":"","u":"https://i.imgur.com/2PDhLDI.jpg","t":"https://i.imgur.com/2PDhLDIl.jpg","k":"","f":false},{"i":31,"n":"","u":"https://i.imgur.com/2pevCEF.jpg","t":"https://i.imgur.com/2pevCEFl.jpg","k":"","f":false},{"i":32,"n":"","u":"https://i.imgur.com/2PiwnZx.jpg","t":"https://i.imgur.com/2PiwnZxl.jpg","k":"","f":false},{"i":33,"n":"","u":"https://i.imgur.com/2w9BqAw.jpg","t":"https://i.imgur.com/2w9BqAwl.jpg","k":"","f":false},{"i":34,"n":"","u":"https://i.imgur.com/2waruYB.jpg","t":"https://i.imgur.com/2waruYBl.jpg","k":"","f":false},{"i":35,"n":"","u":"https://i.imgur.com/2YtJbuk.jpg","t":"https://i.imgur.com/2YtJbukl.jpg","k":"","f":false},{"i":36,"n":"","u":"https://i.imgur.com/2z11O1a.jpg","t":"https://i.imgur.com/2z11O1al.jpg","k":"","f":true},{"i":37,"n":"","u":"https://i.imgur.com/35vKZKx.jpg","t":"https://i.imgur.com/35vKZKxl.jpg","k":"","f":false},{"i":38,"n":"","u":"https://i.imgur.com/3CwKczy.jpg","t":"https://i.imgur.com/3CwKczyl.jpg","k":"","f":false},{"i":39,"n":"","u":"https://i.imgur.com/3D8FRLq.jpg","t":"https://i.imgur.com/3D8FRLql.jpg","k":"","f":false},{"i":40,"n":"","u":"https://i.imgur.com/3ear6u7.jpg","t":"https://i.imgur.com/3ear6u7l.jpg","k":"","f":true},{"i":41,"n":"","u":"https://i.imgur.com/3FbMG2z.png","t":"https://i.imgur.com/3FbMG2zl.jpg","k":"","f":false},{"i":42,"n":"","u":"https://i.imgur.com/3FWnMBM.png","t":"https://i.imgur.com/3FWnMBMl.jpg","k":"","f":false},{"i":43,"n":"","u":"https://i.imgur.com/3gCsJ61.jpg","t":"https://i.imgur.com/3gCsJ61l.jpg","k":"","f":false},{"i":44,"n":"","u":"https://i.imgur.com/3gdtBlx.jpg","t":"https://i.imgur.com/3gdtBlxl.jpg","k":"","f":false},{"i":45,"n":"","u":"https://i.imgur.com/3jL3xLA.jpg","t":"https://i.imgur.com/3jL3xLAl.jpg","k":"","f":false},{"i":46,"n":"","u":"https://i.imgur.com/3jN7PQh.jpg","t":"https://i.imgur.com/3jN7PQhl.jpg","k":"","f":false},{"i":47,"n":"","u":"https://i.imgur.com/3KpRnD8.jpg","t":"https://i.imgur.com/3KpRnD8l.jpg","k":"","f":false},{"i":48,"n":"","u":"https://i.imgur.com/3OK16vR.jpg","t":"https://i.imgur.com/3OK16vRl.jpg","k":"","f":false},{"i":49,"n":"","u":"https://i.imgur.com/3qXL54z.jpg","t":"https://i.imgur.com/3qXL54zl.jpg","k":"","f":false},{"i":50,"n":"","u":"https://i.imgur.com/3UO4XN6.jpg","t":"https://i.imgur.com/3UO4XN6l.jpg","k":"","f":false},{"i":51,"n":"","u":"https://i.imgur.com/3XzXc0i.jpg","t":"https://i.imgur.com/3XzXc0il.jpg","k":"","f":true},{"i":52,"n":"","u":"https://i.imgur.com/40nZ8DL.jpg","t":"https://i.imgur.com/40nZ8DLl.jpg","k":"","f":false},{"i":53,"n":"","u":"https://i.imgur.com/4cA16YD.jpg","t":"https://i.imgur.com/4cA16YDl.jpg","k":"","f":false},{"i":54,"n":"","u":"https://i.imgur.com/4dDteyX.jpg","t":"https://i.imgur.com/4dDteyXl.jpg","k":"","f":false},{"i":55,"n":"","u":"https://i.imgur.com/4eE375i.jpg","t":"https://i.imgur.com/4eE375il.jpg","k":"","f":false},{"i":56,"n":"","u":"https://i.imgur.com/4FyOyTj.jpg","t":"https://i.imgur.com/4FyOyTjl.jpg","k":"","f":false},{"i":57,"n":"","u":"https://i.imgur.com/4gC53RU.jpg","t":"https://i.imgur.com/4gC53RUl.jpg","k":"","f":false},{"i":58,"n":"","u":"https://i.imgur.com/4gPe0JE.jpg","t":"https://i.imgur.com/4gPe0JEl.jpg","k":"","f":false},{"i":59,"n":"","u":"https://i.imgur.com/4ilgXIr.jpg","t":"https://i.imgur.com/4ilgXIrl.jpg","k":"","f":false},{"i":60,"n":"","u":"https://i.imgur.com/4Kx2A7y.jpg","t":"https://i.imgur.com/4Kx2A7yl.jpg","k":"","f":false},{"i":61,"n":"","u":"https://i.imgur.com/4mII0Kq.jpg","t":"https://i.imgur.com/4mII0Kql.jpg","k":"","f":false},{"i":62,"n":"","u":"https://i.imgur.com/4N9ipEf.jpg","t":"https://i.imgur.com/4N9ipEfl.jpg","k":"","f":false},{"i":63,"n":"","u":"https://i.imgur.com/4PxioMr.jpg","t":"https://i.imgur.com/4PxioMrl.jpg","k":"","f":false},{"i":64,"n":"","u":"https://i.imgur.com/4svABbw.jpg","t":"https://i.imgur.com/4svABbwl.jpg","k":"","f":false},{"i":65,"n":"","u":"https://i.imgur.com/4ZiqFOz.jpg","t":"https://i.imgur.com/4ZiqFOzl.jpg","k":"","f":true},{"i":66,"n":"","u":"https://i.imgur.com/4ZMrZW9.jpg","t":"https://i.imgur.com/4ZMrZW9l.jpg","k":"","f":false},{"i":67,"n":"","u":"https://i.imgur.com/4zskLXS.jpg","t":"https://i.imgur.com/4zskLXSl.jpg","k":"","f":false},{"i":68,"n":"","u":"https://i.imgur.com/50cGAZF.jpg","t":"https://i.imgur.com/50cGAZFl.jpg","k":"","f":true},{"i":69,"n":"","u":"https://i.imgur.com/5ACFkII.jpg","t":"https://i.imgur.com/5ACFkIIl.jpg","k":"","f":true},{"i":70,"n":"","u":"https://i.imgur.com/5DHExlG.jpg","t":"https://i.imgur.com/5DHExlGl.jpg","k":"","f":false},{"i":71,"n":"","u":"https://i.imgur.com/5DtjoBn.jpg","t":"https://i.imgur.com/5DtjoBnl.jpg","k":"","f":false},{"i":72,"n":"","u":"https://i.imgur.com/5HZjjhk.jpg","t":"https://i.imgur.com/5HZjjhkl.jpg","k":"","f":false},{"i":73,"n":"","u":"https://i.imgur.com/5IaAgGI.jpg","t":"https://i.imgur.com/5IaAgGIl.jpg","k":"","f":false},{"i":74,"n":"","u":"https://i.imgur.com/5LO2zlm.jpg","t":"https://i.imgur.com/5LO2zlml.jpg","k":"","f":false},{"i":75,"n":"","u":"https://i.imgur.com/5o0HWaF.jpg","t":"https://i.imgur.com/5o0HWaFl.jpg","k":"","f":false},{"i":76,"n":"","u":"https://i.imgur.com/5qf3A8i.jpg","t":"https://i.imgur.com/5qf3A8il.jpg","k":"","f":false},{"i":77,"n":"","u":"https://i.imgur.com/5TDMD5t.jpg","t":"https://i.imgur.com/5TDMD5tl.jpg","k":"","f":true},{"i":78,"n":"","u":"https://i.imgur.com/5TrEIFF.jpg","t":"https://i.imgur.com/5TrEIFFl.jpg","k":"","f":true},{"i":79,"n":"","u":"https://i.imgur.com/5VinT96.jpg","t":"https://i.imgur.com/5VinT96l.jpg","k":"","f":false},{"i":80,"n":"","u":"https://i.imgur.com/5vTR78V.jpg","t":"https://i.imgur.com/5vTR78Vl.jpg","k":"","f":false},{"i":81,"n":"","u":"https://i.imgur.com/5WsbT1i.jpg","t":"https://i.imgur.com/5WsbT1il.jpg","k":"","f":false},{"i":82,"n":"","u":"https://i.imgur.com/6AZjkh5.png","t":"https://i.imgur.com/6AZjkh5l.jpg","k":"","f":false},{"i":83,"n":"","u":"https://i.imgur.com/6Gkhdv4.jpg","t":"https://i.imgur.com/6Gkhdv4l.jpg","k":"","f":false},{"i":84,"n":"","u":"https://i.imgur.com/6Iizw3O.jpg","t":"https://i.imgur.com/6Iizw3Ol.jpg","k":"","f":true},{"i":85,"n":"","u":"https://i.imgur.com/6iY82hz.jpg","t":"https://i.imgur.com/6iY82hzl.jpg","k":"","f":false},{"i":86,"n":"","u":"https://i.imgur.com/6kvveNL.jpg","t":"https://i.imgur.com/6kvveNLl.jpg","k":"","f":false},{"i":87,"n":"","u":"https://i.imgur.com/6lgg1xD.jpg","t":"https://i.imgur.com/6lgg1xDl.jpg","k":"","f":false},{"i":88,"n":"","u":"https://i.imgur.com/6MYsmgi.jpg","t":"https://i.imgur.com/6MYsmgil.jpg","k":"","f":false},{"i":89,"n":"","u":"https://i.imgur.com/6NcD41V.jpg","t":"https://i.imgur.com/6NcD41Vl.jpg","k":"","f":false},{"i":90,"n":"","u":"https://i.imgur.com/6nHes4H.jpg","t":"https://i.imgur.com/6nHes4Hl.jpg","k":"","f":true},{"i":91,"n":"","u":"https://i.imgur.com/6QC1HXO.jpg","t":"https://i.imgur.com/6QC1HXOl.jpg","k":"","f":false},{"i":92,"n":"","u":"https://i.imgur.com/6WyWHNZ.jpg","t":"https://i.imgur.com/6WyWHNZl.jpg","k":"","f":false},{"i":93,"n":"","u":"https://i.imgur.com/6xbWvDw.jpg","t":"https://i.imgur.com/6xbWvDwl.jpg","k":"","f":false},{"i":94,"n":"","u":"https://i.imgur.com/76DJiTO.jpg","t":"https://i.imgur.com/76DJiTOl.jpg","k":"","f":false},{"i":95,"n":"","u":"https://i.imgur.com/7EV9d5X.jpg","t":"https://i.imgur.com/7EV9d5Xl.jpg","k":"","f":true},{"i":96,"n":"","u":"https://i.imgur.com/7f9RIxC.jpg","t":"https://i.imgur.com/7f9RIxCl.jpg","k":"","f":true},{"i":97,"n":"","u":"https://i.imgur.com/7fWQvji.jpg","t":"https://i.imgur.com/7fWQvjil.jpg","k":"","f":false},{"i":98,"n":"","u":"https://i.imgur.com/7H2wGCH.jpg","t":"https://i.imgur.com/7H2wGCHl.jpg","k":"","f":false},{"i":99,"n":"","u":"https://i.imgur.com/7jOCwA8.jpg","t":"https://i.imgur.com/7jOCwA8l.jpg","k":"","f":false},{"i":100,"n":"","u":"https://i.imgur.com/7LLmwKT.jpg","t":"https://i.imgur.com/7LLmwKTl.jpg","k":"","f":false},{"i":101,"n":"","u":"https://i.imgur.com/7n0BP9J.jpg","t":"https://i.imgur.com/7n0BP9Jl.jpg","k":"","f":true},{"i":102,"n":"","u":"https://i.imgur.com/7neKvRj.jpg","t":"https://i.imgur.com/7neKvRjl.jpg","k":"","f":false},{"i":103,"n":"","u":"https://i.imgur.com/7sD1km0.jpg","t":"https://i.imgur.com/7sD1km0l.jpg","k":"","f":false},{"i":104,"n":"","u":"https://i.imgur.com/7Sj5WSR.jpg","t":"https://i.imgur.com/7Sj5WSRl.jpg","k":"","f":false},{"i":105,"n":"","u":"https://i.imgur.com/7TG4tcP.jpg","t":"https://i.imgur.com/7TG4tcPl.jpg","k":"","f":false},{"i":106,"n":"","u":"https://i.imgur.com/7V8K6lo.jpg","t":"https://i.imgur.com/7V8K6lol.jpg","k":"","f":false},{"i":107,"n":"","u":"https://i.imgur.com/7wB4MG5.jpg","t":"https://i.imgur.com/7wB4MG5l.jpg","k":"","f":false},{"i":108,"n":"","u":"https://i.imgur.com/7Y94y3P.jpg","t":"https://i.imgur.com/7Y94y3Pl.jpg","k":"","f":false},{"i":109,"n":"","u":"https://i.imgur.com/84ojLoH.jpg","t":"https://i.imgur.com/84ojLoHl.jpg","k":"","f":false},{"i":110,"n":"","u":"https://i.imgur.com/85FOOCU.jpg","t":"https://i.imgur.com/85FOOCUl.jpg","k":"","f":false},{"i":111,"n":"","u":"https://i.imgur.com/86jhyfu.jpg","t":"https://i.imgur.com/86jhyful.jpg","k":"","f":false},{"i":112,"n":"","u":"https://i.imgur.com/86PQW5h.jpg","t":"https://i.imgur.com/86PQW5hl.jpg","k":"","f":true},{"i":113,"n":"","u":"https://i.imgur.com/8bk7IVX.png","t":"https://i.imgur.com/8bk7IVXl.jpg","k":"","f":false},{"i":114,"n":"","u":"https://i.imgur.com/8hJ4Hr0.jpg","t":"https://i.imgur.com/8hJ4Hr0l.jpg","k":"","f":false},{"i":115,"n":"","u":"https://i.imgur.com/8KPuqQA.jpg","t":"https://i.imgur.com/8KPuqQAl.jpg","k":"","f":false},{"i":116,"n":"","u":"https://i.imgur.com/8kQew9l.jpg","t":"https://i.imgur.com/8kQew9ll.jpg","k":"","f":false},{"i":117,"n":"","u":"https://i.imgur.com/8nnmKS2.jpg","t":"https://i.imgur.com/8nnmKS2l.jpg","k":"","f":true},{"i":118,"n":"","u":"https://i.imgur.com/8oRum5V.jpg","t":"https://i.imgur.com/8oRum5Vl.jpg","k":"","f":false},{"i":119,"n":"","u":"https://i.imgur.com/8pNZCK8.png","t":"https://i.imgur.com/8pNZCK8l.jpg","k":"","f":false},{"i":120,"n":"","u":"https://i.imgur.com/9Bp81WQ.jpg","t":"https://i.imgur.com/9Bp81WQl.jpg","k":"","f":false},{"i":121,"n":"","u":"https://i.imgur.com/9DTlF5t.jpg","t":"https://i.imgur.com/9DTlF5tl.jpg","k":"","f":false},{"i":122,"n":"","u":"https://i.imgur.com/9DygIZm.jpg","t":"https://i.imgur.com/9DygIZml.jpg","k":"","f":false},{"i":123,"n":"","u":"https://i.imgur.com/9eSsMi4.jpg","t":"https://i.imgur.com/9eSsMi4l.jpg","k":"","f":true},{"i":124,"n":"","u":"https://i.imgur.com/9EXaCnq.jpg","t":"https://i.imgur.com/9EXaCnql.jpg","k":"","f":false},{"i":125,"n":"","u":"https://i.imgur.com/9GLpnPI.jpg","t":"https://i.imgur.com/9GLpnPIl.jpg","k":"","f":false},{"i":126,"n":"","u":"https://i.imgur.com/9hDcgaV.jpg","t":"https://i.imgur.com/9hDcgaVl.jpg","k":"","f":false},{"i":127,"n":"","u":"https://i.imgur.com/9HFos1l.jpg","t":"https://i.imgur.com/9HFos1ll.jpg","k":"","f":false},{"i":128,"n":"","u":"https://i.imgur.com/9INEVVk.jpg","t":"https://i.imgur.com/9INEVVkl.jpg","k":"","f":false},{"i":129,"n":"","u":"https://i.imgur.com/9mAqYPz.jpg","t":"https://i.imgur.com/9mAqYPzl.jpg","k":"","f":false},{"i":130,"n":"","u":"https://i.imgur.com/9QWmWL6.jpg","t":"https://i.imgur.com/9QWmWL6l.jpg","k":"","f":false},{"i":131,"n":"","u":"https://i.imgur.com/9sM5SZF.jpg","t":"https://i.imgur.com/9sM5SZFl.jpg","k":"","f":false},{"i":132,"n":"","u":"https://i.imgur.com/9V11VzR.jpg","t":"https://i.imgur.com/9V11VzRl.jpg","k":"","f":true},{"i":133,"n":"","u":"https://i.imgur.com/9vpNxEL.jpg","t":"https://i.imgur.com/9vpNxELl.jpg","k":"","f":true},{"i":134,"n":"","u":"https://i.imgur.com/9Zqij38.jpg","t":"https://i.imgur.com/9Zqij38l.jpg","k":"","f":false},{"i":135,"n":"","u":"https://i.imgur.com/A0eKJ8M.jpg","t":"https://i.imgur.com/A0eKJ8Ml.jpg","k":"","f":false},{"i":136,"n":"","u":"https://i.imgur.com/A1nr4wb.jpg","t":"https://i.imgur.com/A1nr4wbl.jpg","k":"","f":false},{"i":137,"n":"","u":"https://i.imgur.com/a2Hndt0.jpg","t":"https://i.imgur.com/a2Hndt0l.jpg","k":"","f":false},{"i":138,"n":"","u":"https://i.imgur.com/a3EO2iQ.jpg","t":"https://i.imgur.com/a3EO2iQl.jpg","k":"","f":false},{"i":139,"n":"","u":"https://i.imgur.com/A5FDpje.jpg","t":"https://i.imgur.com/A5FDpjel.jpg","k":"","f":false},{"i":140,"n":"","u":"https://i.imgur.com/a5u4Rqi.jpg","t":"https://i.imgur.com/a5u4Rqil.jpg","k":"","f":false},{"i":141,"n":"","u":"https://i.imgur.com/A6k7RJW.jpg","t":"https://i.imgur.com/A6k7RJWl.jpg","k":"","f":true},{"i":142,"n":"","u":"https://i.imgur.com/A8QRha5.jpg","t":"https://i.imgur.com/A8QRha5l.jpg","k":"","f":false},{"i":143,"n":"","u":"https://i.imgur.com/a8tqhjm.jpg","t":"https://i.imgur.com/a8tqhjml.jpg","k":"","f":false},{"i":144,"n":"","u":"https://i.imgur.com/aajIdIF.jpg","t":"https://i.imgur.com/aajIdIFl.jpg","k":"","f":false},{"i":145,"n":"","u":"https://i.imgur.com/AD7sIHJ.jpg","t":"https://i.imgur.com/AD7sIHJl.jpg","k":"","f":false},{"i":146,"n":"","u":"https://i.imgur.com/AdpeMCO.jpg","t":"https://i.imgur.com/AdpeMCOl.jpg","k":"","f":false},{"i":147,"n":"","u":"https://i.imgur.com/aeeDriD.jpg","t":"https://i.imgur.com/aeeDriDl.jpg","k":"","f":false},{"i":148,"n":"","u":"https://i.imgur.com/aES5vQe.jpg","t":"https://i.imgur.com/aES5vQel.jpg","k":"","f":false},{"i":149,"n":"","u":"https://i.imgur.com/AfmdLx0.jpg","t":"https://i.imgur.com/AfmdLx0l.jpg","k":"","f":false},{"i":150,"n":"","u":"https://i.imgur.com/afmHNgl.jpg","t":"https://i.imgur.com/afmHNgll.jpg","k":"","f":false},{"i":151,"n":"","u":"https://i.imgur.com/AhXFTk8.jpg","t":"https://i.imgur.com/AhXFTk8l.jpg","k":"","f":false},{"i":152,"n":"","u":"https://i.imgur.com/Aj5pjDM.jpg","t":"https://i.imgur.com/Aj5pjDMl.jpg","k":"","f":false},{"i":153,"n":"","u":"https://i.imgur.com/AJ8BUH1.jpg","t":"https://i.imgur.com/AJ8BUH1l.jpg","k":"","f":false},{"i":154,"n":"","u":"https://i.imgur.com/AJCMRVS.jpg","t":"https://i.imgur.com/AJCMRVSl.jpg","k":"","f":false},{"i":155,"n":"","u":"https://i.imgur.com/aJO6Snf.jpg","t":"https://i.imgur.com/aJO6Snfl.jpg","k":"","f":false},{"i":156,"n":"","u":"https://i.imgur.com/aMTrp2X.jpg","t":"https://i.imgur.com/aMTrp2Xl.jpg","k":"","f":false},{"i":157,"n":"","u":"https://i.imgur.com/AnN17my.jpg","t":"https://i.imgur.com/AnN17myl.jpg","k":"","f":false},{"i":158,"n":"","u":"https://i.imgur.com/aOfQUEY.jpg","t":"https://i.imgur.com/aOfQUEYl.jpg","k":"","f":false},{"i":159,"n":"","u":"https://i.imgur.com/Aojof7I.jpg","t":"https://i.imgur.com/Aojof7Il.jpg","k":"","f":false},{"i":160,"n":"","u":"https://i.imgur.com/arfERO0.jpg","t":"https://i.imgur.com/arfERO0l.jpg","k":"","f":false},{"i":161,"n":"","u":"https://i.imgur.com/ARkiPU1.jpg","t":"https://i.imgur.com/ARkiPU1l.jpg","k":"","f":false},{"i":162,"n":"","u":"https://i.imgur.com/AS4292C.jpg","t":"https://i.imgur.com/AS4292Cl.jpg","k":"","f":false},{"i":163,"n":"","u":"https://i.imgur.com/AspJUSe.jpg","t":"https://i.imgur.com/AspJUSel.jpg","k":"","f":true},{"i":164,"n":"","u":"https://i.imgur.com/axCYHbR.jpg","t":"https://i.imgur.com/axCYHbRl.jpg","k":"","f":true},{"i":165,"n":"","u":"https://i.imgur.com/ayEwdIv.jpg","t":"https://i.imgur.com/ayEwdIvl.jpg","k":"","f":false},{"i":166,"n":"","u":"https://i.imgur.com/b7oZzpK.jpg","t":"https://i.imgur.com/b7oZzpKl.jpg","k":"","f":false},{"i":167,"n":"","u":"https://i.imgur.com/B8hAncq.jpg","t":"https://i.imgur.com/B8hAncql.jpg","k":"","f":false},{"i":168,"n":"","u":"https://i.imgur.com/bB6GjWs.jpg","t":"https://i.imgur.com/bB6GjWsl.jpg","k":"","f":false},{"i":169,"n":"","u":"https://i.imgur.com/bbdsNGp.jpg","t":"https://i.imgur.com/bbdsNGpl.jpg","k":"","f":true},{"i":170,"n":"","u":"https://i.imgur.com/BeDkjUk.jpg","t":"https://i.imgur.com/BeDkjUkl.jpg","k":"","f":false},{"i":171,"n":"","u":"https://i.imgur.com/bEIrGJk.jpg","t":"https://i.imgur.com/bEIrGJkl.jpg","k":"","f":false},{"i":172,"n":"","u":"https://i.imgur.com/bFEpjV5.jpg","t":"https://i.imgur.com/bFEpjV5l.jpg","k":"","f":false},{"i":173,"n":"","u":"https://i.imgur.com/bHMq0AK.jpg","t":"https://i.imgur.com/bHMq0AKl.jpg","k":"","f":false},{"i":174,"n":"","u":"https://i.imgur.com/bHolMZu.jpg","t":"https://i.imgur.com/bHolMZul.jpg","k":"","f":true},{"i":175,"n":"","u":"https://i.imgur.com/BiQ6ob6.jpg","t":"https://i.imgur.com/BiQ6ob6l.jpg","k":"","f":false},{"i":176,"n":"","u":"https://i.imgur.com/bJItEFS.jpg","t":"https://i.imgur.com/bJItEFSl.jpg","k":"","f":false},{"i":177,"n":"","u":"https://i.imgur.com/BJRizH6.jpg","t":"https://i.imgur.com/BJRizH6l.jpg","k":"","f":false},{"i":178,"n":"","u":"https://i.imgur.com/bkouxyQ.jpg","t":"https://i.imgur.com/bkouxyQl.jpg","k":"","f":false},{"i":179,"n":"","u":"https://i.imgur.com/bKZ5Ebe.jpg","t":"https://i.imgur.com/bKZ5Ebel.jpg","k":"","f":false},{"i":180,"n":"","u":"https://i.imgur.com/BlixTeL.jpg","t":"https://i.imgur.com/BlixTeLl.jpg","k":"","f":false},{"i":181,"n":"","u":"https://i.imgur.com/BLoR9An.jpg","t":"https://i.imgur.com/BLoR9Anl.jpg","k":"","f":false},{"i":182,"n":"","u":"https://i.imgur.com/BOGlFig.jpg","t":"https://i.imgur.com/BOGlFigl.jpg","k":"","f":false},{"i":183,"n":"","u":"https://i.imgur.com/bOrBfjh.jpg","t":"https://i.imgur.com/bOrBfjhl.jpg","k":"","f":false},{"i":184,"n":"","u":"https://i.imgur.com/BosEbBq.jpg","t":"https://i.imgur.com/BosEbBql.jpg","k":"","f":true},{"i":185,"n":"","u":"https://i.imgur.com/BpD19K2.jpg","t":"https://i.imgur.com/BpD19K2l.jpg","k":"","f":false},{"i":186,"n":"","u":"https://i.imgur.com/bqVf1WL.jpg","t":"https://i.imgur.com/bqVf1WLl.jpg","k":"","f":false},{"i":187,"n":"","u":"https://i.imgur.com/Br9PR2T.jpg","t":"https://i.imgur.com/Br9PR2Tl.jpg","k":"","f":false},{"i":188,"n":"","u":"https://i.imgur.com/Bsjxa8T.jpg","t":"https://i.imgur.com/Bsjxa8Tl.jpg","k":"","f":false},{"i":189,"n":"","u":"https://i.imgur.com/bt42gcn.jpg","t":"https://i.imgur.com/bt42gcnl.jpg","k":"","f":true},{"i":190,"n":"","u":"https://i.imgur.com/BTlnUv3.jpg","t":"https://i.imgur.com/BTlnUv3l.jpg","k":"","f":false},{"i":191,"n":"","u":"https://i.imgur.com/BUhfmJl.jpg","t":"https://i.imgur.com/BUhfmJll.jpg","k":"","f":false},{"i":192,"n":"","u":"https://i.imgur.com/BWMkSqg.jpg","t":"https://i.imgur.com/BWMkSqgl.jpg","k":"","f":true},{"i":193,"n":"","u":"https://i.imgur.com/BX1fS8N.jpg","t":"https://i.imgur.com/BX1fS8Nl.jpg","k":"","f":false},{"i":194,"n":"","u":"https://i.imgur.com/BY01mn3.jpg","t":"https://i.imgur.com/BY01mn3l.jpg","k":"","f":false},{"i":195,"n":"","u":"https://i.imgur.com/Bzd12k8.jpg","t":"https://i.imgur.com/Bzd12k8l.jpg","k":"","f":false},{"i":196,"n":"","u":"https://i.imgur.com/bzEAG3l.png","t":"https://i.imgur.com/bzEAG3ll.jpg","k":"","f":false},{"i":197,"n":"","u":"https://i.imgur.com/c7gFjKI.jpg","t":"https://i.imgur.com/c7gFjKIl.jpg","k":"","f":false},{"i":198,"n":"","u":"https://i.imgur.com/cFzeMhl.jpg","t":"https://i.imgur.com/cFzeMhll.jpg","k":"","f":false},{"i":199,"n":"","u":"https://i.imgur.com/CGPrdSi.jpg","t":"https://i.imgur.com/CGPrdSil.jpg","k":"","f":false},{"i":200,"n":"","u":"https://i.imgur.com/cHpdMxr.jpg","t":"https://i.imgur.com/cHpdMxrl.jpg","k":"","f":false},{"i":201,"n":"","u":"https://i.imgur.com/cHT1JNk.jpg","t":"https://i.imgur.com/cHT1JNkl.jpg","k":"","f":true},{"i":202,"n":"","u":"https://i.imgur.com/cHzniR3.jpg","t":"https://i.imgur.com/cHzniR3l.jpg","k":"","f":false},{"i":203,"n":"","u":"https://i.imgur.com/CJMxkVp.jpg","t":"https://i.imgur.com/CJMxkVpl.jpg","k":"","f":false},{"i":204,"n":"","u":"https://i.imgur.com/cJuwBe4.jpg","t":"https://i.imgur.com/cJuwBe4l.jpg","k":"","f":false},{"i":205,"n":"","u":"https://i.imgur.com/cKscpBM.jpg","t":"https://i.imgur.com/cKscpBMl.jpg","k":"","f":false},{"i":206,"n":"","u":"https://i.imgur.com/ckTx9oa.jpg","t":"https://i.imgur.com/ckTx9oal.jpg","k":"","f":false},{"i":207,"n":"","u":"https://i.imgur.com/CM2rIUL.jpg","t":"https://i.imgur.com/CM2rIULl.jpg","k":"","f":false},{"i":208,"n":"","u":"https://i.imgur.com/cmBINRG.jpg","t":"https://i.imgur.com/cmBINRGl.jpg","k":"","f":true},{"i":209,"n":"","u":"https://i.imgur.com/cneJNkI.jpg","t":"https://i.imgur.com/cneJNkIl.jpg","k":"","f":true},{"i":210,"n":"","u":"https://i.imgur.com/cqAk711.jpg","t":"https://i.imgur.com/cqAk711l.jpg","k":"","f":false},{"i":211,"n":"","u":"https://i.imgur.com/cqLoN8n.jpg","t":"https://i.imgur.com/cqLoN8nl.jpg","k":"","f":false},{"i":212,"n":"","u":"https://i.imgur.com/cqTULQJ.jpg","t":"https://i.imgur.com/cqTULQJl.jpg","k":"","f":false},{"i":213,"n":"","u":"https://i.imgur.com/crIuvJC.jpg","t":"https://i.imgur.com/crIuvJCl.jpg","k":"","f":true},{"i":214,"n":"","u":"https://i.imgur.com/CsrP7zh.jpg","t":"https://i.imgur.com/CsrP7zhl.jpg","k":"","f":false},{"i":215,"n":"","u":"https://i.imgur.com/cSwUKvi.jpg","t":"https://i.imgur.com/cSwUKvil.jpg","k":"","f":false},{"i":216,"n":"","u":"https://i.imgur.com/CTPFlKQ.jpg","t":"https://i.imgur.com/CTPFlKQl.jpg","k":"","f":true},{"i":217,"n":"","u":"https://i.imgur.com/CuXSlCB.jpg","t":"https://i.imgur.com/CuXSlCBl.jpg","k":"","f":false},{"i":218,"n":"","u":"https://i.imgur.com/cwaYeRd.jpg","t":"https://i.imgur.com/cwaYeRdl.jpg","k":"","f":false},{"i":219,"n":"","u":"https://i.imgur.com/cwscHIi.jpg","t":"https://i.imgur.com/cwscHIil.jpg","k":"","f":false},{"i":220,"n":"","u":"https://i.imgur.com/cxv2SMe.jpg","t":"https://i.imgur.com/cxv2SMel.jpg","k":"","f":false},{"i":221,"n":"","u":"https://i.imgur.com/d1ZfUE7.png","t":"https://i.imgur.com/d1ZfUE7l.jpg","k":"","f":false},{"i":222,"n":"","u":"https://i.imgur.com/D5p5T9j.jpg","t":"https://i.imgur.com/D5p5T9jl.jpg","k":"","f":false},{"i":223,"n":"","u":"https://i.imgur.com/D8sPLVL.jpg","t":"https://i.imgur.com/D8sPLVLl.jpg","k":"","f":false},{"i":224,"n":"","u":"https://i.imgur.com/DA6lB6G.jpg","t":"https://i.imgur.com/DA6lB6Gl.jpg","k":"","f":false},{"i":225,"n":"","u":"https://i.imgur.com/Dbj1ENh.jpg","t":"https://i.imgur.com/Dbj1ENhl.jpg","k":"","f":false},{"i":226,"n":"","u":"https://i.imgur.com/dBn3C7z.jpg","t":"https://i.imgur.com/dBn3C7zl.jpg","k":"","f":false},{"i":227,"n":"","u":"https://i.imgur.com/dbWHkx3.jpg","t":"https://i.imgur.com/dbWHkx3l.jpg","k":"","f":false},{"i":228,"n":"","u":"https://i.imgur.com/DcfCwsK.jpg","t":"https://i.imgur.com/DcfCwsKl.jpg","k":"","f":true},{"i":229,"n":"","u":"https://i.imgur.com/DCLkY3n.jpg","t":"https://i.imgur.com/DCLkY3nl.jpg","k":"","f":false},{"i":230,"n":"","u":"https://i.imgur.com/ddrQ6Gk.png","t":"https://i.imgur.com/ddrQ6Gkl.jpg","k":"","f":false},{"i":231,"n":"","u":"https://i.imgur.com/deSbr9x.jpg","t":"https://i.imgur.com/deSbr9xl.jpg","k":"","f":false},{"i":232,"n":"","u":"https://i.imgur.com/dhevGcX.jpg","t":"https://i.imgur.com/dhevGcXl.jpg","k":"","f":false},{"i":233,"n":"","u":"https://i.imgur.com/DI26m5y.jpg","t":"https://i.imgur.com/DI26m5yl.jpg","k":"","f":false},{"i":234,"n":"","u":"https://i.imgur.com/dk2CJ8i.jpg","t":"https://i.imgur.com/dk2CJ8il.jpg","k":"","f":false},{"i":235,"n":"","u":"https://i.imgur.com/dkkjOw8.jpg","t":"https://i.imgur.com/dkkjOw8l.jpg","k":"","f":false},{"i":236,"n":"","u":"https://i.imgur.com/DkoV9nA.jpg","t":"https://i.imgur.com/DkoV9nAl.jpg","k":"","f":true},{"i":237,"n":"","u":"https://i.imgur.com/DKqCJz8.jpg","t":"https://i.imgur.com/DKqCJz8l.jpg","k":"","f":false},{"i":238,"n":"","u":"https://i.imgur.com/DnJP8cO.jpg","t":"https://i.imgur.com/DnJP8cOl.jpg","k":"","f":false},{"i":239,"n":"","u":"https://i.imgur.com/dNy1j14.jpg","t":"https://i.imgur.com/dNy1j14l.jpg","k":"","f":true},{"i":240,"n":"","u":"https://i.imgur.com/Do16Gzb.jpg","t":"https://i.imgur.com/Do16Gzbl.jpg","k":"","f":false},{"i":241,"n":"","u":"https://i.imgur.com/Drs79Ky.png","t":"https://i.imgur.com/Drs79Kyl.jpg","k":"","f":false},{"i":242,"n":"","u":"https://i.imgur.com/drwA1Rs.jpg","t":"https://i.imgur.com/drwA1Rsl.jpg","k":"","f":false},{"i":243,"n":"","u":"https://i.imgur.com/DT3V4UU.jpg","t":"https://i.imgur.com/DT3V4UUl.jpg","k":"","f":false},{"i":244,"n":"","u":"https://i.imgur.com/DUKqAMT.jpg","t":"https://i.imgur.com/DUKqAMTl.jpg","k":"","f":false},{"i":245,"n":"","u":"https://i.imgur.com/dXsWIuy.jpg","t":"https://i.imgur.com/dXsWIuyl.jpg","k":"","f":false},{"i":246,"n":"","u":"https://i.imgur.com/DyhLpQC.jpg","t":"https://i.imgur.com/DyhLpQCl.jpg","k":"","f":false},{"i":247,"n":"","u":"https://i.imgur.com/DYT5Euv.jpg","t":"https://i.imgur.com/DYT5Euvl.jpg","k":"","f":true},{"i":248,"n":"","u":"https://i.imgur.com/E0X9NVt.jpg","t":"https://i.imgur.com/E0X9NVtl.jpg","k":"","f":false},{"i":249,"n":"","u":"https://i.imgur.com/E3cecvO.jpg","t":"https://i.imgur.com/E3cecvOl.jpg","k":"","f":false},{"i":250,"n":"","u":"https://i.imgur.com/E6X2qzR.jpg","t":"https://i.imgur.com/E6X2qzRl.jpg","k":"","f":false},{"i":251,"n":"","u":"https://i.imgur.com/EarxDin.jpg","t":"https://i.imgur.com/EarxDinl.jpg","k":"","f":true},{"i":252,"n":"","u":"https://i.imgur.com/EbrNUMo.jpg","t":"https://i.imgur.com/EbrNUMol.jpg","k":"","f":false},{"i":253,"n":"","u":"https://i.imgur.com/eBXxcuX.jpg","t":"https://i.imgur.com/eBXxcuXl.jpg","k":"","f":false},{"i":254,"n":"","u":"https://i.imgur.com/EIPNyL5.jpg","t":"https://i.imgur.com/EIPNyL5l.jpg","k":"","f":true},{"i":255,"n":"","u":"https://i.imgur.com/El8B5ol.jpg","t":"https://i.imgur.com/El8B5oll.jpg","k":"","f":false},{"i":256,"n":"","u":"https://i.imgur.com/EnBCZ3Z.jpg","t":"https://i.imgur.com/EnBCZ3Zl.jpg","k":"","f":false},{"i":257,"n":"","u":"https://i.imgur.com/eQpQD24.jpg","t":"https://i.imgur.com/eQpQD24l.jpg","k":"","f":false},{"i":258,"n":"","u":"https://i.imgur.com/eUouE8c.jpg","t":"https://i.imgur.com/eUouE8cl.jpg","k":"","f":false},{"i":259,"n":"","u":"https://i.imgur.com/Euw1TDK.jpg","t":"https://i.imgur.com/Euw1TDKl.jpg","k":"","f":true},{"i":260,"n":"","u":"https://i.imgur.com/eVvvcbF.jpg","t":"https://i.imgur.com/eVvvcbFl.jpg","k":"","f":false},{"i":261,"n":"","u":"https://i.imgur.com/evZYfeD.jpg","t":"https://i.imgur.com/evZYfeDl.jpg","k":"","f":true},{"i":262,"n":"","u":"https://i.imgur.com/eXVd4yH.jpg","t":"https://i.imgur.com/eXVd4yHl.jpg","k":"","f":false},{"i":263,"n":"","u":"https://i.imgur.com/EyXb2p1.jpg","t":"https://i.imgur.com/EyXb2p1l.jpg","k":"","f":false},{"i":264,"n":"","u":"https://i.imgur.com/EzrPLzi.jpg","t":"https://i.imgur.com/EzrPLzil.jpg","k":"","f":true},{"i":265,"n":"","u":"https://i.imgur.com/f3LyDKm.jpg","t":"https://i.imgur.com/f3LyDKml.jpg","k":"","f":false},{"i":266,"n":"","u":"https://i.imgur.com/f9oORcJ.jpg","t":"https://i.imgur.com/f9oORcJl.jpg","k":"","f":false},{"i":267,"n":"","u":"https://i.imgur.com/f9pCQsn.jpg","t":"https://i.imgur.com/f9pCQsnl.jpg","k":"","f":false},{"i":268,"n":"","u":"https://i.imgur.com/F9vKOO4.jpg","t":"https://i.imgur.com/F9vKOO4l.jpg","k":"","f":false},{"i":269,"n":"","u":"https://i.imgur.com/FaDngZx.jpg","t":"https://i.imgur.com/FaDngZxl.jpg","k":"","f":false},{"i":270,"n":"","u":"https://i.imgur.com/fbDE87u.jpg","t":"https://i.imgur.com/fbDE87ul.jpg","k":"","f":false},{"i":271,"n":"","u":"https://i.imgur.com/fc5nzQo.jpg","t":"https://i.imgur.com/fc5nzQol.jpg","k":"","f":true},{"i":272,"n":"","u":"https://i.imgur.com/FCeh5Zj.jpg","t":"https://i.imgur.com/FCeh5Zjl.jpg","k":"","f":false},{"i":273,"n":"","u":"https://i.imgur.com/feocngM.jpg","t":"https://i.imgur.com/feocngMl.jpg","k":"","f":false},{"i":274,"n":"","u":"https://i.imgur.com/FfOS9O4.jpg","t":"https://i.imgur.com/FfOS9O4l.jpg","k":"","f":false},{"i":275,"n":"","u":"https://i.imgur.com/FGg76LB.jpg","t":"https://i.imgur.com/FGg76LBl.jpg","k":"","f":true},{"i":276,"n":"","u":"https://i.imgur.com/FGkkIvJ.jpg","t":"https://i.imgur.com/FGkkIvJl.jpg","k":"","f":true},{"i":277,"n":"","u":"https://i.imgur.com/fHNwPMl.jpg","t":"https://i.imgur.com/fHNwPMll.jpg","k":"","f":false},{"i":278,"n":"","u":"https://i.imgur.com/FHoJzMt.jpg","t":"https://i.imgur.com/FHoJzMtl.jpg","k":"","f":true},{"i":279,"n":"","u":"https://i.imgur.com/FIsnBDd.jpg","t":"https://i.imgur.com/FIsnBDdl.jpg","k":"","f":false},{"i":280,"n":"","u":"https://i.imgur.com/FjATj4x.jpg","t":"https://i.imgur.com/FjATj4xl.jpg","k":"","f":false},{"i":281,"n":"","u":"https://i.imgur.com/FjmYw7O.jpg","t":"https://i.imgur.com/FjmYw7Ol.jpg","k":"","f":false},{"i":282,"n":"","u":"https://i.imgur.com/FJqDCXr.jpg","t":"https://i.imgur.com/FJqDCXrl.jpg","k":"","f":false},{"i":283,"n":"","u":"https://i.imgur.com/fk9FSy8.jpg","t":"https://i.imgur.com/fk9FSy8l.jpg","k":"","f":false},{"i":284,"n":"","u":"https://i.imgur.com/FKPGcxe.jpg","t":"https://i.imgur.com/FKPGcxel.jpg","k":"","f":false},{"i":285,"n":"","u":"https://i.imgur.com/fLHfetw.jpg","t":"https://i.imgur.com/fLHfetwl.jpg","k":"","f":false},{"i":286,"n":"","u":"https://i.imgur.com/FlTGXJT.png","t":"https://i.imgur.com/FlTGXJTl.jpg","k":"","f":true},{"i":287,"n":"","u":"https://i.imgur.com/FMHNRIo.jpg","t":"https://i.imgur.com/FMHNRIol.jpg","k":"","f":false},{"i":288,"n":"","u":"https://i.imgur.com/FMQzFpo.jpg","t":"https://i.imgur.com/FMQzFpol.jpg","k":"","f":true},{"i":289,"n":"","u":"https://i.imgur.com/fMT3ytg.jpg","t":"https://i.imgur.com/fMT3ytgl.jpg","k":"","f":true},{"i":290,"n":"","u":"https://i.imgur.com/FNSEdsh.jpg","t":"https://i.imgur.com/FNSEdshl.jpg","k":"","f":false},{"i":291,"n":"","u":"https://i.imgur.com/fP0Nsp3.jpg","t":"https://i.imgur.com/fP0Nsp3l.jpg","k":"","f":false},{"i":292,"n":"","u":"https://i.imgur.com/FpRiaAh.jpg","t":"https://i.imgur.com/FpRiaAhl.jpg","k":"","f":false},{"i":293,"n":"","u":"https://i.imgur.com/FPucuBI.jpg","t":"https://i.imgur.com/FPucuBIl.jpg","k":"","f":false},{"i":294,"n":"","u":"https://i.imgur.com/FpxvHY4.jpg","t":"https://i.imgur.com/FpxvHY4l.jpg","k":"","f":false},{"i":295,"n":"","u":"https://i.imgur.com/fREvMmx.jpg","t":"https://i.imgur.com/fREvMmxl.jpg","k":"","f":false},{"i":296,"n":"","u":"https://i.imgur.com/fshsIw2.jpg","t":"https://i.imgur.com/fshsIw2l.jpg","k":"","f":false},{"i":297,"n":"","u":"https://i.imgur.com/fV4SYTn.jpg","t":"https://i.imgur.com/fV4SYTnl.jpg","k":"","f":false},{"i":298,"n":"","u":"https://i.imgur.com/Fya1EHL.jpg","t":"https://i.imgur.com/Fya1EHLl.jpg","k":"","f":false},{"i":299,"n":"","u":"https://i.imgur.com/fzlu3xa.jpg","t":"https://i.imgur.com/fzlu3xal.jpg","k":"","f":true},{"i":300,"n":"","u":"https://i.imgur.com/g0Cj7Ji.jpg","t":"https://i.imgur.com/g0Cj7Jil.jpg","k":"","f":true},{"i":301,"n":"","u":"https://i.imgur.com/G0J2feO.jpg","t":"https://i.imgur.com/G0J2feOl.jpg","k":"","f":false},{"i":302,"n":"","u":"https://i.imgur.com/g0tU0Md.jpg","t":"https://i.imgur.com/g0tU0Mdl.jpg","k":"","f":false},{"i":303,"n":"","u":"https://i.imgur.com/G1IRd1O.jpg","t":"https://i.imgur.com/G1IRd1Ol.jpg","k":"","f":false},{"i":304,"n":"","u":"https://i.imgur.com/g3cJyxK.jpg","t":"https://i.imgur.com/g3cJyxKl.jpg","k":"","f":false},{"i":305,"n":"","u":"https://i.imgur.com/G3iw21z.jpg","t":"https://i.imgur.com/G3iw21zl.jpg","k":"","f":false},{"i":306,"n":"","u":"https://i.imgur.com/g3ZiZaT.jpg","t":"https://i.imgur.com/g3ZiZaTl.jpg","k":"","f":false},{"i":307,"n":"","u":"https://i.imgur.com/g4hGupg.jpg","t":"https://i.imgur.com/g4hGupgl.jpg","k":"","f":false},{"i":308,"n":"","u":"https://i.imgur.com/g71SbCF.jpg","t":"https://i.imgur.com/g71SbCFl.jpg","k":"","f":false},{"i":309,"n":"","u":"https://i.imgur.com/GCD8vAq.png","t":"https://i.imgur.com/GCD8vAql.jpg","k":"","f":true},{"i":310,"n":"","u":"https://i.imgur.com/gCHEHdh.jpg","t":"https://i.imgur.com/gCHEHdhl.jpg","k":"","f":false},{"i":311,"n":"","u":"https://i.imgur.com/gciuC26.jpg","t":"https://i.imgur.com/gciuC26l.jpg","k":"","f":false},{"i":312,"n":"","u":"https://i.imgur.com/gCVLAUI.jpg","t":"https://i.imgur.com/gCVLAUIl.jpg","k":"","f":true},{"i":313,"n":"","u":"https://i.imgur.com/gdKbJsX.jpg","t":"https://i.imgur.com/gdKbJsXl.jpg","k":"","f":false},{"i":314,"n":"","u":"https://i.imgur.com/Gep2nUY.jpg","t":"https://i.imgur.com/Gep2nUYl.jpg","k":"","f":true},{"i":315,"n":"","u":"https://i.imgur.com/gG3Cl7j.jpg","t":"https://i.imgur.com/gG3Cl7jl.jpg","k":"","f":false},{"i":316,"n":"","u":"https://i.imgur.com/ggV54Rp.jpg","t":"https://i.imgur.com/ggV54Rpl.jpg","k":"","f":false},{"i":317,"n":"","u":"https://i.imgur.com/gIxEQ1l.jpg","t":"https://i.imgur.com/gIxEQ1ll.jpg","k":"","f":false},{"i":318,"n":"","u":"https://i.imgur.com/gLbzVs3.jpg","t":"https://i.imgur.com/gLbzVs3l.jpg","k":"","f":false},{"i":319,"n":"","u":"https://i.imgur.com/gMqk7xj.jpg","t":"https://i.imgur.com/gMqk7xjl.jpg","k":"","f":false},{"i":320,"n":"","u":"https://i.imgur.com/GMRVQwh.jpg","t":"https://i.imgur.com/GMRVQwhl.jpg","k":"","f":false},{"i":321,"n":"","u":"https://i.imgur.com/gnfq2eJ.jpg","t":"https://i.imgur.com/gnfq2eJl.jpg","k":"","f":false},{"i":322,"n":"","u":"https://i.imgur.com/grREiSq.png","t":"https://i.imgur.com/grREiSql.jpg","k":"","f":true},{"i":323,"n":"","u":"https://i.imgur.com/gSiP13Y.jpg","t":"https://i.imgur.com/gSiP13Yl.jpg","k":"","f":false},{"i":324,"n":"","u":"https://i.imgur.com/gTsP1sX.jpg","t":"https://i.imgur.com/gTsP1sXl.jpg","k":"","f":false},{"i":325,"n":"","u":"https://i.imgur.com/GUxZ2AQ.jpg","t":"https://i.imgur.com/GUxZ2AQl.jpg","k":"","f":false},{"i":326,"n":"","u":"https://i.imgur.com/GwDUL2J.jpg","t":"https://i.imgur.com/GwDUL2Jl.jpg","k":"","f":false},{"i":327,"n":"","u":"https://i.imgur.com/GWK8pHJ.jpg","t":"https://i.imgur.com/GWK8pHJl.jpg","k":"","f":false},{"i":328,"n":"","u":"https://i.imgur.com/GWnegtH.jpg","t":"https://i.imgur.com/GWnegtHl.jpg","k":"","f":false},{"i":329,"n":"","u":"https://i.imgur.com/gX4QtVK.jpg","t":"https://i.imgur.com/gX4QtVKl.jpg","k":"","f":false},{"i":330,"n":"","u":"https://i.imgur.com/GxcrCWC.jpg","t":"https://i.imgur.com/GxcrCWCl.jpg","k":"","f":false},{"i":331,"n":"","u":"https://i.imgur.com/gYNK6J9.jpg","t":"https://i.imgur.com/gYNK6J9l.jpg","k":"","f":false},{"i":332,"n":"","u":"https://i.imgur.com/GywS61r.jpg","t":"https://i.imgur.com/GywS61rl.jpg","k":"","f":false},{"i":333,"n":"","u":"https://i.imgur.com/H1yXEIR.jpg","t":"https://i.imgur.com/H1yXEIRl.jpg","k":"","f":true},{"i":334,"n":"","u":"https://i.imgur.com/h22P1Al.jpg","t":"https://i.imgur.com/h22P1All.jpg","k":"","f":false},{"i":335,"n":"","u":"https://i.imgur.com/h2CdcXP.jpg","t":"https://i.imgur.com/h2CdcXPl.jpg","k":"","f":false},{"i":336,"n":"","u":"https://i.imgur.com/h4JTVVI.jpg","t":"https://i.imgur.com/h4JTVVIl.jpg","k":"","f":false},{"i":337,"n":"","u":"https://i.imgur.com/h69P8og.jpg","t":"https://i.imgur.com/h69P8ogl.jpg","k":"","f":false},{"i":338,"n":"","u":"https://i.imgur.com/H9a2e6J.jpg","t":"https://i.imgur.com/H9a2e6Jl.jpg","k":"","f":false},{"i":339,"n":"","u":"https://i.imgur.com/H9MvIZ7.jpg","t":"https://i.imgur.com/H9MvIZ7l.jpg","k":"","f":false},{"i":340,"n":"","u":"https://i.imgur.com/HBx2BRB.jpg","t":"https://i.imgur.com/HBx2BRBl.jpg","k":"","f":false},{"i":341,"n":"","u":"https://i.imgur.com/HC76V4x.jpg","t":"https://i.imgur.com/HC76V4xl.jpg","k":"","f":false},{"i":342,"n":"","u":"https://i.imgur.com/hERhH9f.jpg","t":"https://i.imgur.com/hERhH9fl.jpg","k":"","f":false},{"i":343,"n":"","u":"https://i.imgur.com/heWAuEr.jpg","t":"https://i.imgur.com/heWAuErl.jpg","k":"","f":true},{"i":344,"n":"","u":"https://i.imgur.com/HFz47aU.jpg","t":"https://i.imgur.com/HFz47aUl.jpg","k":"","f":false},{"i":345,"n":"","u":"https://i.imgur.com/HgECOh9.jpg","t":"https://i.imgur.com/HgECOh9l.jpg","k":"","f":false},{"i":346,"n":"","u":"https://i.imgur.com/hibmP32.jpg","t":"https://i.imgur.com/hibmP32l.jpg","k":"","f":false},{"i":347,"n":"","u":"https://i.imgur.com/HIEeFaj.jpg","t":"https://i.imgur.com/HIEeFajl.jpg","k":"","f":false},{"i":348,"n":"","u":"https://i.imgur.com/hjk8Sad.jpg","t":"https://i.imgur.com/hjk8Sadl.jpg","k":"","f":false},{"i":349,"n":"","u":"https://i.imgur.com/hK3NwbZ.jpg","t":"https://i.imgur.com/hK3NwbZl.jpg","k":"","f":false},{"i":350,"n":"","u":"https://i.imgur.com/HLBxbwk.jpg","t":"https://i.imgur.com/HLBxbwkl.jpg","k":"","f":false},{"i":351,"n":"","u":"https://i.imgur.com/hLfGUam.png","t":"https://i.imgur.com/hLfGUaml.jpg","k":"","f":true},{"i":352,"n":"","u":"https://i.imgur.com/Hq8EGcs.jpg","t":"https://i.imgur.com/Hq8EGcsl.jpg","k":"","f":false},{"i":353,"n":"","u":"https://i.imgur.com/hqJF21f.jpg","t":"https://i.imgur.com/hqJF21fl.jpg","k":"","f":false},{"i":354,"n":"","u":"https://i.imgur.com/HrVjjhi.jpg","t":"https://i.imgur.com/HrVjjhil.jpg","k":"","f":true},{"i":355,"n":"","u":"https://i.imgur.com/hrwUXAX.jpg","t":"https://i.imgur.com/hrwUXAXl.jpg","k":"","f":true},{"i":356,"n":"","u":"https://i.imgur.com/HsBeBvV.jpg","t":"https://i.imgur.com/HsBeBvVl.jpg","k":"","f":true},{"i":357,"n":"","u":"https://i.imgur.com/hTHDmtp.jpg","t":"https://i.imgur.com/hTHDmtpl.jpg","k":"","f":false},{"i":358,"n":"","u":"https://i.imgur.com/hwrBaos.jpg","t":"https://i.imgur.com/hwrBaosl.jpg","k":"","f":false},{"i":359,"n":"","u":"https://i.imgur.com/HzveoXM.jpg","t":"https://i.imgur.com/HzveoXMl.jpg","k":"","f":false},{"i":360,"n":"","u":"https://i.imgur.com/hzZ5G3t.jpg","t":"https://i.imgur.com/hzZ5G3tl.jpg","k":"","f":false},{"i":361,"n":"","u":"https://i.imgur.com/I2bCvyi.jpg","t":"https://i.imgur.com/I2bCvyil.jpg","k":"","f":true},{"i":362,"n":"","u":"https://i.imgur.com/i48YZpn.jpg","t":"https://i.imgur.com/i48YZpnl.jpg","k":"","f":false},{"i":363,"n":"","u":"https://i.imgur.com/i4KN65N.jpg","t":"https://i.imgur.com/i4KN65Nl.jpg","k":"","f":false},{"i":364,"n":"","u":"https://i.imgur.com/I6rwC49.jpg","t":"https://i.imgur.com/I6rwC49l.jpg","k":"","f":true},{"i":365,"n":"","u":"https://i.imgur.com/I8yfM3Y.jpg","t":"https://i.imgur.com/I8yfM3Yl.jpg","k":"","f":true},{"i":366,"n":"","u":"https://i.imgur.com/IabuoAG.jpg","t":"https://i.imgur.com/IabuoAGl.jpg","k":"","f":false},{"i":367,"n":"","u":"https://i.imgur.com/IakmO2e.jpg","t":"https://i.imgur.com/IakmO2el.jpg","k":"","f":false},{"i":368,"n":"","u":"https://i.imgur.com/iAnwHQk.jpg","t":"https://i.imgur.com/iAnwHQkl.jpg","k":"","f":false},{"i":369,"n":"","u":"https://i.imgur.com/IbIeyCU.jpg","t":"https://i.imgur.com/IbIeyCUl.jpg","k":"","f":false},{"i":370,"n":"","u":"https://i.imgur.com/ICBQ8VA.jpg","t":"https://i.imgur.com/ICBQ8VAl.jpg","k":"","f":false},{"i":371,"n":"","u":"https://i.imgur.com/icReSPc.jpg","t":"https://i.imgur.com/icReSPcl.jpg","k":"","f":false},{"i":372,"n":"","u":"https://i.imgur.com/ID8dgxe.jpg","t":"https://i.imgur.com/ID8dgxel.jpg","k":"","f":false},{"i":373,"n":"","u":"https://i.imgur.com/iDtgmDR.jpg","t":"https://i.imgur.com/iDtgmDRl.jpg","k":"","f":false},{"i":374,"n":"","u":"https://i.imgur.com/Ie7LQNm.png","t":"https://i.imgur.com/Ie7LQNml.jpg","k":"","f":true},{"i":375,"n":"","u":"https://i.imgur.com/iHFvAYr.jpg","t":"https://i.imgur.com/iHFvAYrl.jpg","k":"","f":true},{"i":376,"n":"","u":"https://i.imgur.com/IjONdnd.jpg","t":"https://i.imgur.com/IjONdndl.jpg","k":"","f":false},{"i":377,"n":"","u":"https://i.imgur.com/ijpxbEi.jpg","t":"https://i.imgur.com/ijpxbEil.jpg","k":"","f":false},{"i":378,"n":"","u":"https://i.imgur.com/ikAJeg5.jpg","t":"https://i.imgur.com/ikAJeg5l.jpg","k":"","f":true},{"i":379,"n":"","u":"https://i.imgur.com/IlCOSR3.jpg","t":"https://i.imgur.com/IlCOSR3l.jpg","k":"","f":false},{"i":380,"n":"","u":"https://i.imgur.com/Ip5YB0T.jpg","t":"https://i.imgur.com/Ip5YB0Tl.jpg","k":"","f":false},{"i":381,"n":"","u":"https://i.imgur.com/IPLqbwq.jpg","t":"https://i.imgur.com/IPLqbwql.jpg","k":"","f":false},{"i":382,"n":"","u":"https://i.imgur.com/iqxPNCD.jpg","t":"https://i.imgur.com/iqxPNCDl.jpg","k":"","f":true},{"i":383,"n":"","u":"https://i.imgur.com/iTUmczn.jpg","t":"https://i.imgur.com/iTUmcznl.jpg","k":"","f":true},{"i":384,"n":"","u":"https://i.imgur.com/iuRvJVm.jpg","t":"https://i.imgur.com/iuRvJVml.jpg","k":"","f":true},{"i":385,"n":"","u":"https://i.imgur.com/IvHtDb3.jpg","t":"https://i.imgur.com/IvHtDb3l.jpg","k":"","f":false},{"i":386,"n":"","u":"https://i.imgur.com/IViuFYy.jpg","t":"https://i.imgur.com/IViuFYyl.jpg","k":"","f":false},{"i":387,"n":"","u":"https://i.imgur.com/iyBGhh9.jpg","t":"https://i.imgur.com/iyBGhh9l.jpg","k":"","f":false},{"i":388,"n":"","u":"https://i.imgur.com/IZnvBhP.jpg","t":"https://i.imgur.com/IZnvBhPl.jpg","k":"","f":true},{"i":389,"n":"","u":"https://i.imgur.com/J1e2Ff9.png","t":"https://i.imgur.com/J1e2Ff9l.jpg","k":"","f":true},{"i":390,"n":"","u":"https://i.imgur.com/J7Ex42K.jpg","t":"https://i.imgur.com/J7Ex42Kl.jpg","k":"","f":false},{"i":391,"n":"","u":"https://i.imgur.com/j8yOLda.jpg","t":"https://i.imgur.com/j8yOLdal.jpg","k":"","f":false},{"i":392,"n":"","u":"https://i.imgur.com/jaf9U47.jpg","t":"https://i.imgur.com/jaf9U47l.jpg","k":"","f":false},{"i":393,"n":"","u":"https://i.imgur.com/JBp919K.jpg","t":"https://i.imgur.com/JBp919Kl.jpg","k":"","f":false},{"i":394,"n":"","u":"https://i.imgur.com/jC1aEna.jpg","t":"https://i.imgur.com/jC1aEnal.jpg","k":"","f":false},{"i":395,"n":"","u":"https://i.imgur.com/jc99KUx.jpg","t":"https://i.imgur.com/jc99KUxl.jpg","k":"","f":false},{"i":396,"n":"","u":"https://i.imgur.com/JcwnrkS.jpg","t":"https://i.imgur.com/JcwnrkSl.jpg","k":"","f":false},{"i":397,"n":"","u":"https://i.imgur.com/jekmSfW.jpg","t":"https://i.imgur.com/jekmSfWl.jpg","k":"","f":false},{"i":398,"n":"","u":"https://i.imgur.com/jGmANbb.jpg","t":"https://i.imgur.com/jGmANbbl.jpg","k":"","f":true},{"i":399,"n":"","u":"https://i.imgur.com/jgP1jTF.jpg","t":"https://i.imgur.com/jgP1jTFl.jpg","k":"","f":true},{"i":400,"n":"","u":"https://i.imgur.com/JiLMli7.jpg","t":"https://i.imgur.com/JiLMli7l.jpg","k":"","f":false},{"i":401,"n":"","u":"https://i.imgur.com/JKHijTk.jpg","t":"https://i.imgur.com/JKHijTkl.jpg","k":"","f":false},{"i":402,"n":"","u":"https://i.imgur.com/Jm2W8Xc.jpg","t":"https://i.imgur.com/Jm2W8Xcl.jpg","k":"","f":false},{"i":403,"n":"","u":"https://i.imgur.com/JmREBRh.jpg","t":"https://i.imgur.com/JmREBRhl.jpg","k":"","f":false},{"i":404,"n":"","u":"https://i.imgur.com/JmrNHIG.jpg","t":"https://i.imgur.com/JmrNHIGl.jpg","k":"","f":false},{"i":405,"n":"","u":"https://i.imgur.com/JnBDMBn.jpg","t":"https://i.imgur.com/JnBDMBnl.jpg","k":"","f":false},{"i":406,"n":"","u":"https://i.imgur.com/jNeJc3n.jpg","t":"https://i.imgur.com/jNeJc3nl.jpg","k":"","f":false},{"i":407,"n":"","u":"https://i.imgur.com/Jp93Vx7.jpg","t":"https://i.imgur.com/Jp93Vx7l.jpg","k":"","f":false},{"i":408,"n":"","u":"https://i.imgur.com/JpahnJb.jpg","t":"https://i.imgur.com/JpahnJbl.jpg","k":"","f":false},{"i":409,"n":"","u":"https://i.imgur.com/JpZfsYw.jpg","t":"https://i.imgur.com/JpZfsYwl.jpg","k":"","f":true},{"i":410,"n":"","u":"https://i.imgur.com/JrxBu7k.jpg","t":"https://i.imgur.com/JrxBu7kl.jpg","k":"","f":false},{"i":411,"n":"","u":"https://i.imgur.com/JubHyLJ.jpg","t":"https://i.imgur.com/JubHyLJl.jpg","k":"","f":true},{"i":412,"n":"","u":"https://i.imgur.com/jZVBFEj.jpg","t":"https://i.imgur.com/jZVBFEjl.jpg","k":"","f":false},{"i":413,"n":"","u":"https://i.imgur.com/JZvRjBh.jpg","t":"https://i.imgur.com/JZvRjBhl.jpg","k":"","f":false},{"i":414,"n":"","u":"https://i.imgur.com/k0T89ss.jpg","t":"https://i.imgur.com/k0T89ssl.jpg","k":"","f":false},{"i":415,"n":"","u":"https://i.imgur.com/k2Dz2Xy.jpg","t":"https://i.imgur.com/k2Dz2Xyl.jpg","k":"","f":false},{"i":416,"n":"","u":"https://i.imgur.com/k3s6cJB.jpg","t":"https://i.imgur.com/k3s6cJBl.jpg","k":"","f":false},{"i":417,"n":"","u":"https://i.imgur.com/k5BL8ZT.jpg","t":"https://i.imgur.com/k5BL8ZTl.jpg","k":"","f":false},{"i":418,"n":"","u":"https://i.imgur.com/K6xMqC0.jpg","t":"https://i.imgur.com/K6xMqC0l.jpg","k":"","f":false},{"i":419,"n":"","u":"https://i.imgur.com/kcMSeaD.jpg","t":"https://i.imgur.com/kcMSeaDl.jpg","k":"","f":false},{"i":420,"n":"","u":"https://i.imgur.com/kdmo6Zy.jpg","t":"https://i.imgur.com/kdmo6Zyl.jpg","k":"","f":false},{"i":421,"n":"","u":"https://i.imgur.com/KFtFKnO.jpg","t":"https://i.imgur.com/KFtFKnOl.jpg","k":"","f":false},{"i":422,"n":"","u":"https://i.imgur.com/kJcgn5Q.jpg","t":"https://i.imgur.com/kJcgn5Ql.jpg","k":"","f":false},{"i":423,"n":"","u":"https://i.imgur.com/kjdnOgC.jpg","t":"https://i.imgur.com/kjdnOgCl.jpg","k":"","f":false},{"i":424,"n":"","u":"https://i.imgur.com/kJwQRbF.jpg","t":"https://i.imgur.com/kJwQRbFl.jpg","k":"","f":false},{"i":425,"n":"","u":"https://i.imgur.com/kKFCztr.jpg","t":"https://i.imgur.com/kKFCztrl.jpg","k":"","f":false},{"i":426,"n":"","u":"https://i.imgur.com/KlRzH5y.jpg","t":"https://i.imgur.com/KlRzH5yl.jpg","k":"","f":false},{"i":427,"n":"","u":"https://i.imgur.com/KSFBEgY.jpg","t":"https://i.imgur.com/KSFBEgYl.jpg","k":"","f":false},{"i":428,"n":"","u":"https://i.imgur.com/KsR6ALy.jpg","t":"https://i.imgur.com/KsR6ALyl.jpg","k":"","f":false},{"i":429,"n":"","u":"https://i.imgur.com/kSZ4fED.jpg","t":"https://i.imgur.com/kSZ4fEDl.jpg","k":"","f":false},{"i":430,"n":"","u":"https://i.imgur.com/KTtrRan.jpg","t":"https://i.imgur.com/KTtrRanl.jpg","k":"","f":false},{"i":431,"n":"","u":"https://i.imgur.com/KUhIeI8.jpg","t":"https://i.imgur.com/KUhIeI8l.jpg","k":"","f":false},{"i":432,"n":"","u":"https://i.imgur.com/KVneNfI.jpg","t":"https://i.imgur.com/KVneNfIl.jpg","k":"","f":true},{"i":433,"n":"","u":"https://i.imgur.com/Kw4DlC9.jpg","t":"https://i.imgur.com/Kw4DlC9l.jpg","k":"","f":false},{"i":434,"n":"","u":"https://i.imgur.com/kwhUwal.jpg","t":"https://i.imgur.com/kwhUwall.jpg","k":"","f":true},{"i":435,"n":"","u":"https://i.imgur.com/KzyOKRF.jpg","t":"https://i.imgur.com/KzyOKRFl.jpg","k":"","f":false},{"i":436,"n":"","u":"https://i.imgur.com/l1Jsag0.jpg","t":"https://i.imgur.com/l1Jsag0l.jpg","k":"","f":true},{"i":437,"n":"","u":"https://i.imgur.com/l21jJ0i.jpg","t":"https://i.imgur.com/l21jJ0il.jpg","k":"","f":false},{"i":438,"n":"","u":"https://i.imgur.com/l5pySny.jpg","t":"https://i.imgur.com/l5pySnyl.jpg","k":"","f":true},{"i":439,"n":"","u":"https://i.imgur.com/L5ryu94.jpg","t":"https://i.imgur.com/L5ryu94l.jpg","k":"","f":false},{"i":440,"n":"","u":"https://i.imgur.com/l9IWoQ3.png","t":"https://i.imgur.com/l9IWoQ3l.jpg","k":"","f":false},{"i":441,"n":"","u":"https://i.imgur.com/LcJFagy.jpg","t":"https://i.imgur.com/LcJFagyl.jpg","k":"","f":true},{"i":442,"n":"","u":"https://i.imgur.com/LFDAHsa.jpg","t":"https://i.imgur.com/LFDAHsal.jpg","k":"","f":false},{"i":443,"n":"","u":"https://i.imgur.com/LfRg9QR.png","t":"https://i.imgur.com/LfRg9QRl.jpg","k":"","f":false},{"i":444,"n":"","u":"https://i.imgur.com/lG641md.jpg","t":"https://i.imgur.com/lG641mdl.jpg","k":"","f":false},{"i":445,"n":"","u":"https://i.imgur.com/Lg7g2Ig.jpg","t":"https://i.imgur.com/Lg7g2Igl.jpg","k":"","f":true},{"i":446,"n":"","u":"https://i.imgur.com/lIa5pqw.jpg","t":"https://i.imgur.com/lIa5pqwl.jpg","k":"","f":false},{"i":447,"n":"","u":"https://i.imgur.com/LJpWfLD.jpg","t":"https://i.imgur.com/LJpWfLDl.jpg","k":"","f":true},{"i":448,"n":"","u":"https://i.imgur.com/lk6uoTL.jpg","t":"https://i.imgur.com/lk6uoTLl.jpg","k":"","f":false},{"i":449,"n":"","u":"https://i.imgur.com/LkajbVH.jpg","t":"https://i.imgur.com/LkajbVHl.jpg","k":"","f":false},{"i":450,"n":"","u":"https://i.imgur.com/LKi9ZoP.jpg","t":"https://i.imgur.com/LKi9ZoPl.jpg","k":"","f":false},{"i":451,"n":"","u":"https://i.imgur.com/lNSsgb0.jpg","t":"https://i.imgur.com/lNSsgb0l.jpg","k":"","f":false},{"i":452,"n":"","u":"https://i.imgur.com/LntkBmB.jpg","t":"https://i.imgur.com/LntkBmBl.jpg","k":"","f":false},{"i":453,"n":"","u":"https://i.imgur.com/LnwFk0O.jpg","t":"https://i.imgur.com/LnwFk0Ol.jpg","k":"","f":false},{"i":454,"n":"","u":"https://i.imgur.com/LoNEXfR.jpg","t":"https://i.imgur.com/LoNEXfRl.jpg","k":"","f":false},{"i":455,"n":"","u":"https://i.imgur.com/LoQmV5i.jpg","t":"https://i.imgur.com/LoQmV5il.jpg","k":"","f":false},{"i":456,"n":"","u":"https://i.imgur.com/Lp2rj3k.png","t":"https://i.imgur.com/Lp2rj3kl.jpg","k":"","f":true},{"i":457,"n":"","u":"https://i.imgur.com/lPVE07i.jpg","t":"https://i.imgur.com/lPVE07il.jpg","k":"","f":false},{"i":458,"n":"","u":"https://i.imgur.com/LqH46Io.png","t":"https://i.imgur.com/LqH46Iol.jpg","k":"","f":true},{"i":459,"n":"","u":"https://i.imgur.com/lt9dUuq.jpg","t":"https://i.imgur.com/lt9dUuql.jpg","k":"","f":false},{"i":460,"n":"","u":"https://i.imgur.com/lUCpxHA.jpg","t":"https://i.imgur.com/lUCpxHAl.jpg","k":"","f":false},{"i":461,"n":"","u":"https://i.imgur.com/lV5Pif2.jpg","t":"https://i.imgur.com/lV5Pif2l.jpg","k":"","f":false},{"i":462,"n":"","u":"https://i.imgur.com/LwM3Ycm.jpg","t":"https://i.imgur.com/LwM3Ycml.jpg","k":"","f":false},{"i":463,"n":"","u":"https://i.imgur.com/Ly7ifTG.jpg","t":"https://i.imgur.com/Ly7ifTGl.jpg","k":"","f":true},{"i":464,"n":"","u":"https://i.imgur.com/LyZJdV7.jpg","t":"https://i.imgur.com/LyZJdV7l.jpg","k":"","f":false},{"i":465,"n":"","u":"https://i.imgur.com/m6KkGwa.jpg","t":"https://i.imgur.com/m6KkGwal.jpg","k":"","f":false},{"i":466,"n":"","u":"https://i.imgur.com/MA03u43.jpg","t":"https://i.imgur.com/MA03u43l.jpg","k":"","f":false},{"i":467,"n":"","u":"https://i.imgur.com/mBtfVgl.jpg","t":"https://i.imgur.com/mBtfVgll.jpg","k":"","f":false},{"i":468,"n":"","u":"https://i.imgur.com/mCmuWiv.jpg","t":"https://i.imgur.com/mCmuWivl.jpg","k":"","f":false},{"i":469,"n":"","u":"https://i.imgur.com/mEAGCR4.jpg","t":"https://i.imgur.com/mEAGCR4l.jpg","k":"","f":false},{"i":470,"n":"","u":"https://i.imgur.com/MENnSSj.jpg","t":"https://i.imgur.com/MENnSSjl.jpg","k":"","f":false},{"i":471,"n":"","u":"https://i.imgur.com/MKcvrKP.jpg","t":"https://i.imgur.com/MKcvrKPl.jpg","k":"","f":false},{"i":472,"n":"","u":"https://i.imgur.com/mkGwjsT.jpg","t":"https://i.imgur.com/mkGwjsTl.jpg","k":"","f":true},{"i":473,"n":"","u":"https://i.imgur.com/MMe3umM.jpg","t":"https://i.imgur.com/MMe3umMl.jpg","k":"","f":false},{"i":474,"n":"","u":"https://i.imgur.com/MMqqeGz.jpg","t":"https://i.imgur.com/MMqqeGzl.jpg","k":"","f":true},{"i":475,"n":"","u":"https://i.imgur.com/MOjihXR.jpg","t":"https://i.imgur.com/MOjihXRl.jpg","k":"","f":false},{"i":476,"n":"","u":"https://i.imgur.com/moZwrnY.png","t":"https://i.imgur.com/moZwrnYl.jpg","k":"","f":false},{"i":477,"n":"","u":"https://i.imgur.com/mQFemjb.jpg","t":"https://i.imgur.com/mQFemjbl.jpg","k":"","f":true},{"i":478,"n":"","u":"https://i.imgur.com/mR9zqzZ.jpg","t":"https://i.imgur.com/mR9zqzZl.jpg","k":"","f":false},{"i":479,"n":"","u":"https://i.imgur.com/MRRRkPc.jpg","t":"https://i.imgur.com/MRRRkPcl.jpg","k":"","f":false},{"i":480,"n":"","u":"https://i.imgur.com/mruATMX.jpg","t":"https://i.imgur.com/mruATMXl.jpg","k":"","f":false},{"i":481,"n":"","u":"https://i.imgur.com/MSwwPAM.jpg","t":"https://i.imgur.com/MSwwPAMl.jpg","k":"","f":false},{"i":482,"n":"","u":"https://i.imgur.com/mt4FHSs.jpg","t":"https://i.imgur.com/mt4FHSsl.jpg","k":"","f":false},{"i":483,"n":"","u":"https://i.imgur.com/mtnMNxe.jpg","t":"https://i.imgur.com/mtnMNxel.jpg","k":"","f":true},{"i":484,"n":"","u":"https://i.imgur.com/mz0IVza.jpg","t":"https://i.imgur.com/mz0IVzal.jpg","k":"","f":false},{"i":485,"n":"","u":"https://i.imgur.com/MzBhzXe.jpg","t":"https://i.imgur.com/MzBhzXel.jpg","k":"","f":true},{"i":486,"n":"","u":"https://i.imgur.com/N0g89BB.jpg","t":"https://i.imgur.com/N0g89BBl.jpg","k":"","f":false},{"i":487,"n":"","u":"https://i.imgur.com/n20wnIj.jpg","t":"https://i.imgur.com/n20wnIjl.jpg","k":"","f":false},{"i":488,"n":"","u":"https://i.imgur.com/NajmNSd.jpg","t":"https://i.imgur.com/NajmNSdl.jpg","k":"","f":false},{"i":489,"n":"","u":"https://i.imgur.com/Nb2cHLH.jpg","t":"https://i.imgur.com/Nb2cHLHl.jpg","k":"","f":false},{"i":490,"n":"","u":"https://i.imgur.com/nEHWh8b.jpg","t":"https://i.imgur.com/nEHWh8bl.jpg","k":"","f":false},{"i":491,"n":"","u":"https://i.imgur.com/ngtXSwK.jpg","t":"https://i.imgur.com/ngtXSwKl.jpg","k":"","f":false},{"i":492,"n":"","u":"https://i.imgur.com/Nj9E3u5.jpg","t":"https://i.imgur.com/Nj9E3u5l.jpg","k":"","f":false},{"i":493,"n":"","u":"https://i.imgur.com/nJRnZcU.jpg","t":"https://i.imgur.com/nJRnZcUl.jpg","k":"","f":false},{"i":494,"n":"","u":"https://i.imgur.com/NmdeVxx.jpg","t":"https://i.imgur.com/NmdeVxxl.jpg","k":"","f":false},{"i":495,"n":"","u":"https://i.imgur.com/NnsBPY6.jpg","t":"https://i.imgur.com/NnsBPY6l.jpg","k":"","f":true},{"i":496,"n":"","u":"https://i.imgur.com/NOFBsPs.jpg","t":"https://i.imgur.com/NOFBsPsl.jpg","k":"","f":false},{"i":497,"n":"","u":"https://i.imgur.com/npQUrbN.jpg","t":"https://i.imgur.com/npQUrbNl.jpg","k":"","f":false},{"i":498,"n":"","u":"https://i.imgur.com/NS5oIzl.jpg","t":"https://i.imgur.com/NS5oIzll.jpg","k":"","f":false},{"i":499,"n":"","u":"https://i.imgur.com/Nvbfzn9.jpg","t":"https://i.imgur.com/Nvbfzn9l.jpg","k":"","f":false},{"i":500,"n":"","u":"https://i.imgur.com/nYC2RpS.jpg","t":"https://i.imgur.com/nYC2RpSl.jpg","k":"","f":false},{"i":501,"n":"","u":"https://i.imgur.com/nyeAVXP.jpg","t":"https://i.imgur.com/nyeAVXPl.jpg","k":"","f":false},{"i":502,"n":"","u":"https://i.imgur.com/O0yuk0M.jpg","t":"https://i.imgur.com/O0yuk0Ml.jpg","k":"","f":false},{"i":503,"n":"","u":"https://i.imgur.com/o0ZFVsP.jpg","t":"https://i.imgur.com/o0ZFVsPl.jpg","k":"","f":true},{"i":504,"n":"","u":"https://i.imgur.com/O70ZrK2.jpg","t":"https://i.imgur.com/O70ZrK2l.jpg","k":"","f":false},{"i":505,"n":"","u":"https://i.imgur.com/O91SOjH.jpg","t":"https://i.imgur.com/O91SOjHl.jpg","k":"","f":false},{"i":506,"n":"","u":"https://i.imgur.com/oCBGUtY.jpg","t":"https://i.imgur.com/oCBGUtYl.jpg","k":"","f":false},{"i":507,"n":"","u":"https://i.imgur.com/od2A5Pz.jpg","t":"https://i.imgur.com/od2A5Pzl.jpg","k":"","f":true},{"i":508,"n":"","u":"https://i.imgur.com/ODC0rWR.jpg","t":"https://i.imgur.com/ODC0rWRl.jpg","k":"","f":false},{"i":509,"n":"","u":"https://i.imgur.com/OGunGMG.jpg","t":"https://i.imgur.com/OGunGMGl.jpg","k":"","f":false},{"i":510,"n":"","u":"https://i.imgur.com/oJvFd42.jpg","t":"https://i.imgur.com/oJvFd42l.jpg","k":"","f":true},{"i":511,"n":"","u":"https://i.imgur.com/oKg0cDp.jpg","t":"https://i.imgur.com/oKg0cDpl.jpg","k":"","f":false},{"i":512,"n":"","u":"https://i.imgur.com/OKZWULe.jpg","t":"https://i.imgur.com/OKZWULel.jpg","k":"","f":true},{"i":513,"n":"","u":"https://i.imgur.com/Oo1cqSd.jpg","t":"https://i.imgur.com/Oo1cqSdl.jpg","k":"","f":true},{"i":514,"n":"","u":"https://i.imgur.com/oo8lwJK.jpg","t":"https://i.imgur.com/oo8lwJKl.jpg","k":"","f":false},{"i":515,"n":"","u":"https://i.imgur.com/OPVotam.jpg","t":"https://i.imgur.com/OPVotaml.jpg","k":"","f":false},{"i":516,"n":"","u":"https://i.imgur.com/ora7xol.jpg","t":"https://i.imgur.com/ora7xoll.jpg","k":"","f":true},{"i":517,"n":"","u":"https://i.imgur.com/ORHe36i.jpg","t":"https://i.imgur.com/ORHe36il.jpg","k":"","f":true},{"i":518,"n":"","u":"https://i.imgur.com/OrHElkF.jpg","t":"https://i.imgur.com/OrHElkFl.jpg","k":"","f":false},{"i":519,"n":"","u":"https://i.imgur.com/Os26rtk.jpg","t":"https://i.imgur.com/Os26rtkl.jpg","k":"","f":false},{"i":520,"n":"","u":"https://i.imgur.com/osEOuvE.jpg","t":"https://i.imgur.com/osEOuvEl.jpg","k":"","f":true},{"i":521,"n":"","u":"https://i.imgur.com/OslARyB.jpg","t":"https://i.imgur.com/OslARyBl.jpg","k":"","f":false},{"i":522,"n":"","u":"https://i.imgur.com/OsZ6dvl.jpg","t":"https://i.imgur.com/OsZ6dvll.jpg","k":"","f":false},{"i":523,"n":"","u":"https://i.imgur.com/oUOWyTm.jpg","t":"https://i.imgur.com/oUOWyTml.jpg","k":"","f":false},{"i":524,"n":"","u":"https://i.imgur.com/OURPjaV.jpg","t":"https://i.imgur.com/OURPjaVl.jpg","k":"","f":false},{"i":525,"n":"","u":"https://i.imgur.com/OvIaqjT.jpg","t":"https://i.imgur.com/OvIaqjTl.jpg","k":"","f":false},{"i":526,"n":"","u":"https://i.imgur.com/Ow2tIAh.jpg","t":"https://i.imgur.com/Ow2tIAhl.jpg","k":"","f":false},{"i":527,"n":"","u":"https://i.imgur.com/Ow9US5c.jpg","t":"https://i.imgur.com/Ow9US5cl.jpg","k":"","f":true},{"i":528,"n":"","u":"https://i.imgur.com/OWoma37.jpg","t":"https://i.imgur.com/OWoma37l.jpg","k":"","f":false},{"i":529,"n":"","u":"https://i.imgur.com/P3W9CO9.jpg","t":"https://i.imgur.com/P3W9CO9l.jpg","k":"","f":false},{"i":530,"n":"","u":"https://i.imgur.com/p71kI9g.jpg","t":"https://i.imgur.com/p71kI9gl.jpg","k":"","f":false},{"i":531,"n":"","u":"https://i.imgur.com/pB0Jwkk.jpg","t":"https://i.imgur.com/pB0Jwkkl.jpg","k":"","f":false},{"i":532,"n":"","u":"https://i.imgur.com/PC09Zri.jpg","t":"https://i.imgur.com/PC09Zril.jpg","k":"","f":false},{"i":533,"n":"","u":"https://i.imgur.com/pC2B47u.png","t":"https://i.imgur.com/pC2B47ul.jpg","k":"","f":false},{"i":534,"n":"","u":"https://i.imgur.com/PHUnMNR.jpg","t":"https://i.imgur.com/PHUnMNRl.jpg","k":"","f":false},{"i":535,"n":"","u":"https://i.imgur.com/PmBQXrf.jpg","t":"https://i.imgur.com/PmBQXrfl.jpg","k":"","f":true},{"i":536,"n":"","u":"https://i.imgur.com/PmhR3U4.jpg","t":"https://i.imgur.com/PmhR3U4l.jpg","k":"","f":true},{"i":537,"n":"","u":"https://i.imgur.com/pnVT5Zm.jpg","t":"https://i.imgur.com/pnVT5Zml.jpg","k":"","f":false},{"i":538,"n":"","u":"https://i.imgur.com/POh5Fz5.png","t":"https://i.imgur.com/POh5Fz5l.jpg","k":"","f":false},{"i":539,"n":"","u":"https://i.imgur.com/PORZ4qF.jpg","t":"https://i.imgur.com/PORZ4qFl.jpg","k":"","f":false},{"i":540,"n":"","u":"https://i.imgur.com/ppjQDCn.jpg","t":"https://i.imgur.com/ppjQDCnl.jpg","k":"","f":false},{"i":541,"n":"","u":"https://i.imgur.com/PpS4IOH.jpg","t":"https://i.imgur.com/PpS4IOHl.jpg","k":"","f":false},{"i":542,"n":"","u":"https://i.imgur.com/pQfw8rf.jpg","t":"https://i.imgur.com/pQfw8rfl.jpg","k":"","f":false},{"i":543,"n":"","u":"https://i.imgur.com/PrLHlbh.png","t":"https://i.imgur.com/PrLHlbhl.jpg","k":"","f":false},{"i":544,"n":"","u":"https://i.imgur.com/PSZSA3y.jpg","t":"https://i.imgur.com/PSZSA3yl.jpg","k":"","f":false},{"i":545,"n":"","u":"https://i.imgur.com/pV58uBu.jpg","t":"https://i.imgur.com/pV58uBul.jpg","k":"","f":false},{"i":546,"n":"","u":"https://i.imgur.com/pVJRbbK.jpg","t":"https://i.imgur.com/pVJRbbKl.jpg","k":"","f":false},{"i":547,"n":"","u":"https://i.imgur.com/PZRNZ3D.jpg","t":"https://i.imgur.com/PZRNZ3Dl.jpg","k":"","f":false},{"i":548,"n":"","u":"https://i.imgur.com/Q1LDVrO.jpg","t":"https://i.imgur.com/Q1LDVrOl.jpg","k":"","f":false},{"i":549,"n":"","u":"https://i.imgur.com/q1to15J.png","t":"https://i.imgur.com/q1to15Jl.jpg","k":"","f":false},{"i":550,"n":"","u":"https://i.imgur.com/q6oan7a.jpg","t":"https://i.imgur.com/q6oan7al.jpg","k":"","f":false},{"i":551,"n":"","u":"https://i.imgur.com/q9Ed9uG.jpg","t":"https://i.imgur.com/q9Ed9uGl.jpg","k":"","f":true},{"i":552,"n":"","u":"https://i.imgur.com/qaUTjlN.jpg","t":"https://i.imgur.com/qaUTjlNl.jpg","k":"","f":false},{"i":553,"n":"","u":"https://i.imgur.com/QBxCuVa.jpg","t":"https://i.imgur.com/QBxCuVal.jpg","k":"","f":false},{"i":554,"n":"","u":"https://i.imgur.com/QcVKmzU.jpg","t":"https://i.imgur.com/QcVKmzUl.jpg","k":"","f":false},{"i":555,"n":"","u":"https://i.imgur.com/QDwkhsq.jpg","t":"https://i.imgur.com/QDwkhsql.jpg","k":"","f":false},{"i":556,"n":"","u":"https://i.imgur.com/qfaIurt.jpg","t":"https://i.imgur.com/qfaIurtl.jpg","k":"","f":false},{"i":557,"n":"","u":"https://i.imgur.com/QfHtxUG.jpg","t":"https://i.imgur.com/QfHtxUGl.jpg","k":"","f":true},{"i":558,"n":"","u":"https://i.imgur.com/Qg49pbG.jpg","t":"https://i.imgur.com/Qg49pbGl.jpg","k":"","f":false},{"i":559,"n":"","u":"https://i.imgur.com/qhzcOOp.jpg","t":"https://i.imgur.com/qhzcOOpl.jpg","k":"","f":false},{"i":560,"n":"","u":"https://i.imgur.com/qi6rtdQ.jpg","t":"https://i.imgur.com/qi6rtdQl.jpg","k":"","f":false},{"i":561,"n":"","u":"https://i.imgur.com/qK2axWI.jpg","t":"https://i.imgur.com/qK2axWIl.jpg","k":"","f":false},{"i":562,"n":"","u":"https://i.imgur.com/QmZYIGQ.jpg","t":"https://i.imgur.com/QmZYIGQl.jpg","k":"","f":false},{"i":563,"n":"","u":"https://i.imgur.com/QNXQgWK.jpg","t":"https://i.imgur.com/QNXQgWKl.jpg","k":"","f":false},{"i":564,"n":"","u":"https://i.imgur.com/qppt8yM.jpg","t":"https://i.imgur.com/qppt8yMl.jpg","k":"","f":false},{"i":565,"n":"","u":"https://i.imgur.com/qrdhBS4.png","t":"https://i.imgur.com/qrdhBS4l.jpg","k":"","f":true},{"i":566,"n":"","u":"https://i.imgur.com/QRSwUjJ.jpg","t":"https://i.imgur.com/QRSwUjJl.jpg","k":"","f":false},{"i":567,"n":"","u":"https://i.imgur.com/qSDdjGj.jpg","t":"https://i.imgur.com/qSDdjGjl.jpg","k":"","f":true},{"i":568,"n":"","u":"https://i.imgur.com/QTD1RL8.jpg","t":"https://i.imgur.com/QTD1RL8l.jpg","k":"","f":false},{"i":569,"n":"","u":"https://i.imgur.com/QUlEqNv.jpg","t":"https://i.imgur.com/QUlEqNvl.jpg","k":"","f":false},{"i":570,"n":"","u":"https://i.imgur.com/QUZHDdY.jpg","t":"https://i.imgur.com/QUZHDdYl.jpg","k":"","f":false},{"i":571,"n":"","u":"https://i.imgur.com/QWaotQU.jpg","t":"https://i.imgur.com/QWaotQUl.jpg","k":"","f":true},{"i":572,"n":"","u":"https://i.imgur.com/r2tKmMu.jpg","t":"https://i.imgur.com/r2tKmMul.jpg","k":"","f":false},{"i":573,"n":"","u":"https://i.imgur.com/r2vYrgb.jpg","t":"https://i.imgur.com/r2vYrgbl.jpg","k":"","f":false},{"i":574,"n":"","u":"https://i.imgur.com/r4AZfLb.jpg","t":"https://i.imgur.com/r4AZfLbl.jpg","k":"","f":false},{"i":575,"n":"","u":"https://i.imgur.com/r86fylK.jpg","t":"https://i.imgur.com/r86fylKl.jpg","k":"","f":false},{"i":576,"n":"","u":"https://i.imgur.com/r8K7Pza.jpg","t":"https://i.imgur.com/r8K7Pzal.jpg","k":"","f":false},{"i":577,"n":"","u":"https://i.imgur.com/rEYRmLl.jpg","t":"https://i.imgur.com/rEYRmLll.jpg","k":"","f":false},{"i":578,"n":"","u":"https://i.imgur.com/RfH04Zh.jpg","t":"https://i.imgur.com/RfH04Zhl.jpg","k":"","f":false},{"i":579,"n":"","u":"https://i.imgur.com/rFVCOKY.jpg","t":"https://i.imgur.com/rFVCOKYl.jpg","k":"","f":false},{"i":580,"n":"","u":"https://i.imgur.com/RgnC5Tt.jpg","t":"https://i.imgur.com/RgnC5Ttl.jpg","k":"","f":false},{"i":581,"n":"","u":"https://i.imgur.com/RHq0ekz.jpg","t":"https://i.imgur.com/RHq0ekzl.jpg","k":"","f":false},{"i":582,"n":"","u":"https://i.imgur.com/rkOjszT.jpg","t":"https://i.imgur.com/rkOjszTl.jpg","k":"","f":false},{"i":583,"n":"","u":"https://i.imgur.com/rQw2TDl.jpg","t":"https://i.imgur.com/rQw2TDll.jpg","k":"","f":false},{"i":584,"n":"","u":"https://i.imgur.com/RvwqxFQ.jpg","t":"https://i.imgur.com/RvwqxFQl.jpg","k":"","f":true},{"i":585,"n":"","u":"https://i.imgur.com/rvXeN7W.jpg","t":"https://i.imgur.com/rvXeN7Wl.jpg","k":"","f":false},{"i":586,"n":"","u":"https://i.imgur.com/RwJJQVw.jpg","t":"https://i.imgur.com/RwJJQVwl.jpg","k":"","f":true},{"i":587,"n":"","u":"https://i.imgur.com/rxXUA9v.jpg","t":"https://i.imgur.com/rxXUA9vl.jpg","k":"","f":false},{"i":588,"n":"","u":"https://i.imgur.com/S5JyWVz.jpg","t":"https://i.imgur.com/S5JyWVzl.jpg","k":"","f":false},{"i":589,"n":"","u":"https://i.imgur.com/s67z0KI.jpg","t":"https://i.imgur.com/s67z0KIl.jpg","k":"","f":true},{"i":590,"n":"","u":"https://i.imgur.com/s8OeVRz.jpg","t":"https://i.imgur.com/s8OeVRzl.jpg","k":"","f":false},{"i":591,"n":"","u":"https://i.imgur.com/s9OFp30.jpg","t":"https://i.imgur.com/s9OFp30l.jpg","k":"","f":false},{"i":592,"n":"","u":"https://i.imgur.com/san7WrG.jpg","t":"https://i.imgur.com/san7WrGl.jpg","k":"","f":true},{"i":593,"n":"","u":"https://i.imgur.com/SaTPHJu.jpg","t":"https://i.imgur.com/SaTPHJul.jpg","k":"","f":true},{"i":594,"n":"","u":"https://i.imgur.com/SBEIBuf.jpg","t":"https://i.imgur.com/SBEIBufl.jpg","k":"","f":false},{"i":595,"n":"","u":"https://i.imgur.com/sDA0Hrm.jpg","t":"https://i.imgur.com/sDA0Hrml.jpg","k":"","f":false},{"i":596,"n":"","u":"https://i.imgur.com/sdnnBAa.jpg","t":"https://i.imgur.com/sdnnBAal.jpg","k":"","f":true},{"i":597,"n":"","u":"https://i.imgur.com/Se06ZuC.jpg","t":"https://i.imgur.com/Se06ZuCl.jpg","k":"","f":false},{"i":598,"n":"","u":"https://i.imgur.com/SF0j99b.jpg","t":"https://i.imgur.com/SF0j99bl.jpg","k":"","f":false},{"i":599,"n":"","u":"https://i.imgur.com/SflaBCf.jpg","t":"https://i.imgur.com/SflaBCfl.jpg","k":"","f":false},{"i":600,"n":"","u":"https://i.imgur.com/SHVNOzd.png","t":"https://i.imgur.com/SHVNOzdl.jpg","k":"","f":false},{"i":601,"n":"","u":"https://i.imgur.com/sIX2jRN.jpg","t":"https://i.imgur.com/sIX2jRNl.jpg","k":"","f":false},{"i":602,"n":"","u":"https://i.imgur.com/sJIDxA0.jpg","t":"https://i.imgur.com/sJIDxA0l.jpg","k":"","f":true},{"i":603,"n":"","u":"https://i.imgur.com/sKLJ6HA.jpg","t":"https://i.imgur.com/sKLJ6HAl.jpg","k":"","f":false},{"i":604,"n":"","u":"https://i.imgur.com/snFlYJk.jpg","t":"https://i.imgur.com/snFlYJkl.jpg","k":"","f":false},{"i":605,"n":"","u":"https://i.imgur.com/SNLsugI.jpg","t":"https://i.imgur.com/SNLsugIl.jpg","k":"","f":false},{"i":606,"n":"","u":"https://i.imgur.com/snqxn0h.jpg","t":"https://i.imgur.com/snqxn0hl.jpg","k":"","f":false},{"i":607,"n":"","u":"https://i.imgur.com/SoGdWxq.jpg","t":"https://i.imgur.com/SoGdWxql.jpg","k":"","f":false},{"i":608,"n":"","u":"https://i.imgur.com/SQzW4d6.jpg","t":"https://i.imgur.com/SQzW4d6l.jpg","k":"","f":false},{"i":609,"n":"","u":"https://i.imgur.com/SSkEVOa.jpg","t":"https://i.imgur.com/SSkEVOal.jpg","k":"","f":false},{"i":610,"n":"","u":"https://i.imgur.com/ssNI04h.jpg","t":"https://i.imgur.com/ssNI04hl.jpg","k":"","f":false},{"i":611,"n":"","u":"https://i.imgur.com/ST7W3xy.jpg","t":"https://i.imgur.com/ST7W3xyl.jpg","k":"","f":false},{"i":612,"n":"","u":"https://i.imgur.com/STF1QFZ.jpg","t":"https://i.imgur.com/STF1QFZl.jpg","k":"","f":false},{"i":613,"n":"","u":"https://i.imgur.com/StJ6b54.jpg","t":"https://i.imgur.com/StJ6b54l.jpg","k":"","f":false},{"i":614,"n":"","u":"https://i.imgur.com/SUmY3Fi.png","t":"https://i.imgur.com/SUmY3Fil.jpg","k":"","f":false},{"i":615,"n":"","u":"https://i.imgur.com/Sv2aCTU.jpg","t":"https://i.imgur.com/Sv2aCTUl.jpg","k":"","f":false},{"i":616,"n":"","u":"https://i.imgur.com/Sv3iKWV.jpg","t":"https://i.imgur.com/Sv3iKWVl.jpg","k":"","f":false},{"i":617,"n":"","u":"https://i.imgur.com/swLIJEi.jpg","t":"https://i.imgur.com/swLIJEil.jpg","k":"","f":false},{"i":618,"n":"","u":"https://i.imgur.com/Sy4sN5C.jpg","t":"https://i.imgur.com/Sy4sN5Cl.jpg","k":"","f":false},{"i":619,"n":"","u":"https://i.imgur.com/Sy6qvjY.jpg","t":"https://i.imgur.com/Sy6qvjYl.jpg","k":"","f":false},{"i":620,"n":"","u":"https://i.imgur.com/SYDHorI.jpg","t":"https://i.imgur.com/SYDHorIl.jpg","k":"","f":false},{"i":621,"n":"","u":"https://i.imgur.com/sYiG8u2.jpg","t":"https://i.imgur.com/sYiG8u2l.jpg","k":"","f":false},{"i":622,"n":"","u":"https://i.imgur.com/SZlKjum.jpg","t":"https://i.imgur.com/SZlKjuml.jpg","k":"","f":false},{"i":623,"n":"","u":"https://i.imgur.com/T1Xr8e7.jpg","t":"https://i.imgur.com/T1Xr8e7l.jpg","k":"","f":false},{"i":624,"n":"","u":"https://i.imgur.com/t6Y7hn5.jpg","t":"https://i.imgur.com/t6Y7hn5l.jpg","k":"","f":true},{"i":625,"n":"","u":"https://i.imgur.com/Tc9bZ1K.jpg","t":"https://i.imgur.com/Tc9bZ1Kl.jpg","k":"","f":false},{"i":626,"n":"","u":"https://i.imgur.com/TEPzKdk.jpg","t":"https://i.imgur.com/TEPzKdkl.jpg","k":"","f":true},{"i":627,"n":"","u":"https://i.imgur.com/TFwVnuV.jpg","t":"https://i.imgur.com/TFwVnuVl.jpg","k":"","f":false},{"i":628,"n":"","u":"https://i.imgur.com/tHBY9Bi.jpg","t":"https://i.imgur.com/tHBY9Bil.jpg","k":"","f":false},{"i":629,"n":"","u":"https://i.imgur.com/TMpcXjS.jpg","t":"https://i.imgur.com/TMpcXjSl.jpg","k":"","f":false},{"i":630,"n":"","u":"https://i.imgur.com/tQgn7gM.jpg","t":"https://i.imgur.com/tQgn7gMl.jpg","k":"","f":false},{"i":631,"n":"","u":"https://i.imgur.com/trxPJvo.jpg","t":"https://i.imgur.com/trxPJvol.jpg","k":"","f":true},{"i":632,"n":"","u":"https://i.imgur.com/TSIEMmF.jpg","t":"https://i.imgur.com/TSIEMmFl.jpg","k":"","f":false},{"i":633,"n":"","u":"https://i.imgur.com/TUS9ggR.png","t":"https://i.imgur.com/TUS9ggRl.jpg","k":"","f":false},{"i":634,"n":"","u":"https://i.imgur.com/TvIji0h.jpg","t":"https://i.imgur.com/TvIji0hl.jpg","k":"","f":false},{"i":635,"n":"","u":"https://i.imgur.com/tvKx1vJ.jpg","t":"https://i.imgur.com/tvKx1vJl.jpg","k":"","f":true},{"i":636,"n":"","u":"https://i.imgur.com/U0yLggm.jpg","t":"https://i.imgur.com/U0yLggml.jpg","k":"","f":false},{"i":637,"n":"","u":"https://i.imgur.com/u1z0J35.jpg","t":"https://i.imgur.com/u1z0J35l.jpg","k":"","f":false},{"i":638,"n":"","u":"https://i.imgur.com/u4jG4Hs.jpg","t":"https://i.imgur.com/u4jG4Hsl.jpg","k":"","f":false},{"i":639,"n":"","u":"https://i.imgur.com/u4YzOxR.jpg","t":"https://i.imgur.com/u4YzOxRl.jpg","k":"","f":false},{"i":640,"n":"","u":"https://i.imgur.com/U5ZUE5G.jpg","t":"https://i.imgur.com/U5ZUE5Gl.jpg","k":"","f":false},{"i":641,"n":"","u":"https://i.imgur.com/u8Ap3yG.jpg","t":"https://i.imgur.com/u8Ap3yGl.jpg","k":"","f":false},{"i":642,"n":"","u":"https://i.imgur.com/UAtvU1S.png","t":"https://i.imgur.com/UAtvU1Sl.jpg","k":"","f":false},{"i":643,"n":"","u":"https://i.imgur.com/ub1zDqB.jpg","t":"https://i.imgur.com/ub1zDqBl.jpg","k":"","f":false},{"i":644,"n":"","u":"https://i.imgur.com/ubzwqg3.png","t":"https://i.imgur.com/ubzwqg3l.jpg","k":"","f":false},{"i":645,"n":"","u":"https://i.imgur.com/uDH1VmX.jpg","t":"https://i.imgur.com/uDH1VmXl.jpg","k":"","f":false},{"i":646,"n":"","u":"https://i.imgur.com/uexCUoy.jpg","t":"https://i.imgur.com/uexCUoyl.jpg","k":"","f":false},{"i":647,"n":"","u":"https://i.imgur.com/uf7td1a.jpg","t":"https://i.imgur.com/uf7td1al.jpg","k":"","f":false},{"i":648,"n":"","u":"https://i.imgur.com/uGM7z81.jpg","t":"https://i.imgur.com/uGM7z81l.jpg","k":"","f":false},{"i":649,"n":"","u":"https://i.imgur.com/ugPuyQX.jpg","t":"https://i.imgur.com/ugPuyQXl.jpg","k":"","f":false},{"i":650,"n":"","u":"https://i.imgur.com/ujh8O5j.jpg","t":"https://i.imgur.com/ujh8O5jl.jpg","k":"","f":false},{"i":651,"n":"","u":"https://i.imgur.com/UleeRik.jpg","t":"https://i.imgur.com/UleeRikl.jpg","k":"","f":false},{"i":652,"n":"","u":"https://i.imgur.com/ulpZ9yQ.jpg","t":"https://i.imgur.com/ulpZ9yQl.jpg","k":"","f":false},{"i":653,"n":"","u":"https://i.imgur.com/ulqCiA8.jpg","t":"https://i.imgur.com/ulqCiA8l.jpg","k":"","f":false},{"i":654,"n":"","u":"https://i.imgur.com/Um7RBYU.png","t":"https://i.imgur.com/Um7RBYUl.jpg","k":"","f":true},{"i":655,"n":"","u":"https://i.imgur.com/uMyumCR.jpg","t":"https://i.imgur.com/uMyumCRl.jpg","k":"","f":false},{"i":656,"n":"","u":"https://i.imgur.com/UndycM7.png","t":"https://i.imgur.com/UndycM7l.jpg","k":"","f":false},{"i":657,"n":"","u":"https://i.imgur.com/uQi25CU.jpg","t":"https://i.imgur.com/uQi25CUl.jpg","k":"","f":false},{"i":658,"n":"","u":"https://i.imgur.com/UqogtkD.jpg","t":"https://i.imgur.com/UqogtkDl.jpg","k":"","f":true},{"i":659,"n":"","u":"https://i.imgur.com/uRTsy2b.jpg","t":"https://i.imgur.com/uRTsy2bl.jpg","k":"","f":true},{"i":660,"n":"","u":"https://i.imgur.com/UrxgaOJ.jpg","t":"https://i.imgur.com/UrxgaOJl.jpg","k":"","f":false},{"i":661,"n":"","u":"https://i.imgur.com/URXtJv2.png","t":"https://i.imgur.com/URXtJv2l.jpg","k":"","f":false},{"i":662,"n":"","u":"https://i.imgur.com/UsmlIm1.jpg","t":"https://i.imgur.com/UsmlIm1l.jpg","k":"","f":false},{"i":663,"n":"","u":"https://i.imgur.com/uUdnGsO.jpg","t":"https://i.imgur.com/uUdnGsOl.jpg","k":"","f":false},{"i":664,"n":"","u":"https://i.imgur.com/uV7zx1N.jpg","t":"https://i.imgur.com/uV7zx1Nl.jpg","k":"","f":false},{"i":665,"n":"","u":"https://i.imgur.com/UyGPHhz.jpg","t":"https://i.imgur.com/UyGPHhzl.jpg","k":"","f":false},{"i":666,"n":"","u":"https://i.imgur.com/uyUqrsX.png","t":"https://i.imgur.com/uyUqrsXl.jpg","k":"","f":false},{"i":667,"n":"","u":"https://i.imgur.com/V0LUX2J.jpg","t":"https://i.imgur.com/V0LUX2Jl.jpg","k":"","f":false},{"i":668,"n":"","u":"https://i.imgur.com/V2H8AmY.jpg","t":"https://i.imgur.com/V2H8AmYl.jpg","k":"","f":false},{"i":669,"n":"","u":"https://i.imgur.com/v3drmtb.jpg","t":"https://i.imgur.com/v3drmtbl.jpg","k":"","f":false},{"i":670,"n":"","u":"https://i.imgur.com/v3qfy3q.jpg","t":"https://i.imgur.com/v3qfy3ql.jpg","k":"","f":false},{"i":671,"n":"","u":"https://i.imgur.com/V6etkUW.jpg","t":"https://i.imgur.com/V6etkUWl.jpg","k":"","f":true},{"i":672,"n":"","u":"https://i.imgur.com/VAe3CCl.jpg","t":"https://i.imgur.com/VAe3CCll.jpg","k":"","f":false},{"i":673,"n":"","u":"https://i.imgur.com/VbDT6k2.jpg","t":"https://i.imgur.com/VbDT6k2l.jpg","k":"","f":false},{"i":674,"n":"","u":"https://i.imgur.com/VbjRs6v.jpg","t":"https://i.imgur.com/VbjRs6vl.jpg","k":"","f":false},{"i":675,"n":"","u":"https://i.imgur.com/VE8kdsD.jpg","t":"https://i.imgur.com/VE8kdsDl.jpg","k":"","f":false},{"i":676,"n":"","u":"https://i.imgur.com/VEfrSrg.jpg","t":"https://i.imgur.com/VEfrSrgl.jpg","k":"","f":true},{"i":677,"n":"","u":"https://i.imgur.com/vepQqm2.jpg","t":"https://i.imgur.com/vepQqm2l.jpg","k":"","f":false},{"i":678,"n":"","u":"https://i.imgur.com/Vf5revr.jpg","t":"https://i.imgur.com/Vf5revrl.jpg","k":"","f":false},{"i":679,"n":"","u":"https://i.imgur.com/vFBo7hS.jpg","t":"https://i.imgur.com/vFBo7hSl.jpg","k":"","f":true},{"i":680,"n":"","u":"https://i.imgur.com/VFjtUTn.jpg","t":"https://i.imgur.com/VFjtUTnl.jpg","k":"","f":false},{"i":681,"n":"","u":"https://i.imgur.com/VhoUG5H.jpg","t":"https://i.imgur.com/VhoUG5Hl.jpg","k":"","f":false},{"i":682,"n":"","u":"https://i.imgur.com/VI1mPoh.jpg","t":"https://i.imgur.com/VI1mPohl.jpg","k":"","f":true},{"i":683,"n":"","u":"https://i.imgur.com/vIewvya.jpg","t":"https://i.imgur.com/vIewvyal.jpg","k":"","f":false},{"i":684,"n":"","u":"https://i.imgur.com/viqckJv.jpg","t":"https://i.imgur.com/viqckJvl.jpg","k":"","f":false},{"i":685,"n":"","u":"https://i.imgur.com/vkUFMLc.jpg","t":"https://i.imgur.com/vkUFMLcl.jpg","k":"","f":false},{"i":686,"n":"","u":"https://i.imgur.com/vLkS7lj.jpg","t":"https://i.imgur.com/vLkS7ljl.jpg","k":"","f":false},{"i":687,"n":"","u":"https://i.imgur.com/Vm0KF3J.jpg","t":"https://i.imgur.com/Vm0KF3Jl.jpg","k":"","f":false},{"i":688,"n":"","u":"https://i.imgur.com/vn7BG3J.jpg","t":"https://i.imgur.com/vn7BG3Jl.jpg","k":"","f":false},{"i":689,"n":"","u":"https://i.imgur.com/VpBmRYx.jpg","t":"https://i.imgur.com/VpBmRYxl.jpg","k":"","f":false},{"i":690,"n":"","u":"https://i.imgur.com/Vs9YOYm.jpg","t":"https://i.imgur.com/Vs9YOYml.jpg","k":"","f":false},{"i":691,"n":"","u":"https://i.imgur.com/VTJkwxT.jpg","t":"https://i.imgur.com/VTJkwxTl.jpg","k":"","f":false},{"i":692,"n":"","u":"https://i.imgur.com/vu62H8y.jpg","t":"https://i.imgur.com/vu62H8yl.jpg","k":"","f":true},{"i":693,"n":"","u":"https://i.imgur.com/vyODlqY.jpg","t":"https://i.imgur.com/vyODlqYl.jpg","k":"","f":false},{"i":694,"n":"","u":"https://i.imgur.com/W11YD1n.jpg","t":"https://i.imgur.com/W11YD1nl.jpg","k":"","f":false},{"i":695,"n":"","u":"https://i.imgur.com/W2aaZOv.jpg","t":"https://i.imgur.com/W2aaZOvl.jpg","k":"","f":false},{"i":696,"n":"","u":"https://i.imgur.com/W7qfx0K.jpg","t":"https://i.imgur.com/W7qfx0Kl.jpg","k":"","f":true},{"i":697,"n":"","u":"https://i.imgur.com/W8eAq8i.jpg","t":"https://i.imgur.com/W8eAq8il.jpg","k":"","f":false},{"i":698,"n":"","u":"https://i.imgur.com/W97kroV.jpg","t":"https://i.imgur.com/W97kroVl.jpg","k":"","f":false},{"i":699,"n":"","u":"https://i.imgur.com/W9eWG3y.jpg","t":"https://i.imgur.com/W9eWG3yl.jpg","k":"","f":false},{"i":700,"n":"","u":"https://i.imgur.com/wBPUXUW.jpg","t":"https://i.imgur.com/wBPUXUWl.jpg","k":"","f":false},{"i":701,"n":"","u":"https://i.imgur.com/WcU30SM.jpg","t":"https://i.imgur.com/WcU30SMl.jpg","k":"","f":true},{"i":702,"n":"","u":"https://i.imgur.com/wD8Cm78.png","t":"https://i.imgur.com/wD8Cm78l.jpg","k":"","f":false},{"i":703,"n":"","u":"https://i.imgur.com/wE2vE93.jpg","t":"https://i.imgur.com/wE2vE93l.jpg","k":"","f":false},{"i":704,"n":"","u":"https://i.imgur.com/WHeNItm.jpg","t":"https://i.imgur.com/WHeNItml.jpg","k":"","f":false},{"i":705,"n":"","u":"https://i.imgur.com/whsWMFc.jpg","t":"https://i.imgur.com/whsWMFcl.jpg","k":"","f":false},{"i":706,"n":"","u":"https://i.imgur.com/wi3OQuI.jpg","t":"https://i.imgur.com/wi3OQuIl.jpg","k":"","f":false},{"i":707,"n":"","u":"https://i.imgur.com/WiBbCF2.png","t":"https://i.imgur.com/WiBbCF2l.jpg","k":"","f":false},{"i":708,"n":"","u":"https://i.imgur.com/WIe5Zq6.jpg","t":"https://i.imgur.com/WIe5Zq6l.jpg","k":"","f":false},{"i":709,"n":"","u":"https://i.imgur.com/wIG72DX.jpg","t":"https://i.imgur.com/wIG72DXl.jpg","k":"","f":false},{"i":710,"n":"","u":"https://i.imgur.com/wKeRoCD.jpg","t":"https://i.imgur.com/wKeRoCDl.jpg","k":"","f":false},{"i":711,"n":"","u":"https://i.imgur.com/wLit8bM.jpg","t":"https://i.imgur.com/wLit8bMl.jpg","k":"","f":false},{"i":712,"n":"","u":"https://i.imgur.com/WM5BeQv.jpg","t":"https://i.imgur.com/WM5BeQvl.jpg","k":"","f":true},{"i":713,"n":"","u":"https://i.imgur.com/WmRf9NB.jpg","t":"https://i.imgur.com/WmRf9NBl.jpg","k":"","f":true},{"i":714,"n":"","u":"https://i.imgur.com/WnMVSuO.jpg","t":"https://i.imgur.com/WnMVSuOl.jpg","k":"","f":true},{"i":715,"n":"","u":"https://i.imgur.com/WP0JJcQ.jpg","t":"https://i.imgur.com/WP0JJcQl.jpg","k":"","f":false},{"i":716,"n":"","u":"https://i.imgur.com/WpRDNkt.jpg","t":"https://i.imgur.com/WpRDNktl.jpg","k":"","f":true},{"i":717,"n":"","u":"https://i.imgur.com/WSqDNFN.jpg","t":"https://i.imgur.com/WSqDNFNl.jpg","k":"","f":false},{"i":718,"n":"","u":"https://i.imgur.com/WXGeR36.jpg","t":"https://i.imgur.com/WXGeR36l.jpg","k":"","f":true},{"i":719,"n":"","u":"https://i.imgur.com/wxWrnrD.jpg","t":"https://i.imgur.com/wxWrnrDl.jpg","k":"","f":false},{"i":720,"n":"","u":"https://i.imgur.com/X1FO22h.jpg","t":"https://i.imgur.com/X1FO22hl.jpg","k":"","f":false},{"i":721,"n":"","u":"https://i.imgur.com/X1ulvDk.jpg","t":"https://i.imgur.com/X1ulvDkl.jpg","k":"","f":true},{"i":722,"n":"","u":"https://i.imgur.com/X56T41c.jpg","t":"https://i.imgur.com/X56T41cl.jpg","k":"","f":false},{"i":723,"n":"","u":"https://i.imgur.com/xBT9hR9.jpg","t":"https://i.imgur.com/xBT9hR9l.jpg","k":"","f":false},{"i":724,"n":"","u":"https://i.imgur.com/XBUFx8Y.jpg","t":"https://i.imgur.com/XBUFx8Yl.jpg","k":"","f":false},{"i":725,"n":"","u":"https://i.imgur.com/XESRZcJ.jpg","t":"https://i.imgur.com/XESRZcJl.jpg","k":"","f":false},{"i":726,"n":"","u":"https://i.imgur.com/xg9WITE.jpg","t":"https://i.imgur.com/xg9WITEl.jpg","k":"","f":false},{"i":727,"n":"","u":"https://i.imgur.com/xgZAoG4.jpg","t":"https://i.imgur.com/xgZAoG4l.jpg","k":"","f":true},{"i":728,"n":"","u":"https://i.imgur.com/xHl8xq9.jpg","t":"https://i.imgur.com/xHl8xq9l.jpg","k":"","f":false},{"i":729,"n":"","u":"https://i.imgur.com/xI7ykBV.jpg","t":"https://i.imgur.com/xI7ykBVl.jpg","k":"","f":true},{"i":730,"n":"","u":"https://i.imgur.com/XiUmRV4.jpg","t":"https://i.imgur.com/XiUmRV4l.jpg","k":"","f":false},{"i":731,"n":"","u":"https://i.imgur.com/xJ39BLz.jpg","t":"https://i.imgur.com/xJ39BLzl.jpg","k":"","f":false},{"i":732,"n":"","u":"https://i.imgur.com/xJb4s39.jpg","t":"https://i.imgur.com/xJb4s39l.jpg","k":"","f":false},{"i":733,"n":"","u":"https://i.imgur.com/xku2mgg.jpg","t":"https://i.imgur.com/xku2mggl.jpg","k":"","f":false},{"i":734,"n":"","u":"https://i.imgur.com/xLrY1fC.png","t":"https://i.imgur.com/xLrY1fCl.jpg","k":"","f":false},{"i":735,"n":"","u":"https://i.imgur.com/Xm0ZKdd.jpg","t":"https://i.imgur.com/Xm0ZKddl.jpg","k":"","f":false},{"i":736,"n":"","u":"https://i.imgur.com/XMRWZsm.jpg","t":"https://i.imgur.com/XMRWZsml.jpg","k":"","f":false},{"i":737,"n":"","u":"https://i.imgur.com/xNE9XvD.jpg","t":"https://i.imgur.com/xNE9XvDl.jpg","k":"","f":false},{"i":738,"n":"","u":"https://i.imgur.com/XQiyTt8.jpg","t":"https://i.imgur.com/XQiyTt8l.jpg","k":"","f":false},{"i":739,"n":"","u":"https://i.imgur.com/xqNkGxD.jpg","t":"https://i.imgur.com/xqNkGxDl.jpg","k":"","f":false},{"i":740,"n":"","u":"https://i.imgur.com/xR2DGZf.jpg","t":"https://i.imgur.com/xR2DGZfl.jpg","k":"","f":true},{"i":741,"n":"","u":"https://i.imgur.com/XrDL1OQ.jpg","t":"https://i.imgur.com/XrDL1OQl.jpg","k":"","f":true},{"i":742,"n":"","u":"https://i.imgur.com/XrE3Bfd.jpg","t":"https://i.imgur.com/XrE3Bfdl.jpg","k":"","f":false},{"i":743,"n":"","u":"https://i.imgur.com/XrjeU0B.jpg","t":"https://i.imgur.com/XrjeU0Bl.jpg","k":"","f":false},{"i":744,"n":"","u":"https://i.imgur.com/XS3hfwA.png","t":"https://i.imgur.com/XS3hfwAl.jpg","k":"","f":false},{"i":745,"n":"","u":"https://i.imgur.com/xSFzU99.jpg","t":"https://i.imgur.com/xSFzU99l.jpg","k":"","f":false},{"i":746,"n":"","u":"https://i.imgur.com/xSU7tnP.jpg","t":"https://i.imgur.com/xSU7tnPl.jpg","k":"","f":false},{"i":747,"n":"","u":"https://i.imgur.com/xtH5ksW.jpg","t":"https://i.imgur.com/xtH5ksWl.jpg","k":"","f":false},{"i":748,"n":"","u":"https://i.imgur.com/XUSzmA5.jpg","t":"https://i.imgur.com/XUSzmA5l.jpg","k":"","f":false},{"i":749,"n":"","u":"https://i.imgur.com/xv5JGgV.jpg","t":"https://i.imgur.com/xv5JGgVl.jpg","k":"","f":false},{"i":750,"n":"","u":"https://i.imgur.com/xVs8aqD.jpg","t":"https://i.imgur.com/xVs8aqDl.jpg","k":"","f":false},{"i":751,"n":"","u":"https://i.imgur.com/xXij6jE.jpg","t":"https://i.imgur.com/xXij6jEl.jpg","k":"","f":false},{"i":752,"n":"","u":"https://i.imgur.com/xZjSs3q.jpg","t":"https://i.imgur.com/xZjSs3ql.jpg","k":"","f":false},{"i":753,"n":"","u":"https://i.imgur.com/y1Gk9Pw.jpg","t":"https://i.imgur.com/y1Gk9Pwl.jpg","k":"","f":false},{"i":754,"n":"","u":"https://i.imgur.com/Y7kdY1J.jpg","t":"https://i.imgur.com/Y7kdY1Jl.jpg","k":"","f":false},{"i":755,"n":"","u":"https://i.imgur.com/y9y3QVw.jpg","t":"https://i.imgur.com/y9y3QVwl.jpg","k":"","f":false},{"i":756,"n":"","u":"https://i.imgur.com/yaiGSTZ.png","t":"https://i.imgur.com/yaiGSTZl.jpg","k":"","f":false},{"i":757,"n":"","u":"https://i.imgur.com/yCskzyj.jpg","t":"https://i.imgur.com/yCskzyjl.jpg","k":"","f":false},{"i":758,"n":"","u":"https://i.imgur.com/YcXz5hI.png","t":"https://i.imgur.com/YcXz5hIl.jpg","k":"","f":false},{"i":759,"n":"","u":"https://i.imgur.com/ydF8yOJ.png","t":"https://i.imgur.com/ydF8yOJl.jpg","k":"","f":true},{"i":760,"n":"","u":"https://i.imgur.com/yDH6E4Z.jpg","t":"https://i.imgur.com/yDH6E4Zl.jpg","k":"","f":false},{"i":761,"n":"","u":"https://i.imgur.com/YdMw3Xz.jpg","t":"https://i.imgur.com/YdMw3Xzl.jpg","k":"","f":false},{"i":762,"n":"","u":"https://i.imgur.com/yDnAeak.jpg","t":"https://i.imgur.com/yDnAeakl.jpg","k":"","f":false},{"i":763,"n":"","u":"https://i.imgur.com/YHXStkE.jpg","t":"https://i.imgur.com/YHXStkEl.jpg","k":"","f":false},{"i":764,"n":"","u":"https://i.imgur.com/yIP7kCm.jpg","t":"https://i.imgur.com/yIP7kCml.jpg","k":"","f":false},{"i":765,"n":"","u":"https://i.imgur.com/yJZPVFP.jpg","t":"https://i.imgur.com/yJZPVFPl.jpg","k":"","f":false},{"i":766,"n":"","u":"https://i.imgur.com/YkjLzXl.jpg","t":"https://i.imgur.com/YkjLzXll.jpg","k":"","f":false},{"i":767,"n":"","u":"https://i.imgur.com/YKNBrIV.jpg","t":"https://i.imgur.com/YKNBrIVl.jpg","k":"","f":true},{"i":768,"n":"","u":"https://i.imgur.com/ymhHSWj.jpg","t":"https://i.imgur.com/ymhHSWjl.jpg","k":"","f":false},{"i":769,"n":"","u":"https://i.imgur.com/YpfmT4F.jpg","t":"https://i.imgur.com/YpfmT4Fl.jpg","k":"","f":false},{"i":770,"n":"","u":"https://i.imgur.com/YRPJkWC.jpg","t":"https://i.imgur.com/YRPJkWCl.jpg","k":"","f":false},{"i":771,"n":"","u":"https://i.imgur.com/YRTNXzk.jpg","t":"https://i.imgur.com/YRTNXzkl.jpg","k":"","f":false},{"i":772,"n":"","u":"https://i.imgur.com/Ys3pe1Y.jpg","t":"https://i.imgur.com/Ys3pe1Yl.jpg","k":"","f":false},{"i":773,"n":"","u":"https://i.imgur.com/Yy8Tn9d.jpg","t":"https://i.imgur.com/Yy8Tn9dl.jpg","k":"","f":false},{"i":774,"n":"","u":"https://i.imgur.com/yyFMB2N.jpg","t":"https://i.imgur.com/yyFMB2Nl.jpg","k":"","f":false},{"i":775,"n":"","u":"https://i.imgur.com/YzkLMl5.jpg","t":"https://i.imgur.com/YzkLMl5l.jpg","k":"","f":false},{"i":776,"n":"","u":"https://i.imgur.com/Z0DB0uy.jpg","t":"https://i.imgur.com/Z0DB0uyl.jpg","k":"","f":false},{"i":777,"n":"","u":"https://i.imgur.com/z3SozJy.jpg","t":"https://i.imgur.com/z3SozJyl.jpg","k":"","f":true},{"i":778,"n":"","u":"https://i.imgur.com/z8m8Zuw.jpg","t":"https://i.imgur.com/z8m8Zuwl.jpg","k":"","f":false},{"i":779,"n":"","u":"https://i.imgur.com/Z90In46.jpg","t":"https://i.imgur.com/Z90In46l.jpg","k":"","f":false},{"i":780,"n":"","u":"https://i.imgur.com/z9gaSZB.png","t":"https://i.imgur.com/z9gaSZBl.jpg","k":"","f":false},{"i":781,"n":"","u":"https://i.imgur.com/ZbBVzs1.png","t":"https://i.imgur.com/ZbBVzs1l.jpg","k":"","f":true},{"i":782,"n":"","u":"https://i.imgur.com/ZbkZubL.jpg","t":"https://i.imgur.com/ZbkZubLl.jpg","k":"","f":false},{"i":783,"n":"","u":"https://i.imgur.com/zbsQXT7.jpg","t":"https://i.imgur.com/zbsQXT7l.jpg","k":"","f":true},{"i":784,"n":"","u":"https://i.imgur.com/ZByUtEl.jpg","t":"https://i.imgur.com/ZByUtEll.jpg","k":"","f":false},{"i":785,"n":"","u":"https://i.imgur.com/ZD0PePG.jpg","t":"https://i.imgur.com/ZD0PePGl.jpg","k":"","f":true},{"i":786,"n":"","u":"https://i.imgur.com/zHCY22R.jpg","t":"https://i.imgur.com/zHCY22Rl.jpg","k":"","f":true},{"i":787,"n":"","u":"https://i.imgur.com/zhMj90v.jpg","t":"https://i.imgur.com/zhMj90vl.jpg","k":"","f":false},{"i":788,"n":"","u":"https://i.imgur.com/zHOkQO2.jpg","t":"https://i.imgur.com/zHOkQO2l.jpg","k":"","f":false},{"i":789,"n":"","u":"https://i.imgur.com/ziL2v7h.jpg","t":"https://i.imgur.com/ziL2v7hl.jpg","k":"","f":false},{"i":790,"n":"","u":"https://i.imgur.com/zj16gID.jpg","t":"https://i.imgur.com/zj16gIDl.jpg","k":"","f":false},{"i":791,"n":"","u":"https://i.imgur.com/ZlifJ1Q.jpg","t":"https://i.imgur.com/ZlifJ1Ql.jpg","k":"","f":true},{"i":792,"n":"","u":"https://i.imgur.com/zLoy9RF.jpg","t":"https://i.imgur.com/zLoy9RFl.jpg","k":"","f":false},{"i":793,"n":"","u":"https://i.imgur.com/ZmsJ22B.jpg","t":"https://i.imgur.com/ZmsJ22Bl.jpg","k":"","f":false},{"i":794,"n":"","u":"https://i.imgur.com/ZNlnY3b.jpg","t":"https://i.imgur.com/ZNlnY3bl.jpg","k":"","f":false},{"i":795,"n":"","u":"https://i.imgur.com/ZrOZc3d.jpg","t":"https://i.imgur.com/ZrOZc3dl.jpg","k":"","f":false},{"i":796,"n":"","u":"https://i.imgur.com/zSu4xAD.jpg","t":"https://i.imgur.com/zSu4xADl.jpg","k":"","f":false},{"i":797,"n":"","u":"https://i.imgur.com/zttSAsD.jpg","t":"https://i.imgur.com/zttSAsDl.jpg","k":"","f":false},{"i":798,"n":"","u":"https://i.imgur.com/zuhIiIH.jpg","t":"https://i.imgur.com/zuhIiIHl.jpg","k":"","f":true},{"i":799,"n":"","u":"https://i.imgur.com/zUMnTX9.jpg","t":"https://i.imgur.com/zUMnTX9l.jpg","k":"","f":false},{"i":800,"n":"","u":"https://i.imgur.com/zWfw1Mo.jpg","t":"https://i.imgur.com/zWfw1Mol.jpg","k":"","f":true},{"i":801,"n":"","u":"https://i.imgur.com/zX9gULq.jpg","t":"https://i.imgur.com/zX9gULql.jpg","k":"","f":false},{"i":802,"n":"","u":"https://i.imgur.com/ZXXeVra.jpg","t":"https://i.imgur.com/ZXXeVral.jpg","k":"","f":false},{"i":803,"n":"","u":"https://i.imgur.com/ZZXp6sd.jpg","t":"https://i.imgur.com/ZZXp6sdl.jpg","k":"","f":false}]}